Workbook

Sheet Graphs
B2: Overall | C2: 1 | D2: 2 | E2: 3 | F2: 4 | G2: 5 | H2: 6 | I2: 7 | T2: Macro F1 Score | W2: SOTA
A3: GPT | B3: =Main!E40 -> 0.95931 | T3: GPT 4.1m | U3: Gemini 2.5 Flash | V3: Gemini 3.1 Pro | W3: Legal BERT
A4: GPT | S4: Zero Shot LLM Fairness | T4: =Main!G52 -> 0.44107 | U4: =Main!G53 -> 0.57518 | V4: =Main!G54 -> 0.63136 | W4: N/A
A5: Gemin | S5: Zero Shot Prompting | T5: =Main!G45 -> 0.53627 | U5: =Main!G50 -> 0.6782 | V5: =Main!G51 -> 0.71753 | W5: N/A
S6: Few Shot Prompting | T6: =Main!G57 -> 0.65973 | U6: =Main!G60 -> 0.7003 | V6: =Main!G61 -> 0.73928 | W6: N/A
A7: Overall Methodology Comparison (Grouped Bar Chart or Summary Table) | S7: Fined Tuned | T7: =Main!G40 -> 0.83037 | U7: =Main!G41 -> 0.80666 | V7: N/A | W7: 0.83
A25: Handling Class Imbalance (Confusion Matrices or Stacked Bar Charts)
A27: Not sure how to
A30: Performance Across Specific Unfair Categories (Radar Chart or Detailed Heatmap)
A32: Check Main Sheet
A35: The Progression of Prompt Engineering (Line Graph)
AA40: 5532 | AB40: =AA40/$AA$43 -> 0.58763544
AA41: 2275 | AB41: =AA41/$AA$43 -> 0.24166136
AA42: 1607 | AB42: =AA42/$AA$43 -> 0.17070321
AA43: =SUM(AA40:AA42) -> 9414 | AB43: =AA43/$AA$43 -> 1

Sheet Main
B1: Name | C1: Tab Name | D1: Category | E1: Precision | F1: Recall | G1: F1 | H1: F1 Micro | I1: Support | J1: TP | K1: FP | L1: FN | M1: TN | N1: Accuracy | O1: invalid_prediction_count | P1: invalid_prediction_rate
E2: B | F2: C | G2: D | H2: E | I2: F | J2: G | K2: H | L2: I | M2: J | N2: K | O2: L | P2: M
B3: GPT4.1m-fine-tunned | C3: GPT4.1m-fine-tunned | D3: All | E3: {=INDIRECT("'"&$C3&"'!"&E$2&MATCH($D3,INDIRECT("'"&$C3&"'!$A:$A"),0))} -> 0.95931 | F3: {=INDIRECT("'"&$C3&"'!"&F$2&MATCH($D3,INDIRECT("'"&$C3&"'!$A:$A"),0))} -> 0.9599 | G3: {=INDIRECT("'"&$C3&"'!"&G$2&MATCH($D3,INDIRECT("'"&$C3&"'!$A:$A"),0))} -> 0.83037 | I3: {=INDIRECT("'"&$C3&"'!"&I$2&MATCH($D3,INDIRECT("'"&$C3&"'!$A:$A"),0))} -> 1607 | N3: {=INDIRECT("'"&$C3&"'!"&N$2&MATCH($D3,INDIRECT("'"&$C3&"'!$A:$A"),0))} -> 0.95644 | O3: {=INDIRECT("'"&$C3&"'!"&O$2&MATCH($D3,INDIRECT("'"&$C3&"'!$A:$A"),0))} -> 0 | P3: {=INDIRECT("'"&$C3&"'!"&P$2&MATCH($D3,INDIRECT("'"&$C3&"'!$A:$A"),0))} -> 0
B4: GPT4.1m-fine-tunned | C4: GPT4.1m-fine-tunned | D4: 0 | E4: {=INDIRECT("'"&$C4&"'!"&E$2&MATCH($D4,INDIRECT("'"&$C4&"'!$A:$A"),0))} -> 0.70455 | F4: {=INDIRECT("'"&$C4&"'!"&F$2&MATCH($D4,INDIRECT("'"&$C4&"'!$A:$A"),0))} -> 0.81579 | G4: {=INDIRECT("'"&$C4&"'!"&G$2&MATCH($D4,INDIRECT("'"&$C4&"'!$A:$A"),0))} -> 0.7561 | I4: {=INDIRECT("'"&$C4&"'!"&I$2&MATCH($D4,INDIRECT("'"&$C4&"'!$A:$A"),0))} -> 38 | J4: {=INDIRECT("'"&$C4&"'!"&J$2&MATCH($D4,INDIRECT("'"&$C4&"'!$A:$A"),0))} -> 31 | K4: {=INDIRECT("'"&$C4&"'!"&K$2&MATCH($D4,INDIRECT("'"&$C4&"'!$A:$A"),0))} -> 13 | L4: {=INDIRECT("'"&$C4&"'!"&L$2&MATCH($D4,INDIRECT("'"&$C4&"'!$A:$A"),0))} -> 7
B5: GPT4.1m-fine-tunned | C5: GPT4.1m-fine-tunned | D5: 1 | E5: {=INDIRECT("'"&$C5&"'!"&E$2&MATCH($D5,INDIRECT("'"&$C5&"'!$A:$A"),0))} -> 0.78378 | F5: {=INDIRECT("'"&$C5&"'!"&F$2&MATCH($D5,INDIRECT("'"&$C5&"'!$A:$A"),0))} -> 0.76316 | G5: {=INDIRECT("'"&$C5&"'!"&G$2&MATCH($D5,INDIRECT("'"&$C5&"'!$A:$A"),0))} -> 0.77333 | I5: {=INDIRECT("'"&$C5&"'!"&I$2&MATCH($D5,INDIRECT("'"&$C5&"'!$A:$A"),0))} -> 38 | J5: {=INDIRECT("'"&$C5&"'!"&J$2&MATCH($D5,INDIRECT("'"&$C5&"'!$A:$A"),0))} -> 29 | K5: {=INDIRECT("'"&$C5&"'!"&K$2&MATCH($D5,INDIRECT("'"&$C5&"'!$A:$A"),0))} -> 8 | L5: {=INDIRECT("'"&$C5&"'!"&L$2&MATCH($D5,INDIRECT("'"&$C5&"'!$A:$A"),0))} -> 9
B6: GPT4.1m-fine-tunned | C6: GPT4.1m-fine-tunned | D6: 2 | E6: {=INDIRECT("'"&$C6&"'!"&E$2&MATCH($D6,INDIRECT("'"&$C6&"'!$A:$A"),0))} -> 0.84375 | F6: {=INDIRECT("'"&$C6&"'!"&F$2&MATCH($D6,INDIRECT("'"&$C6&"'!$A:$A"),0))} -> 0.71053 | G6: {=INDIRECT("'"&$C6&"'!"&G$2&MATCH($D6,INDIRECT("'"&$C6&"'!$A:$A"),0))} -> 0.77143 | I6: {=INDIRECT("'"&$C6&"'!"&I$2&MATCH($D6,INDIRECT("'"&$C6&"'!$A:$A"),0))} -> 38 | J6: {=INDIRECT("'"&$C6&"'!"&J$2&MATCH($D6,INDIRECT("'"&$C6&"'!$A:$A"),0))} -> 27 | K6: {=INDIRECT("'"&$C6&"'!"&K$2&MATCH($D6,INDIRECT("'"&$C6&"'!$A:$A"),0))} -> 5 | L6: {=INDIRECT("'"&$C6&"'!"&L$2&MATCH($D6,INDIRECT("'"&$C6&"'!$A:$A"),0))} -> 11
B7: GPT4.1m-fine-tunned | C7: GPT4.1m-fine-tunned | D7: 3 | E7: {=INDIRECT("'"&$C7&"'!"&E$2&MATCH($D7,INDIRECT("'"&$C7&"'!$A:$A"),0))} -> 0.61905 | F7: {=INDIRECT("'"&$C7&"'!"&F$2&MATCH($D7,INDIRECT("'"&$C7&"'!$A:$A"),0))} -> 1 | G7: {=INDIRECT("'"&$C7&"'!"&G$2&MATCH($D7,INDIRECT("'"&$C7&"'!$A:$A"),0))} -> 0.76471 | I7: {=INDIRECT("'"&$C7&"'!"&I$2&MATCH($D7,INDIRECT("'"&$C7&"'!$A:$A"),0))} -> 13 | J7: {=INDIRECT("'"&$C7&"'!"&J$2&MATCH($D7,INDIRECT("'"&$C7&"'!$A:$A"),0))} -> 13 | K7: {=INDIRECT("'"&$C7&"'!"&K$2&MATCH($D7,INDIRECT("'"&$C7&"'!$A:$A"),0))} -> 8 | L7: {=INDIRECT("'"&$C7&"'!"&L$2&MATCH($D7,INDIRECT("'"&$C7&"'!$A:$A"),0))} -> 0
B8: GPT4.1m-fine-tunned | C8: GPT4.1m-fine-tunned | D8: 4 | E8: {=INDIRECT("'"&$C8&"'!"&E$2&MATCH($D8,INDIRECT("'"&$C8&"'!$A:$A"),0))} -> 0.81818 | F8: {=INDIRECT("'"&$C8&"'!"&F$2&MATCH($D8,INDIRECT("'"&$C8&"'!$A:$A"),0))} -> 0.78261 | G8: {=INDIRECT("'"&$C8&"'!"&G$2&MATCH($D8,INDIRECT("'"&$C8&"'!$A:$A"),0))} -> 0.8 | I8: {=INDIRECT("'"&$C8&"'!"&I$2&MATCH($D8,INDIRECT("'"&$C8&"'!$A:$A"),0))} -> 23 | J8: {=INDIRECT("'"&$C8&"'!"&J$2&MATCH($D8,INDIRECT("'"&$C8&"'!$A:$A"),0))} -> 18 | K8: {=INDIRECT("'"&$C8&"'!"&K$2&MATCH($D8,INDIRECT("'"&$C8&"'!$A:$A"),0))} -> 4 | L8: {=INDIRECT("'"&$C8&"'!"&L$2&MATCH($D8,INDIRECT("'"&$C8&"'!$A:$A"),0))} -> 5
B9: GPT4.1m-fine-tunned | C9: GPT4.1m-fine-tunned | D9: 5 | E9: {=INDIRECT("'"&$C9&"'!"&E$2&MATCH($D9,INDIRECT("'"&$C9&"'!$A:$A"),0))} -> 1 | F9: {=INDIRECT("'"&$C9&"'!"&F$2&MATCH($D9,INDIRECT("'"&$C9&"'!$A:$A"),0))} -> 0.92308 | G9: {=INDIRECT("'"&$C9&"'!"&G$2&MATCH($D9,INDIRECT("'"&$C9&"'!$A:$A"),0))} -> 0.96 | I9: {=INDIRECT("'"&$C9&"'!"&I$2&MATCH($D9,INDIRECT("'"&$C9&"'!$A:$A"),0))} -> 13 | J9: {=INDIRECT("'"&$C9&"'!"&J$2&MATCH($D9,INDIRECT("'"&$C9&"'!$A:$A"),0))} -> 12 | K9: {=INDIRECT("'"&$C9&"'!"&K$2&MATCH($D9,INDIRECT("'"&$C9&"'!$A:$A"),0))} -> 0 | L9: {=INDIRECT("'"&$C9&"'!"&L$2&MATCH($D9,INDIRECT("'"&$C9&"'!$A:$A"),0))} -> 1
B10: GPT4.1m-fine-tunned | C10: GPT4.1m-fine-tunned | D10: 6 | E10: {=INDIRECT("'"&$C10&"'!"&E$2&MATCH($D10,INDIRECT("'"&$C10&"'!$A:$A"),0))} -> 1 | F10: {=INDIRECT("'"&$C10&"'!"&F$2&MATCH($D10,INDIRECT("'"&$C10&"'!$A:$A"),0))} -> 1 | G10: {=INDIRECT("'"&$C10&"'!"&G$2&MATCH($D10,INDIRECT("'"&$C10&"'!$A:$A"),0))} -> 1 | I10: {=INDIRECT("'"&$C10&"'!"&I$2&MATCH($D10,INDIRECT("'"&$C10&"'!$A:$A"),0))} -> 16 | J10: {=INDIRECT("'"&$C10&"'!"&J$2&MATCH($D10,INDIRECT("'"&$C10&"'!$A:$A"),0))} -> 16 | K10: {=INDIRECT("'"&$C10&"'!"&K$2&MATCH($D10,INDIRECT("'"&$C10&"'!$A:$A"),0))} -> 0 | L10: {=INDIRECT("'"&$C10&"'!"&L$2&MATCH($D10,INDIRECT("'"&$C10&"'!$A:$A"),0))} -> 0
B11: GPT4.1m-fine-tunned | C11: GPT4.1m-fine-tunned | D11: 7 | E11: {=INDIRECT("'"&$C11&"'!"&E$2&MATCH($D11,INDIRECT("'"&$C11&"'!$A:$A"),0))} -> 0.54545 | F11: {=INDIRECT("'"&$C11&"'!"&F$2&MATCH($D11,INDIRECT("'"&$C11&"'!$A:$A"),0))} -> 0.85714 | G11: {=INDIRECT("'"&$C11&"'!"&G$2&MATCH($D11,INDIRECT("'"&$C11&"'!$A:$A"),0))} -> 0.66667 | I11: {=INDIRECT("'"&$C11&"'!"&I$2&MATCH($D11,INDIRECT("'"&$C11&"'!$A:$A"),0))} -> 7 | J11: {=INDIRECT("'"&$C11&"'!"&J$2&MATCH($D11,INDIRECT("'"&$C11&"'!$A:$A"),0))} -> 6 | K11: {=INDIRECT("'"&$C11&"'!"&K$2&MATCH($D11,INDIRECT("'"&$C11&"'!$A:$A"),0))} -> 5 | L11: {=INDIRECT("'"&$C11&"'!"&L$2&MATCH($D11,INDIRECT("'"&$C11&"'!$A:$A"),0))} -> 1
B12: GPT4.1m-fine-tunned | C12: GPT4.1m-fine-tunned | D12: 8 | E12: {=INDIRECT("'"&$C12&"'!"&E$2&MATCH($D12,INDIRECT("'"&$C12&"'!$A:$A"),0))} -> 0.98388 | F12: {=INDIRECT("'"&$C12&"'!"&F$2&MATCH($D12,INDIRECT("'"&$C12&"'!$A:$A"),0))} -> 0.9784 | G12: {=INDIRECT("'"&$C12&"'!"&G$2&MATCH($D12,INDIRECT("'"&$C12&"'!$A:$A"),0))} -> 0.98113 | I12: {=INDIRECT("'"&$C12&"'!"&I$2&MATCH($D12,INDIRECT("'"&$C12&"'!$A:$A"),0))} -> 1435 | J12: {=INDIRECT("'"&$C12&"'!"&J$2&MATCH($D12,INDIRECT("'"&$C12&"'!$A:$A"),0))} -> 1404 | K12: {=INDIRECT("'"&$C12&"'!"&K$2&MATCH($D12,INDIRECT("'"&$C12&"'!$A:$A"),0))} -> 23 | L12: {=INDIRECT("'"&$C12&"'!"&L$2&MATCH($D12,INDIRECT("'"&$C12&"'!$A:$A"),0))} -> 31
B13: GPT4.1m-fine-tunned | C13: GPT4.1m-fine-tunned | D13: unfair_binary | E13: {=INDIRECT("'"&$C13&"'!"&E$2&MATCH($D13,INDIRECT("'"&$C13&"'!$A:$A"),0))} -> 0.82778 | F13: {=INDIRECT("'"&$C13&"'!"&F$2&MATCH($D13,INDIRECT("'"&$C13&"'!$A:$A"),0))} -> 0.86628 | G13: {=INDIRECT("'"&$C13&"'!"&G$2&MATCH($D13,INDIRECT("'"&$C13&"'!$A:$A"),0))} -> 0.84659 | J13: {=INDIRECT("'"&$C13&"'!"&J$2&MATCH($D13,INDIRECT("'"&$C13&"'!$A:$A"),0))} -> 149 | K13: {=INDIRECT("'"&$C13&"'!"&K$2&MATCH($D13,INDIRECT("'"&$C13&"'!$A:$A"),0))} -> 31 | L13: {=INDIRECT("'"&$C13&"'!"&L$2&MATCH($D13,INDIRECT("'"&$C13&"'!$A:$A"),0))} -> 23 | M13: {=INDIRECT("'"&$C13&"'!"&M$2&MATCH($D13,INDIRECT("'"&$C13&"'!$A:$A"),0))} -> 1404 | N13: {=INDIRECT("'"&$C13&"'!"&N$2&MATCH($D13,INDIRECT("'"&$C13&"'!$A:$A"),0))} -> 0.9664
B15: Gemini-2.5-flash-fine-tunned | C15: Gemini-2.5-flash-fine-tunned | D15: All | E15: {=INDIRECT("'"&$C15&"'!"&E$2&MATCH($D15,INDIRECT("'"&$C15&"'!$A:$A"),0))} -> 0.94479 | F15: {=INDIRECT("'"&$C15&"'!"&F$2&MATCH($D15,INDIRECT("'"&$C15&"'!$A:$A"),0))} -> 0.95003 | G15: {=INDIRECT("'"&$C15&"'!"&G$2&MATCH($D15,INDIRECT("'"&$C15&"'!$A:$A"),0))} -> 0.80666 | I15: {=INDIRECT("'"&$C15&"'!"&I$2&MATCH($D15,INDIRECT("'"&$C15&"'!$A:$A"),0))} -> 1607 | N15: {=INDIRECT("'"&$C15&"'!"&N$2&MATCH($D15,INDIRECT("'"&$C15&"'!$A:$A"),0))} -> 0.94213 | O15: {=INDIRECT("'"&$C15&"'!"&O$2&MATCH($D15,INDIRECT("'"&$C15&"'!$A:$A"),0))} -> 0 | P15: {=INDIRECT("'"&$C15&"'!"&P$2&MATCH($D15,INDIRECT("'"&$C15&"'!$A:$A"),0))} -> 0
B16: Gemini-2.5-flash-fine-tunned | C16: Gemini-2.5-flash-fine-tunned | D16: 0 | E16: {=INDIRECT("'"&$C16&"'!"&E$2&MATCH($D16,INDIRECT("'"&$C16&"'!$A:$A"),0))} -> 0.625 | F16: {=INDIRECT("'"&$C16&"'!"&F$2&MATCH($D16,INDIRECT("'"&$C16&"'!$A:$A"),0))} -> 0.78947 | G16: {=INDIRECT("'"&$C16&"'!"&G$2&MATCH($D16,INDIRECT("'"&$C16&"'!$A:$A"),0))} -> 0.69767 | I16: {=INDIRECT("'"&$C16&"'!"&I$2&MATCH($D16,INDIRECT("'"&$C16&"'!$A:$A"),0))} -> 38 | J16: {=INDIRECT("'"&$C16&"'!"&J$2&MATCH($D16,INDIRECT("'"&$C16&"'!$A:$A"),0))} -> 30 | K16: {=INDIRECT("'"&$C16&"'!"&K$2&MATCH($D16,INDIRECT("'"&$C16&"'!$A:$A"),0))} -> 18 | L16: {=INDIRECT("'"&$C16&"'!"&L$2&MATCH($D16,INDIRECT("'"&$C16&"'!$A:$A"),0))} -> 8
B17: Gemini-2.5-flash-fine-tunned | C17: Gemini-2.5-flash-fine-tunned | D17: 1 | E17: {=INDIRECT("'"&$C17&"'!"&E$2&MATCH($D17,INDIRECT("'"&$C17&"'!$A:$A"),0))} -> 0.62264 | F17: {=INDIRECT("'"&$C17&"'!"&F$2&MATCH($D17,INDIRECT("'"&$C17&"'!$A:$A"),0))} -> 0.86842 | G17: {=INDIRECT("'"&$C17&"'!"&G$2&MATCH($D17,INDIRECT("'"&$C17&"'!$A:$A"),0))} -> 0.72527 | I17: {=INDIRECT("'"&$C17&"'!"&I$2&MATCH($D17,INDIRECT("'"&$C17&"'!$A:$A"),0))} -> 38 | J17: {=INDIRECT("'"&$C17&"'!"&J$2&MATCH($D17,INDIRECT("'"&$C17&"'!$A:$A"),0))} -> 33 | K17: {=INDIRECT("'"&$C17&"'!"&K$2&MATCH($D17,INDIRECT("'"&$C17&"'!$A:$A"),0))} -> 20 | L17: {=INDIRECT("'"&$C17&"'!"&L$2&MATCH($D17,INDIRECT("'"&$C17&"'!$A:$A"),0))} -> 5
B18: Gemini-2.5-flash-fine-tunned | C18: Gemini-2.5-flash-fine-tunned | D18: 2 | E18: {=INDIRECT("'"&$C18&"'!"&E$2&MATCH($D18,INDIRECT("'"&$C18&"'!$A:$A"),0))} -> 0.64706 | F18: {=INDIRECT("'"&$C18&"'!"&F$2&MATCH($D18,INDIRECT("'"&$C18&"'!$A:$A"),0))} -> 0.86842 | G18: {=INDIRECT("'"&$C18&"'!"&G$2&MATCH($D18,INDIRECT("'"&$C18&"'!$A:$A"),0))} -> 0.74157 | I18: {=INDIRECT("'"&$C18&"'!"&I$2&MATCH($D18,INDIRECT("'"&$C18&"'!$A:$A"),0))} -> 38 | J18: {=INDIRECT("'"&$C18&"'!"&J$2&MATCH($D18,INDIRECT("'"&$C18&"'!$A:$A"),0))} -> 33 | K18: {=INDIRECT("'"&$C18&"'!"&K$2&MATCH($D18,INDIRECT("'"&$C18&"'!$A:$A"),0))} -> 18 | L18: {=INDIRECT("'"&$C18&"'!"&L$2&MATCH($D18,INDIRECT("'"&$C18&"'!$A:$A"),0))} -> 5
B19: Gemini-2.5-flash-fine-tunned | C19: Gemini-2.5-flash-fine-tunned | D19: 3 | E19: {=INDIRECT("'"&$C19&"'!"&E$2&MATCH($D19,INDIRECT("'"&$C19&"'!$A:$A"),0))} -> 0.66667 | F19: {=INDIRECT("'"&$C19&"'!"&F$2&MATCH($D19,INDIRECT("'"&$C19&"'!$A:$A"),0))} -> 0.92308 | G19: {=INDIRECT("'"&$C19&"'!"&G$2&MATCH($D19,INDIRECT("'"&$C19&"'!$A:$A"),0))} -> 0.77419 | I19: {=INDIRECT("'"&$C19&"'!"&I$2&MATCH($D19,INDIRECT("'"&$C19&"'!$A:$A"),0))} -> 13 | J19: {=INDIRECT("'"&$C19&"'!"&J$2&MATCH($D19,INDIRECT("'"&$C19&"'!$A:$A"),0))} -> 12 | K19: {=INDIRECT("'"&$C19&"'!"&K$2&MATCH($D19,INDIRECT("'"&$C19&"'!$A:$A"),0))} -> 6 | L19: {=INDIRECT("'"&$C19&"'!"&L$2&MATCH($D19,INDIRECT("'"&$C19&"'!$A:$A"),0))} -> 1
B20: Gemini-2.5-flash-fine-tunned | C20: Gemini-2.5-flash-fine-tunned | D20: 4 | E20: {=INDIRECT("'"&$C20&"'!"&E$2&MATCH($D20,INDIRECT("'"&$C20&"'!$A:$A"),0))} -> 0.76 | F20: {=INDIRECT("'"&$C20&"'!"&F$2&MATCH($D20,INDIRECT("'"&$C20&"'!$A:$A"),0))} -> 0.82609 | G20: {=INDIRECT("'"&$C20&"'!"&G$2&MATCH($D20,INDIRECT("'"&$C20&"'!$A:$A"),0))} -> 0.79167 | I20: {=INDIRECT("'"&$C20&"'!"&I$2&MATCH($D20,INDIRECT("'"&$C20&"'!$A:$A"),0))} -> 23 | J20: {=INDIRECT("'"&$C20&"'!"&J$2&MATCH($D20,INDIRECT("'"&$C20&"'!$A:$A"),0))} -> 19 | K20: {=INDIRECT("'"&$C20&"'!"&K$2&MATCH($D20,INDIRECT("'"&$C20&"'!$A:$A"),0))} -> 6 | L20: {=INDIRECT("'"&$C20&"'!"&L$2&MATCH($D20,INDIRECT("'"&$C20&"'!$A:$A"),0))} -> 4
B21: Gemini-2.5-flash-fine-tunned | C21: Gemini-2.5-flash-fine-tunned | D21: 5 | E21: {=INDIRECT("'"&$C21&"'!"&E$2&MATCH($D21,INDIRECT("'"&$C21&"'!$A:$A"),0))} -> 0.92308 | F21: {=INDIRECT("'"&$C21&"'!"&F$2&MATCH($D21,INDIRECT("'"&$C21&"'!$A:$A"),0))} -> 0.92308 | G21: {=INDIRECT("'"&$C21&"'!"&G$2&MATCH($D21,INDIRECT("'"&$C21&"'!$A:$A"),0))} -> 0.92308 | I21: {=INDIRECT("'"&$C21&"'!"&I$2&MATCH($D21,INDIRECT("'"&$C21&"'!$A:$A"),0))} -> 13 | J21: {=INDIRECT("'"&$C21&"'!"&J$2&MATCH($D21,INDIRECT("'"&$C21&"'!$A:$A"),0))} -> 12 | K21: {=INDIRECT("'"&$C21&"'!"&K$2&MATCH($D21,INDIRECT("'"&$C21&"'!$A:$A"),0))} -> 1 | L21: {=INDIRECT("'"&$C21&"'!"&L$2&MATCH($D21,INDIRECT("'"&$C21&"'!$A:$A"),0))} -> 1
B22: Gemini-2.5-flash-fine-tunned | C22: Gemini-2.5-flash-fine-tunned | D22: 6 | E22: {=INDIRECT("'"&$C22&"'!"&E$2&MATCH($D22,INDIRECT("'"&$C22&"'!$A:$A"),0))} -> 1 | F22: {=INDIRECT("'"&$C22&"'!"&F$2&MATCH($D22,INDIRECT("'"&$C22&"'!$A:$A"),0))} -> 1 | G22: {=INDIRECT("'"&$C22&"'!"&G$2&MATCH($D22,INDIRECT("'"&$C22&"'!$A:$A"),0))} -> 1 | I22: {=INDIRECT("'"&$C22&"'!"&I$2&MATCH($D22,INDIRECT("'"&$C22&"'!$A:$A"),0))} -> 16 | J22: {=INDIRECT("'"&$C22&"'!"&J$2&MATCH($D22,INDIRECT("'"&$C22&"'!$A:$A"),0))} -> 16 | K22: {=INDIRECT("'"&$C22&"'!"&K$2&MATCH($D22,INDIRECT("'"&$C22&"'!$A:$A"),0))} -> 0 | L22: {=INDIRECT("'"&$C22&"'!"&L$2&MATCH($D22,INDIRECT("'"&$C22&"'!$A:$A"),0))} -> 0
B23: Gemini-2.5-flash-fine-tunned | C23: Gemini-2.5-flash-fine-tunned | D23: 7 | E23: {=INDIRECT("'"&$C23&"'!"&E$2&MATCH($D23,INDIRECT("'"&$C23&"'!$A:$A"),0))} -> 0.5 | F23: {=INDIRECT("'"&$C23&"'!"&F$2&MATCH($D23,INDIRECT("'"&$C23&"'!$A:$A"),0))} -> 0.85714 | G23: {=INDIRECT("'"&$C23&"'!"&G$2&MATCH($D23,INDIRECT("'"&$C23&"'!$A:$A"),0))} -> 0.63158 | I23: {=INDIRECT("'"&$C23&"'!"&I$2&MATCH($D23,INDIRECT("'"&$C23&"'!$A:$A"),0))} -> 7 | J23: {=INDIRECT("'"&$C23&"'!"&J$2&MATCH($D23,INDIRECT("'"&$C23&"'!$A:$A"),0))} -> 6 | K23: {=INDIRECT("'"&$C23&"'!"&K$2&MATCH($D23,INDIRECT("'"&$C23&"'!$A:$A"),0))} -> 6 | L23: {=INDIRECT("'"&$C23&"'!"&L$2&MATCH($D23,INDIRECT("'"&$C23&"'!$A:$A"),0))} -> 1
B24: Gemini-2.5-flash-fine-tunned | C24: Gemini-2.5-flash-fine-tunned | D24: 8 | E24: {=INDIRECT("'"&$C24&"'!"&E$2&MATCH($D24,INDIRECT("'"&$C24&"'!$A:$A"),0))} -> 0.98924 | F24: {=INDIRECT("'"&$C24&"'!"&F$2&MATCH($D24,INDIRECT("'"&$C24&"'!$A:$A"),0))} -> 0.96098 | G24: {=INDIRECT("'"&$C24&"'!"&G$2&MATCH($D24,INDIRECT("'"&$C24&"'!$A:$A"),0))} -> 0.9749 | I24: {=INDIRECT("'"&$C24&"'!"&I$2&MATCH($D24,INDIRECT("'"&$C24&"'!$A:$A"),0))} -> 1435 | J24: {=INDIRECT("'"&$C24&"'!"&J$2&MATCH($D24,INDIRECT("'"&$C24&"'!$A:$A"),0))} -> 1379 | K24: {=INDIRECT("'"&$C24&"'!"&K$2&MATCH($D24,INDIRECT("'"&$C24&"'!$A:$A"),0))} -> 15 | L24: {=INDIRECT("'"&$C24&"'!"&L$2&MATCH($D24,INDIRECT("'"&$C24&"'!$A:$A"),0))} -> 56
B25: Gemini-2.5-flash-fine-tunned | C25: Gemini-2.5-flash-fine-tunned | D25: unfair_binary | E25: {=INDIRECT("'"&$C25&"'!"&E$2&MATCH($D25,INDIRECT("'"&$C25&"'!$A:$A"),0))} -> 0.73709 | F25: {=INDIRECT("'"&$C25&"'!"&F$2&MATCH($D25,INDIRECT("'"&$C25&"'!$A:$A"),0))} -> 0.91279 | G25: {=INDIRECT("'"&$C25&"'!"&G$2&MATCH($D25,INDIRECT("'"&$C25&"'!$A:$A"),0))} -> 0.81558 | J25: {=INDIRECT("'"&$C25&"'!"&J$2&MATCH($D25,INDIRECT("'"&$C25&"'!$A:$A"),0))} -> 157 | K25: {=INDIRECT("'"&$C25&"'!"&K$2&MATCH($D25,INDIRECT("'"&$C25&"'!$A:$A"),0))} -> 56 | L25: {=INDIRECT("'"&$C25&"'!"&L$2&MATCH($D25,INDIRECT("'"&$C25&"'!$A:$A"),0))} -> 15 | M25: {=INDIRECT("'"&$C25&"'!"&M$2&MATCH($D25,INDIRECT("'"&$C25&"'!$A:$A"),0))} -> 1379 | N25: {=INDIRECT("'"&$C25&"'!"&N$2&MATCH($D25,INDIRECT("'"&$C25&"'!$A:$A"),0))} -> 0.95582
B27: Few Shot Gemini 3.1 Pro | C27: FS6-Full-Gemini3.1-pro-25.04.26 | D27: All | E27: {=INDIRECT("'"&$C27&"'!"&E$2&MATCH($D27,INDIRECT("'"&$C27&"'!$A:$A"),0))} -> 0.91983 | F27: {=INDIRECT("'"&$C27&"'!"&F$2&MATCH($D27,INDIRECT("'"&$C27&"'!$A:$A"),0))} -> 0.92721 | G27: {=INDIRECT("'"&$C27&"'!"&G$2&MATCH($D27,INDIRECT("'"&$C27&"'!$A:$A"),0))} -> 0.73928 | I27: {=INDIRECT("'"&$C27&"'!"&I$2&MATCH($D27,INDIRECT("'"&$C27&"'!$A:$A"),0))} -> 1607 | N27: {=INDIRECT("'"&$C27&"'!"&N$2&MATCH($D27,INDIRECT("'"&$C27&"'!$A:$A"),0))} -> 0.9191 | O27: {=INDIRECT("'"&$C27&"'!"&O$2&MATCH($D27,INDIRECT("'"&$C27&"'!$A:$A"),0))} -> 0 | P27: {=INDIRECT("'"&$C27&"'!"&P$2&MATCH($D27,INDIRECT("'"&$C27&"'!$A:$A"),0))} -> 0
B28: Few Shot Gemini 3.1 Pro | C28: FS6-Full-Gemini3.1-pro-25.04.26 | D28: 0 | E28: {=INDIRECT("'"&$C28&"'!"&E$2&MATCH($D28,INDIRECT("'"&$C28&"'!$A:$A"),0))} -> 0.47541 | F28: {=INDIRECT("'"&$C28&"'!"&F$2&MATCH($D28,INDIRECT("'"&$C28&"'!$A:$A"),0))} -> 0.76316 | G28: {=INDIRECT("'"&$C28&"'!"&G$2&MATCH($D28,INDIRECT("'"&$C28&"'!$A:$A"),0))} -> 0.58586 | I28: {=INDIRECT("'"&$C28&"'!"&I$2&MATCH($D28,INDIRECT("'"&$C28&"'!$A:$A"),0))} -> 38 | J28: {=INDIRECT("'"&$C28&"'!"&J$2&MATCH($D28,INDIRECT("'"&$C28&"'!$A:$A"),0))} -> 29 | K28: {=INDIRECT("'"&$C28&"'!"&K$2&MATCH($D28,INDIRECT("'"&$C28&"'!$A:$A"),0))} -> 32 | L28: {=INDIRECT("'"&$C28&"'!"&L$2&MATCH($D28,INDIRECT("'"&$C28&"'!$A:$A"),0))} -> 9 | Q28: Limitation of Liability
B29: Few Shot Gemini 3.1 Pro | C29: FS6-Full-Gemini3.1-pro-25.04.26 | D29: 1 | E29: {=INDIRECT("'"&$C29&"'!"&E$2&MATCH($D29,INDIRECT("'"&$C29&"'!$A:$A"),0))} -> 0.65455 | F29: {=INDIRECT("'"&$C29&"'!"&F$2&MATCH($D29,INDIRECT("'"&$C29&"'!$A:$A"),0))} -> 0.94737 | G29: {=INDIRECT("'"&$C29&"'!"&G$2&MATCH($D29,INDIRECT("'"&$C29&"'!$A:$A"),0))} -> 0.77419 | I29: {=INDIRECT("'"&$C29&"'!"&I$2&MATCH($D29,INDIRECT("'"&$C29&"'!$A:$A"),0))} -> 38 | J29: {=INDIRECT("'"&$C29&"'!"&J$2&MATCH($D29,INDIRECT("'"&$C29&"'!$A:$A"),0))} -> 36 | K29: {=INDIRECT("'"&$C29&"'!"&K$2&MATCH($D29,INDIRECT("'"&$C29&"'!$A:$A"),0))} -> 19 | L29: {=INDIRECT("'"&$C29&"'!"&L$2&MATCH($D29,INDIRECT("'"&$C29&"'!$A:$A"),0))} -> 2 | Q29: Unilateral Termination
B30: Few Shot Gemini 3.1 Pro | C30: FS6-Full-Gemini3.1-pro-25.04.26 | D30: 2 | E30: {=INDIRECT("'"&$C30&"'!"&E$2&MATCH($D30,INDIRECT("'"&$C30&"'!$A:$A"),0))} -> 0.54386 | F30: {=INDIRECT("'"&$C30&"'!"&F$2&MATCH($D30,INDIRECT("'"&$C30&"'!$A:$A"),0))} -> 0.81579 | G30: {=INDIRECT("'"&$C30&"'!"&G$2&MATCH($D30,INDIRECT("'"&$C30&"'!$A:$A"),0))} -> 0.65263 | I30: {=INDIRECT("'"&$C30&"'!"&I$2&MATCH($D30,INDIRECT("'"&$C30&"'!$A:$A"),0))} -> 38 | J30: {=INDIRECT("'"&$C30&"'!"&J$2&MATCH($D30,INDIRECT("'"&$C30&"'!$A:$A"),0))} -> 31 | K30: {=INDIRECT("'"&$C30&"'!"&K$2&MATCH($D30,INDIRECT("'"&$C30&"'!$A:$A"),0))} -> 26 | L30: {=INDIRECT("'"&$C30&"'!"&L$2&MATCH($D30,INDIRECT("'"&$C30&"'!$A:$A"),0))} -> 7 | Q30: Unilateral Change
B31: Few Shot Gemini 3.1 Pro | C31: FS6-Full-Gemini3.1-pro-25.04.26 | D31: 3 | E31: {=INDIRECT("'"&$C31&"'!"&E$2&MATCH($D31,INDIRECT("'"&$C31&"'!$A:$A"),0))} -> 0.54545 | F31: {=INDIRECT("'"&$C31&"'!"&F$2&MATCH($D31,INDIRECT("'"&$C31&"'!$A:$A"),0))} -> 0.92308 | G31: {=INDIRECT("'"&$C31&"'!"&G$2&MATCH($D31,INDIRECT("'"&$C31&"'!$A:$A"),0))} -> 0.68571 | I31: {=INDIRECT("'"&$C31&"'!"&I$2&MATCH($D31,INDIRECT("'"&$C31&"'!$A:$A"),0))} -> 13 | J31: {=INDIRECT("'"&$C31&"'!"&J$2&MATCH($D31,INDIRECT("'"&$C31&"'!$A:$A"),0))} -> 12 | K31: {=INDIRECT("'"&$C31&"'!"&K$2&MATCH($D31,INDIRECT("'"&$C31&"'!$A:$A"),0))} -> 10 | L31: {=INDIRECT("'"&$C31&"'!"&L$2&MATCH($D31,INDIRECT("'"&$C31&"'!$A:$A"),0))} -> 1 | Q31: Content Removal
B32: Few Shot Gemini 3.1 Pro | C32: FS6-Full-Gemini3.1-pro-25.04.26 | D32: 4 | E32: {=INDIRECT("'"&$C32&"'!"&E$2&MATCH($D32,INDIRECT("'"&$C32&"'!$A:$A"),0))} -> 0.61765 | F32: {=INDIRECT("'"&$C32&"'!"&F$2&MATCH($D32,INDIRECT("'"&$C32&"'!$A:$A"),0))} -> 0.91304 | G32: {=INDIRECT("'"&$C32&"'!"&G$2&MATCH($D32,INDIRECT("'"&$C32&"'!$A:$A"),0))} -> 0.73684 | I32: {=INDIRECT("'"&$C32&"'!"&I$2&MATCH($D32,INDIRECT("'"&$C32&"'!$A:$A"),0))} -> 23 | J32: {=INDIRECT("'"&$C32&"'!"&J$2&MATCH($D32,INDIRECT("'"&$C32&"'!$A:$A"),0))} -> 21 | K32: {=INDIRECT("'"&$C32&"'!"&K$2&MATCH($D32,INDIRECT("'"&$C32&"'!$A:$A"),0))} -> 13 | L32: {=INDIRECT("'"&$C32&"'!"&L$2&MATCH($D32,INDIRECT("'"&$C32&"'!$A:$A"),0))} -> 2 | Q32: Contract by Using
B33: Few Shot Gemini 3.1 Pro | C33: FS6-Full-Gemini3.1-pro-25.04.26 | D33: 5 | E33: {=INDIRECT("'"&$C33&"'!"&E$2&MATCH($D33,INDIRECT("'"&$C33&"'!$A:$A"),0))} -> 0.85714 | F33: {=INDIRECT("'"&$C33&"'!"&F$2&MATCH($D33,INDIRECT("'"&$C33&"'!$A:$A"),0))} -> 0.92308 | G33: {=INDIRECT("'"&$C33&"'!"&G$2&MATCH($D33,INDIRECT("'"&$C33&"'!$A:$A"),0))} -> 0.88889 | I33: {=INDIRECT("'"&$C33&"'!"&I$2&MATCH($D33,INDIRECT("'"&$C33&"'!$A:$A"),0))} -> 13 | J33: {=INDIRECT("'"&$C33&"'!"&J$2&MATCH($D33,INDIRECT("'"&$C33&"'!$A:$A"),0))} -> 12 | K33: {=INDIRECT("'"&$C33&"'!"&K$2&MATCH($D33,INDIRECT("'"&$C33&"'!$A:$A"),0))} -> 2 | L33: {=INDIRECT("'"&$C33&"'!"&L$2&MATCH($D33,INDIRECT("'"&$C33&"'!$A:$A"),0))} -> 1 | Q33: Choice of Law
B34: Few Shot Gemini 3.1 Pro | C34: FS6-Full-Gemini3.1-pro-25.04.26 | D34: 6 | E34: {=INDIRECT("'"&$C34&"'!"&E$2&MATCH($D34,INDIRECT("'"&$C34&"'!$A:$A"),0))} -> 0.84211 | F34: {=INDIRECT("'"&$C34&"'!"&F$2&MATCH($D34,INDIRECT("'"&$C34&"'!$A:$A"),0))} -> 1 | G34: {=INDIRECT("'"&$C34&"'!"&G$2&MATCH($D34,INDIRECT("'"&$C34&"'!$A:$A"),0))} -> 0.91429 | I34: {=INDIRECT("'"&$C34&"'!"&I$2&MATCH($D34,INDIRECT("'"&$C34&"'!$A:$A"),0))} -> 16 | J34: {=INDIRECT("'"&$C34&"'!"&J$2&MATCH($D34,INDIRECT("'"&$C34&"'!$A:$A"),0))} -> 16 | K34: {=INDIRECT("'"&$C34&"'!"&K$2&MATCH($D34,INDIRECT("'"&$C34&"'!$A:$A"),0))} -> 3 | L34: {=INDIRECT("'"&$C34&"'!"&L$2&MATCH($D34,INDIRECT("'"&$C34&"'!$A:$A"),0))} -> 0 | Q34: Jurisdiction
B35: Few Shot Gemini 3.1 Pro | C35: FS6-Full-Gemini3.1-pro-25.04.26 | D35: 7 | E35: {=INDIRECT("'"&$C35&"'!"&E$2&MATCH($D35,INDIRECT("'"&$C35&"'!$A:$A"),0))} -> 0.33333 | F35: {=INDIRECT("'"&$C35&"'!"&F$2&MATCH($D35,INDIRECT("'"&$C35&"'!$A:$A"),0))} -> 0.71429 | G35: {=INDIRECT("'"&$C35&"'!"&G$2&MATCH($D35,INDIRECT("'"&$C35&"'!$A:$A"),0))} -> 0.45455 | I35: {=INDIRECT("'"&$C35&"'!"&I$2&MATCH($D35,INDIRECT("'"&$C35&"'!$A:$A"),0))} -> 7 | J35: {=INDIRECT("'"&$C35&"'!"&J$2&MATCH($D35,INDIRECT("'"&$C35&"'!$A:$A"),0))} -> 5 | K35: {=INDIRECT("'"&$C35&"'!"&K$2&MATCH($D35,INDIRECT("'"&$C35&"'!$A:$A"),0))} -> 10 | L35: {=INDIRECT("'"&$C35&"'!"&L$2&MATCH($D35,INDIRECT("'"&$C35&"'!$A:$A"),0))} -> 2 | Q35: Arbitration
B36: Few Shot Gemini 3.1 Pro | C36: FS6-Full-Gemini3.1-pro-25.04.26 | D36: 8 | E36: {=INDIRECT("'"&$C36&"'!"&E$2&MATCH($D36,INDIRECT("'"&$C36&"'!$A:$A"),0))} -> 0.98821 | F36: {=INDIRECT("'"&$C36&"'!"&F$2&MATCH($D36,INDIRECT("'"&$C36&"'!$A:$A"),0))} -> 0.93449 | G36: {=INDIRECT("'"&$C36&"'!"&G$2&MATCH($D36,INDIRECT("'"&$C36&"'!$A:$A"),0))} -> 0.9606 | I36: {=INDIRECT("'"&$C36&"'!"&I$2&MATCH($D36,INDIRECT("'"&$C36&"'!$A:$A"),0))} -> 1435 | J36: {=INDIRECT("'"&$C36&"'!"&J$2&MATCH($D36,INDIRECT("'"&$C36&"'!$A:$A"),0))} -> 1341 | K36: {=INDIRECT("'"&$C36&"'!"&K$2&MATCH($D36,INDIRECT("'"&$C36&"'!$A:$A"),0))} -> 16 | L36: {=INDIRECT("'"&$C36&"'!"&L$2&MATCH($D36,INDIRECT("'"&$C36&"'!$A:$A"),0))} -> 94 | Q36: Fair
B37: Few Shot Gemini 3.1 Pro | C37: FS6-Full-Gemini3.1-pro-25.04.26 | D37: unfair_binary | E37: {=INDIRECT("'"&$C37&"'!"&E$2&MATCH($D37,INDIRECT("'"&$C37&"'!$A:$A"),0))} -> 0.624 | F37: {=INDIRECT("'"&$C37&"'!"&F$2&MATCH($D37,INDIRECT("'"&$C37&"'!$A:$A"),0))} -> 0.90698 | G37: {=INDIRECT("'"&$C37&"'!"&G$2&MATCH($D37,INDIRECT("'"&$C37&"'!$A:$A"),0))} -> 0.73934 | J37: {=INDIRECT("'"&$C37&"'!"&J$2&MATCH($D37,INDIRECT("'"&$C37&"'!$A:$A"),0))} -> 156 | K37: {=INDIRECT("'"&$C37&"'!"&K$2&MATCH($D37,INDIRECT("'"&$C37&"'!$A:$A"),0))} -> 94 | L37: {=INDIRECT("'"&$C37&"'!"&L$2&MATCH($D37,INDIRECT("'"&$C37&"'!$A:$A"),0))} -> 16 | M37: {=INDIRECT("'"&$C37&"'!"&M$2&MATCH($D37,INDIRECT("'"&$C37&"'!$A:$A"),0))} -> 1341 | N37: {=INDIRECT("'"&$C37&"'!"&N$2&MATCH($D37,INDIRECT("'"&$C37&"'!$A:$A"),0))} -> 0.93155
B40: Fine Tunned GPT 4.1m | C40: GPT4.1m-fine-tunned | D40: All | E40: {=INDIRECT("'"&$C40&"'!"&E$2&MATCH($D40,INDIRECT("'"&$C40&"'!$A:$A"),0))} -> 0.95931 | F40: {=INDIRECT("'"&$C40&"'!"&F$2&MATCH($D40,INDIRECT("'"&$C40&"'!$A:$A"),0))} -> 0.9599 | G40: {=INDIRECT("'"&$C40&"'!"&G$2&MATCH($D40,INDIRECT("'"&$C40&"'!$A:$A"),0))} -> 0.83037 | H40: {=INDIRECT("'"&$C40&"'!"&H$2&MATCH($D40,INDIRECT("'"&$C40&"'!$A:$A"),0))} -> 0.95961 | I40: {=INDIRECT("'"&$C40&"'!"&I$2&MATCH($D40,INDIRECT("'"&$C40&"'!$A:$A"),0))} -> 1607 | N40: {=INDIRECT("'"&$C40&"'!"&N$2&MATCH($D40,INDIRECT("'"&$C40&"'!$A:$A"),0))} -> 0.95644 | O40: {=INDIRECT("'"&$C40&"'!"&O$2&MATCH($D40,INDIRECT("'"&$C40&"'!$A:$A"),0))} -> 0 | P40: {=INDIRECT("'"&$C40&"'!"&P$2&MATCH($D40,INDIRECT("'"&$C40&"'!$A:$A"),0))} -> 0
B41: Fine Tunned Gemini-2.5-flash | C41: Gemini-2.5-flash-fine-tunned | D41: All | E41: {=INDIRECT("'"&$C41&"'!"&E$2&MATCH($D41,INDIRECT("'"&$C41&"'!$A:$A"),0))} -> 0.94479 | F41: {=INDIRECT("'"&$C41&"'!"&F$2&MATCH($D41,INDIRECT("'"&$C41&"'!$A:$A"),0))} -> 0.95003 | G41: {=INDIRECT("'"&$C41&"'!"&G$2&MATCH($D41,INDIRECT("'"&$C41&"'!$A:$A"),0))} -> 0.80666 | H41: {=INDIRECT("'"&$C41&"'!"&H$2&MATCH($D41,INDIRECT("'"&$C41&"'!$A:$A"),0))} -> 0.9474 | I41: {=INDIRECT("'"&$C41&"'!"&I$2&MATCH($D41,INDIRECT("'"&$C41&"'!$A:$A"),0))} -> 1607 | N41: {=INDIRECT("'"&$C41&"'!"&N$2&MATCH($D41,INDIRECT("'"&$C41&"'!$A:$A"),0))} -> 0.94213 | O41: {=INDIRECT("'"&$C41&"'!"&O$2&MATCH($D41,INDIRECT("'"&$C41&"'!$A:$A"),0))} -> 0 | P41: {=INDIRECT("'"&$C41&"'!"&P$2&MATCH($D41,INDIRECT("'"&$C41&"'!$A:$A"),0))} -> 0
B42: V1 Zero Shot 4.1m | C42: ZS1-Full-4.1m-21.03.26 | D42: All | E42: {=INDIRECT("'"&$C42&"'!"&E$2&MATCH($D42,INDIRECT("'"&$C42&"'!$A:$A"),0))} -> 0.6477 | F42: {=INDIRECT("'"&$C42&"'!"&F$2&MATCH($D42,INDIRECT("'"&$C42&"'!$A:$A"),0))} -> 0.66009 | G42: {=INDIRECT("'"&$C42&"'!"&G$2&MATCH($D42,INDIRECT("'"&$C42&"'!$A:$A"),0))} -> 0.45805 | H42: {=INDIRECT("'"&$C42&"'!"&H$2&MATCH($D42,INDIRECT("'"&$C42&"'!$A:$A"),0))} -> 0.65383 | I42: {=INDIRECT("'"&$C42&"'!"&I$2&MATCH($D42,INDIRECT("'"&$C42&"'!$A:$A"),0))} -> 1607 | N42: {=INDIRECT("'"&$C42&"'!"&N$2&MATCH($D42,INDIRECT("'"&$C42&"'!$A:$A"),0))} -> 0.64717 | O42: {=INDIRECT("'"&$C42&"'!"&O$2&MATCH($D42,INDIRECT("'"&$C42&"'!$A:$A"),0))} -> 0 | P42: {=INDIRECT("'"&$C42&"'!"&P$2&MATCH($D42,INDIRECT("'"&$C42&"'!$A:$A"),0))} -> 0
B43: V2 Zero Shot 4.1m | C43: ZS2-Full-4.1m-07.04.26 | D43: All | E43: {=INDIRECT("'"&$C43&"'!"&E$2&MATCH($D43,INDIRECT("'"&$C43&"'!$A:$A"),0))} -> 0.63702 | F43: {=INDIRECT("'"&$C43&"'!"&F$2&MATCH($D43,INDIRECT("'"&$C43&"'!$A:$A"),0))} -> 0.65392 | G43: {=INDIRECT("'"&$C43&"'!"&G$2&MATCH($D43,INDIRECT("'"&$C43&"'!$A:$A"),0))} -> 0.43696 | H43: {=INDIRECT("'"&$C43&"'!"&H$2&MATCH($D43,INDIRECT("'"&$C43&"'!$A:$A"),0))} -> 0.64536 | I43: {=INDIRECT("'"&$C43&"'!"&I$2&MATCH($D43,INDIRECT("'"&$C43&"'!$A:$A"),0))} -> 1607 | N43: {=INDIRECT("'"&$C43&"'!"&N$2&MATCH($D43,INDIRECT("'"&$C43&"'!$A:$A"),0))} -> 0.63783 | O43: {=INDIRECT("'"&$C43&"'!"&O$2&MATCH($D43,INDIRECT("'"&$C43&"'!$A:$A"),0))} -> 0 | P43: {=INDIRECT("'"&$C43&"'!"&P$2&MATCH($D43,INDIRECT("'"&$C43&"'!$A:$A"),0))} -> 0
B44: V3 Zero Shot 5.4n | C44: ZS3-Full-5.4n-14.04.26 | D44: All | E44: {=INDIRECT("'"&$C44&"'!"&E$2&MATCH($D44,INDIRECT("'"&$C44&"'!$A:$A"),0))} -> 0.76951 | F44: {=INDIRECT("'"&$C44&"'!"&F$2&MATCH($D44,INDIRECT("'"&$C44&"'!$A:$A"),0))} -> 0.77236 | G44: {=INDIRECT("'"&$C44&"'!"&G$2&MATCH($D44,INDIRECT("'"&$C44&"'!$A:$A"),0))} -> 0.53727 | H44: {=INDIRECT("'"&$C44&"'!"&H$2&MATCH($D44,INDIRECT("'"&$C44&"'!$A:$A"),0))} -> 0.77094 | I44: {=INDIRECT("'"&$C44&"'!"&I$2&MATCH($D44,INDIRECT("'"&$C44&"'!$A:$A"),0))} -> 1607 | N44: {=INDIRECT("'"&$C44&"'!"&N$2&MATCH($D44,INDIRECT("'"&$C44&"'!$A:$A"),0))} -> 0.7654 | O44: {=INDIRECT("'"&$C44&"'!"&O$2&MATCH($D44,INDIRECT("'"&$C44&"'!$A:$A"),0))} -> 0 | P44: {=INDIRECT("'"&$C44&"'!"&P$2&MATCH($D44,INDIRECT("'"&$C44&"'!$A:$A"),0))} -> 0
B45: V3 Zero Shot GPT 4.1m | C45: ZS3-Full-4.1m-15.04.26 | D45: All | E45: {=INDIRECT("'"&$C45&"'!"&E$2&MATCH($D45,INDIRECT("'"&$C45&"'!$A:$A"),0))} -> 0.78186 | F45: {=INDIRECT("'"&$C45&"'!"&F$2&MATCH($D45,INDIRECT("'"&$C45&"'!$A:$A"),0))} -> 0.78717 | G45: {=INDIRECT("'"&$C45&"'!"&G$2&MATCH($D45,INDIRECT("'"&$C45&"'!$A:$A"),0))} -> 0.53627 | H45: {=INDIRECT("'"&$C45&"'!"&H$2&MATCH($D45,INDIRECT("'"&$C45&"'!$A:$A"),0))} -> 0.78451 | I45: {=INDIRECT("'"&$C45&"'!"&I$2&MATCH($D45,INDIRECT("'"&$C45&"'!$A:$A"),0))} -> 1607 | N45: {=INDIRECT("'"&$C45&"'!"&N$2&MATCH($D45,INDIRECT("'"&$C45&"'!$A:$A"),0))} -> 0.77909 | O45: {=INDIRECT("'"&$C45&"'!"&O$2&MATCH($D45,INDIRECT("'"&$C45&"'!$A:$A"),0))} -> 0 | P45: {=INDIRECT("'"&$C45&"'!"&P$2&MATCH($D45,INDIRECT("'"&$C45&"'!$A:$A"),0))} -> 0
B46: V4 Zero Shot 5.4n | C46: ZS4-Full-5.4n-14.04.26 | D46: All | E46: {=INDIRECT("'"&$C46&"'!"&E$2&MATCH($D46,INDIRECT("'"&$C46&"'!$A:$A"),0))} -> 0.50232 | F46: {=INDIRECT("'"&$C46&"'!"&F$2&MATCH($D46,INDIRECT("'"&$C46&"'!$A:$A"),0))} -> 0.53486 | G46: {=INDIRECT("'"&$C46&"'!"&G$2&MATCH($D46,INDIRECT("'"&$C46&"'!$A:$A"),0))} -> 0.36101 | H46: {=INDIRECT("'"&$C46&"'!"&H$2&MATCH($D46,INDIRECT("'"&$C46&"'!$A:$A"),0))} -> 0.51808 | I46: {=INDIRECT("'"&$C46&"'!"&I$2&MATCH($D46,INDIRECT("'"&$C46&"'!$A:$A"),0))} -> 1607 | N46: {=INDIRECT("'"&$C46&"'!"&N$2&MATCH($D46,INDIRECT("'"&$C46&"'!$A:$A"),0))} -> 0.51711 | O46: {=INDIRECT("'"&$C46&"'!"&O$2&MATCH($D46,INDIRECT("'"&$C46&"'!$A:$A"),0))} -> 1 | P46: {=INDIRECT("'"&$C46&"'!"&P$2&MATCH($D46,INDIRECT("'"&$C46&"'!$A:$A"),0))} -> 0.00062
B47: V5 Zero Shot 5.4n | C47: ZS5-Full-5.4n-15.04.26 | D47: All | E47: {=INDIRECT("'"&$C47&"'!"&E$2&MATCH($D47,INDIRECT("'"&$C47&"'!$A:$A"),0))} -> 0.6986 | F47: {=INDIRECT("'"&$C47&"'!"&F$2&MATCH($D47,INDIRECT("'"&$C47&"'!$A:$A"),0))} -> 0.70635 | G47: {=INDIRECT("'"&$C47&"'!"&G$2&MATCH($D47,INDIRECT("'"&$C47&"'!$A:$A"),0))} -> 0.48443 | H47: {=INDIRECT("'"&$C47&"'!"&H$2&MATCH($D47,INDIRECT("'"&$C47&"'!$A:$A"),0))} -> 0.70245 | I47: {=INDIRECT("'"&$C47&"'!"&I$2&MATCH($D47,INDIRECT("'"&$C47&"'!$A:$A"),0))} -> 1607 | N47: {=INDIRECT("'"&$C47&"'!"&N$2&MATCH($D47,INDIRECT("'"&$C47&"'!$A:$A"),0))} -> 0.69633 | O47: {=INDIRECT("'"&$C47&"'!"&O$2&MATCH($D47,INDIRECT("'"&$C47&"'!$A:$A"),0))} -> 0 | P47: {=INDIRECT("'"&$C47&"'!"&P$2&MATCH($D47,INDIRECT("'"&$C47&"'!$A:$A"),0))} -> 0
B48: V6 Zero Shot 5.4n | C48: ZS6-Full-5.4n-15.04.26 | D48: All | E48: {=INDIRECT("'"&$C48&"'!"&E$2&MATCH($D48,INDIRECT("'"&$C48&"'!$A:$A"),0))} -> 0.69896 | F48: {=INDIRECT("'"&$C48&"'!"&F$2&MATCH($D48,INDIRECT("'"&$C48&"'!$A:$A"),0))} -> 0.70759 | G48: {=INDIRECT("'"&$C48&"'!"&G$2&MATCH($D48,INDIRECT("'"&$C48&"'!$A:$A"),0))} -> 0.46996 | H48: {=INDIRECT("'"&$C48&"'!"&H$2&MATCH($D48,INDIRECT("'"&$C48&"'!$A:$A"),0))} -> 0.70325 | I48: {=INDIRECT("'"&$C48&"'!"&I$2&MATCH($D48,INDIRECT("'"&$C48&"'!$A:$A"),0))} -> 1607 | N48: {=INDIRECT("'"&$C48&"'!"&N$2&MATCH($D48,INDIRECT("'"&$C48&"'!$A:$A"),0))} -> 0.69695 | O48: {=INDIRECT("'"&$C48&"'!"&O$2&MATCH($D48,INDIRECT("'"&$C48&"'!$A:$A"),0))} -> 2 | P48: {=INDIRECT("'"&$C48&"'!"&P$2&MATCH($D48,INDIRECT("'"&$C48&"'!$A:$A"),0))} -> 0.00124
B49: V7 Zero Shot 5.4n | C49: ZS7-Full-5.4n-15.04.26 | D49: All | E49: {=INDIRECT("'"&$C49&"'!"&E$2&MATCH($D49,INDIRECT("'"&$C49&"'!$A:$A"),0))} -> 0.72297 | F49: {=INDIRECT("'"&$C49&"'!"&F$2&MATCH($D49,INDIRECT("'"&$C49&"'!$A:$A"),0))} -> 0.7261 | G49: {=INDIRECT("'"&$C49&"'!"&G$2&MATCH($D49,INDIRECT("'"&$C49&"'!$A:$A"),0))} -> 0.49403 | H49: {=INDIRECT("'"&$C49&"'!"&H$2&MATCH($D49,INDIRECT("'"&$C49&"'!$A:$A"),0))} -> 0.72453 | I49: {=INDIRECT("'"&$C49&"'!"&I$2&MATCH($D49,INDIRECT("'"&$C49&"'!$A:$A"),0))} -> 1607 | N49: {=INDIRECT("'"&$C49&"'!"&N$2&MATCH($D49,INDIRECT("'"&$C49&"'!$A:$A"),0))} -> 0.71686 | O49: {=INDIRECT("'"&$C49&"'!"&O$2&MATCH($D49,INDIRECT("'"&$C49&"'!$A:$A"),0))} -> 0 | P49: {=INDIRECT("'"&$C49&"'!"&P$2&MATCH($D49,INDIRECT("'"&$C49&"'!$A:$A"),0))} -> 0
B50: V8 Zero Shot Gemini 2.5 Flash | C50: ZS8-Full-Gemini2.5-flash-27.05. | D50: All | E50: {=INDIRECT("'"&$C50&"'!"&E$2&MATCH($D50,INDIRECT("'"&$C50&"'!$A:$A"),0))} -> 0.87805 | F50: {=INDIRECT("'"&$C50&"'!"&F$2&MATCH($D50,INDIRECT("'"&$C50&"'!$A:$A"),0))} -> 0.86613 | G50: {=INDIRECT("'"&$C50&"'!"&G$2&MATCH($D50,INDIRECT("'"&$C50&"'!$A:$A"),0))} -> 0.6782 | H50: {=INDIRECT("'"&$C50&"'!"&H$2&MATCH($D50,INDIRECT("'"&$C50&"'!$A:$A"),0))} -> 0.87205 | I50: {=INDIRECT("'"&$C50&"'!"&I$2&MATCH($D50,INDIRECT("'"&$C50&"'!$A:$A"),0))} -> 1607 | N50: {=INDIRECT("'"&$C50&"'!"&N$2&MATCH($D50,INDIRECT("'"&$C50&"'!$A:$A"),0))} -> 0.85812 | O50: {=INDIRECT("'"&$C50&"'!"&O$2&MATCH($D50,INDIRECT("'"&$C50&"'!$A:$A"),0))} -> 33 | P50: {=INDIRECT("'"&$C50&"'!"&P$2&MATCH($D50,INDIRECT("'"&$C50&"'!$A:$A"),0))} -> 0.02054
B51: V9 Zero Shot Gemini 3.1 Pro | C51: ZS9-Full-Gemini3.1-pro-27.05.26 | D51: All | E51: {=INDIRECT("'"&$C51&"'!"&E$2&MATCH($D51,INDIRECT("'"&$C51&"'!$A:$A"),0))} -> 0.90698 | F51: {=INDIRECT("'"&$C51&"'!"&F$2&MATCH($D51,INDIRECT("'"&$C51&"'!$A:$A"),0))} -> 0.91425 | G51: {=INDIRECT("'"&$C51&"'!"&G$2&MATCH($D51,INDIRECT("'"&$C51&"'!$A:$A"),0))} -> 0.71753 | H51: {=INDIRECT("'"&$C51&"'!"&H$2&MATCH($D51,INDIRECT("'"&$C51&"'!$A:$A"),0))} -> 0.9106 | I51: {=INDIRECT("'"&$C51&"'!"&I$2&MATCH($D51,INDIRECT("'"&$C51&"'!$A:$A"),0))} -> 1607 | N51: {=INDIRECT("'"&$C51&"'!"&N$2&MATCH($D51,INDIRECT("'"&$C51&"'!$A:$A"),0))} -> 0.90666 | O51: {=INDIRECT("'"&$C51&"'!"&O$2&MATCH($D51,INDIRECT("'"&$C51&"'!$A:$A"),0))} -> 0 | P51: {=INDIRECT("'"&$C51&"'!"&P$2&MATCH($D51,INDIRECT("'"&$C51&"'!$A:$A"),0))} -> 0
... B62: V7 Few Shot 4.1m | C62: FS7-Full-4.1m-19.05.26 | D62: All | E62: {=INDIRECT("'"&$C62&"'!"&E$2&MATCH($D62,INDIRECT("'"&$C62&"'!$A:$A"),0))} -> 0.21033 | F62: {=INDIRECT("'"&$C62&"'!"&F$2&MATCH($D62,INDIRECT("'"&$C62&"'!$A:$A"),0))} -> 0.10549 | G62: {=INDIRECT("'"&$C62&"'!"&G$2&MATCH($D62,INDIRECT("'"&$C62&"'!$A:$A"),0))} -> 0.3566 | H62: {=INDIRECT("'"&$C62&"'!"&H$2&MATCH($D62,INDIRECT("'"&$C62&"'!$A:$A"),0))} -> 0.14051 | I62: {=INDIRECT("'"&$C62&"'!"&I$2&MATCH($D62,INDIRECT("'"&$C62&"'!$A:$A"),0))} -> 1607 | N62: {=INDIRECT("'"&$C62&"'!"&N$2&MATCH($D62,INDIRECT("'"&$C62&"'!$A:$A"),0))} -> 0.08836 | O62: {=INDIRECT("'"&$C62&"'!"&O$2&MATCH($D62,INDIRECT("'"&$C62&"'!$A:$A"),0))} -> 825 | P62: {=INDIRECT("'"&$C62&"'!"&P$2&MATCH($D62,INDIRECT("'"&$C62&"'!$A:$A"),0))} -> 0.51338
B65: Fine Tunned GPT 4.1m | C65: GPT4.1m-fine-tunned | D65: 0 | E65: {=INDIRECT("'"&$C65&"'!"&E$2&MATCH($D65,INDIRECT("'"&$C65&"'!$A:$A"),0))} -> 0.70455 | F65: {=INDIRECT("'"&$C65&"'!"&F$2&MATCH($D65,INDIRECT("'"&$C65&"'!$A:$A"),0))} -> 0.81579 | G65: {=INDIRECT("'"&$C65&"'!"&G$2&MATCH($D65,INDIRECT("'"&$C65&"'!$A:$A"),0))} -> 0.7561 | I65: {=INDIRECT("'"&$C65&"'!"&I$2&MATCH($D65,INDIRECT("'"&$C65&"'!$A:$A"),0))} -> 38 | J65: {=INDIRECT("'"&$C65&"'!"&J$2&MATCH($D65,INDIRECT("'"&$C65&"'!$A:$A"),0))} -> 31 | K65: {=INDIRECT("'"&$C65&"'!"&K$2&MATCH($D65,INDIRECT("'"&$C65&"'!$A:$A"),0))} -> 13 | L65: {=INDIRECT("'"&$C65&"'!"&L$2&MATCH($D65,INDIRECT("'"&$C65&"'!$A:$A"),0))} -> 7
B66: Fine Tunned Gemini-2.5-flash | C66: Gemini-2.5-flash-fine-tunned | D66: 0 | E66: {=INDIRECT("'"&$C66&"'!"&E$2&MATCH($D66,INDIRECT("'"&$C66&"'!$A:$A"),0))} -> 0.625 | F66: {=INDIRECT("'"&$C66&"'!"&F$2&MATCH($D66,INDIRECT("'"&$C66&"'!$A:$A"),0))} -> 0.78947 | G66: {=INDIRECT("'"&$C66&"'!"&G$2&MATCH($D66,INDIRECT("'"&$C66&"'!$A:$A"),0))} -> 0.69767 | I66: {=INDIRECT("'"&$C66&"'!"&I$2&MATCH($D66,INDIRECT("'"&$C66&"'!$A:$A"),0))} -> 38 | J66: {=INDIRECT("'"&$C66&"'!"&J$2&MATCH($D66,INDIRECT("'"&$C66&"'!$A:$A"),0))} -> 30 | K66: {=INDIRECT("'"&$C66&"'!"&K$2&MATCH($D66,INDIRECT("'"&$C66&"'!$A:$A"),0))} -> 18 | L66: {=INDIRECT("'"&$C66&"'!"&L$2&MATCH($D66,INDIRECT("'"&$C66&"'!$A:$A"),0))} -> 8
B67: V1 Zero Shot 4.1m | C67: ZS1-Full-4.1m-21.03.26 | D67: 0 | E67: {=INDIRECT("'"&$C67&"'!"&E$2&MATCH($D67,INDIRECT("'"&$C67&"'!$A:$A"),0))} -> 0.15261 | F67: {=INDIRECT("'"&$C67&"'!"&F$2&MATCH($D67,INDIRECT("'"&$C67&"'!$A:$A"),0))} -> 1 | G67: {=INDIRECT("'"&$C67&"'!"&G$2&MATCH($D67,INDIRECT("'"&$C67&"'!$A:$A"),0))} -> 0.26481 | I67: {=INDIRECT("'"&$C67&"'!"&I$2&MATCH($D67,INDIRECT("'"&$C67&"'!$A:$A"),0))} -> 38 | J67: {=INDIRECT("'"&$C67&"'!"&J$2&MATCH($D67,INDIRECT("'"&$C67&"'!$A:$A"),0))} -> 38 | K67: {=INDIRECT("'"&$C67&"'!"&K$2&MATCH($D67,INDIRECT("'"&$C67&"'!$A:$A"),0))} -> 211 | L67: {=INDIRECT("'"&$C67&"'!"&L$2&MATCH($D67,INDIRECT("'"&$C67&"'!$A:$A"),0))} -> 0
B68: V2 Zero Shot 4.1m | C68: ZS2-Full-4.1m-07.04.26 | D68: 0 | E68: {=INDIRECT("'"&$C68&"'!"&E$2&MATCH($D68,INDIRECT("'"&$C68&"'!$A:$A"),0))} -> 0.17117 | F68: {=INDIRECT("'"&$C68&"'!"&F$2&MATCH($D68,INDIRECT("'"&$C68&"'!$A:$A"),0))} -> 1 | G68: {=INDIRECT("'"&$C68&"'!"&G$2&MATCH($D68,INDIRECT("'"&$C68&"'!$A:$A"),0))} -> 0.29231 | I68: {=INDIRECT("'"&$C68&"'!"&I$2&MATCH($D68,INDIRECT("'"&$C68&"'!$A:$A"),0))} -> 38 | J68: {=INDIRECT("'"&$C68&"'!"&J$2&MATCH($D68,INDIRECT("'"&$C68&"'!$A:$A"),0))} -> 38 | K68: {=INDIRECT("'"&$C68&"'!"&K$2&MATCH($D68,INDIRECT("'"&$C68&"'!$A:$A"),0))} -> 184 | L68: {=INDIRECT("'"&$C68&"'!"&L$2&MATCH($D68,INDIRECT("'"&$C68&"'!$A:$A"),0))} -> 0
B69: V3 Zero Shot 5.4n | C69: ZS3-Full-5.4n-14.04.26 | D69: 0 | E69: {=INDIRECT("'"&$C69&"'!"&E$2&MATCH($D69,INDIRECT("'"&$C69&"'!$A:$A"),0))} -> 0.34043 | F69: {=INDIRECT("'"&$C69&"'!"&F$2&MATCH($D69,INDIRECT("'"&$C69&"'!$A:$A"),0))} -> 0.84211 | G69: {=INDIRECT("'"&$C69&"'!"&G$2&MATCH($D69,INDIRECT("'"&$C69&"'!$A:$A"),0))} -> 0.48485 | I69: {=INDIRECT("'"&$C69&"'!"&I$2&MATCH($D69,INDIRECT("'"&$C69&"'!$A:$A"),0))} -> 38 | J69: {=INDIRECT("'"&$C69&"'!"&J$2&MATCH($D69,INDIRECT("'"&$C69&"'!$A:$A"),0))} -> 32 | K69: {=INDIRECT("'"&$C69&"'!"&K$2&MATCH($D69,INDIRECT("'"&$C69&"'!$A:$A"),0))} -> 62 | L69: {=INDIRECT("'"&$C69&"'!"&L$2&MATCH($D69,INDIRECT("'"&$C69&"'!$A:$A"),0))} -> 6
B70: Zero Shot 4.1m | C70: ZS3-Full-4.1m-15.04.26 | D70: 0 | E70: {=INDIRECT("'"&$C70&"'!"&E$2&MATCH($D70,INDIRECT("'"&$C70&"'!$A:$A"),0))} -> 0.30357 | F70: {=INDIRECT("'"&$C70&"'!"&F$2&MATCH($D70,INDIRECT("'"&$C70&"'!$A:$A"),0))} -> 0.89474 | G70: {=INDIRECT("'"&$C70&"'!"&G$2&MATCH($D70,INDIRECT("'"&$C70&"'!$A:$A"),0))} -> 0.45333 | I70: {=INDIRECT("'"&$C70&"'!"&I$2&MATCH($D70,INDIRECT("'"&$C70&"'!$A:$A"),0))} -> 38 | J70: {=INDIRECT("'"&$C70&"'!"&J$2&MATCH($D70,INDIRECT("'"&$C70&"'!$A:$A"),0))} -> 34 | K70: {=INDIRECT("'"&$C70&"'!"&K$2&MATCH($D70,INDIRECT("'"&$C70&"'!$A:$A"),0))} -> 78 | L70: {=INDIRECT("'"&$C70&"'!"&L$2&MATCH($D70,INDIRECT("'"&$C70&"'!$A:$A"),0))} -> 4
B71: V4 Zero Shot 5.4n | C71: ZS4-Full-5.4n-14.04.26 | D71: 0 | E71: {=INDIRECT("'"&$C71&"'!"&E$2&MATCH($D71,INDIRECT("'"&$C71&"'!$A:$A"),0))} -> 0.14859 | F71: {=INDIRECT("'"&$C71&"'!"&F$2&MATCH($D71,INDIRECT("'"&$C71&"'!$A:$A"),0))} -> 0.97368 | G71: {=INDIRECT("'"&$C71&"'!"&G$2&MATCH($D71,INDIRECT("'"&$C71&"'!$A:$A"),0))} -> 0.25784 | I71: {=INDIRECT("'"&$C71&"'!"&I$2&MATCH($D71,INDIRECT("'"&$C71&"'!$A:$A"),0))} -> 38 | J71: {=INDIRECT("'"&$C71&"'!"&J$2&MATCH($D71,INDIRECT("'"&$C71&"'!$A:$A"),0))} -> 37 | K71: {=INDIRECT("'"&$C71&"'!"&K$2&MATCH($D71,INDIRECT("'"&$C71&"'!$A:$A"),0))} -> 212 | L71: {=INDIRECT("'"&$C71&"'!"&L$2&MATCH($D71,INDIRECT("'"&$C71&"'!$A:$A"),0))} -> 1
B72: V5 Zero Shot 5.4n | C72: ZS5-Full-5.4n-15.04.26 | D72: 0 | E72: {=INDIRECT("'"&$C72&"'!"&E$2&MATCH($D72,INDIRECT("'"&$C72&"'!$A:$A"),0))} -> 0.19792 | F72: {=INDIRECT("'"&$C72&"'!"&F$2&MATCH($D72,INDIRECT("'"&$C72&"'!$A:$A"),0))} -> 1 | G72: {=INDIRECT("'"&$C72&"'!"&G$2&MATCH($D72,INDIRECT("'"&$C72&"'!$A:$A"),0))} -> 0.33043 | I72: {=INDIRECT("'"&$C72&"'!"&I$2&MATCH($D72,INDIRECT("'"&$C72&"'!$A:$A"),0))} -> 38 | J72: {=INDIRECT("'"&$C72&"'!"&J$2&MATCH($D72,INDIRECT("'"&$C72&"'!$A:$A"),0))} -> 38 | K72: {=INDIRECT("'"&$C72&"'!"&K$2&MATCH($D72,INDIRECT("'"&$C72&"'!$A:$A"),0))} -> 154 | L72: {=INDIRECT("'"&$C72&"'!"&L$2&MATCH($D72,INDIRECT("'"&$C72&"'!$A:$A"),0))} -> 0
B73: V6 Zero Shot 5.4n | C73: ZS6-Full-5.4n-15.04.26 | D73: 0 | E73: {=INDIRECT("'"&$C73&"'!"&E$2&MATCH($D73,INDIRECT("'"&$C73&"'!$A:$A"),0))} -> 0.21512 | F73: {=INDIRECT("'"&$C73&"'!"&F$2&MATCH($D73,INDIRECT("'"&$C73&"'!$A:$A"),0))} -> 0.97368 | G73: {=INDIRECT("'"&$C73&"'!"&G$2&MATCH($D73,INDIRECT("'"&$C73&"'!$A:$A"),0))} -> 0.35238 | I73: {=INDIRECT("'"&$C73&"'!"&I$2&MATCH($D73,INDIRECT("'"&$C73&"'!$A:$A"),0))} -> 38 | J73: {=INDIRECT("'"&$C73&"'!"&J$2&MATCH($D73,INDIRECT("'"&$C73&"'!$A:$A"),0))} -> 37 | K73: {=INDIRECT("'"&$C73&"'!"&K$2&MATCH($D73,INDIRECT("'"&$C73&"'!$A:$A"),0))} -> 135 | L73: {=INDIRECT("'"&$C73&"'!"&L$2&MATCH($D73,INDIRECT("'"&$C73&"'!$A:$A"),0))} -> 1
B74: V7 Zero Shot 5.4n | C74: ZS7-Full-5.4n-15.04.26 | D74: 0 | E74: {=INDIRECT("'"&$C74&"'!"&E$2&MATCH($D74,INDIRECT("'"&$C74&"'!$A:$A"),0))} -> 0.21765 | F74: {=INDIRECT("'"&$C74&"'!"&F$2&MATCH($D74,INDIRECT("'"&$C74&"'!$A:$A"),0))} -> 0.97368 | G74: {=INDIRECT("'"&$C74&"'!"&G$2&MATCH($D74,INDIRECT("'"&$C74&"'!$A:$A"),0))} -> 0.35577 | I74: {=INDIRECT("'"&$C74&"'!"&I$2&MATCH($D74,INDIRECT("'"&$C74&"'!$A:$A"),0))} -> 38 | J74: {=INDIRECT("'"&$C74&"'!"&J$2&MATCH($D74,INDIRECT("'"&$C74&"'!$A:$A"),0))} -> 37 | K74: {=INDIRECT("'"&$C74&"'!"&K$2&MATCH($D74,INDIRECT("'"&$C74&"'!$A:$A"),0))} -> 133 | L74: {=INDIRECT("'"&$C74&"'!"&L$2&MATCH($D74,INDIRECT("'"&$C74&"'!$A:$A"),0))} -> 1
B75: V8 Zero Shot Gemini 2.5 Flash | C75: ZS8-Full-Gemini2.5-flash-27.05. | D75: 0 | E75: {=INDIRECT("'"&$C75&"'!"&E$2&MATCH($D75,INDIRECT("'"&$C75&"'!$A:$A"),0))} -> 0.425 | F75: {=INDIRECT("'"&$C75&"'!"&F$2&MATCH($D75,INDIRECT("'"&$C75&"'!$A:$A"),0))} -> 0.89474 | G75: {=INDIRECT("'"&$C75&"'!"&G$2&MATCH($D75,INDIRECT("'"&$C75&"'!$A:$A"),0))} -> 0.57627 | I75: {=INDIRECT("'"&$C75&"'!"&I$2&MATCH($D75,INDIRECT("'"&$C75&"'!$A:$A"),0))} -> 38 | J75: {=INDIRECT("'"&$C75&"'!"&J$2&MATCH($D75,INDIRECT("'"&$C75&"'!$A:$A"),0))} -> 34 | K75: {=INDIRECT("'"&$C75&"'!"&K$2&MATCH($D75,INDIRECT("'"&$C75&"'!$A:$A"),0))} -> 46 | L75: {=INDIRECT("'"&$C75&"'!"&L$2&MATCH($D75,INDIRECT("'"&$C75&"'!$A:$A"),0))} -> 4
B76: V9 Zero Shot Gemini 3.1 Pro | C76: ZS9-Full-Gemini3.1-pro-27.05.26 | D76: 0 | E76: {=INDIRECT("'"&$C76&"'!"&E$2&MATCH($D76,INDIRECT("'"&$C76&"'!$A:$A"),0))} -> 0.44928 | F76: {=INDIRECT("'"&$C76&"'!"&F$2&MATCH($D76,INDIRECT("'"&$C76&"'!$A:$A"),0))} -> 0.81579 | G76: {=INDIRECT("'"&$C76&"'!"&G$2&MATCH($D76,INDIRECT("'"&$C76&"'!$A:$A"),0))} -> 0.57944 | I76: {=INDIRECT("'"&$C76&"'!"&I$2&MATCH($D76,INDIRECT("'"&$C76&"'!$A:$A"),0))} -> 38 | J76: {=INDIRECT("'"&$C76&"'!"&J$2&MATCH($D76,INDIRECT("'"&$C76&"'!$A:$A"),0))} -> 31 | K76: {=INDIRECT("'"&$C76&"'!"&K$2&MATCH($D76,INDIRECT("'"&$C76&"'!$A:$A"),0))} -> 38 | L76: {=INDIRECT("'"&$C76&"'!"&L$2&MATCH($D76,INDIRECT("'"&$C76&"'!$A:$A"),0))} -> 7
... B287: V8 Few Shot Gemini 2.5 Flash | C287: FS8-Full-Gemini-2.5-flash-27.05 | D287: 8 | E287: {=INDIRECT("'"&$C287&"'!"&E$2&MATCH($D287,INDIRECT("'"&$C287&"'!$A:$A"),0))} -> 0.98897 | F287: {=INDIRECT("'"&$C287&"'!"&F$2&MATCH($D287,INDIRECT("'"&$C287&"'!$A:$A"),0))} -> 0.87456 | G287: {=INDIRECT("'"&$C287&"'!"&G$2&MATCH($D287,INDIRECT("'"&$C287&"'!$A:$A"),0))} -> 0.92825 | I287: {=INDIRECT("'"&$C287&"'!"&I$2&MATCH($D287,INDIRECT("'"&$C287&"'!$A:$A"),0))} -> 1435 | J287: {=INDIRECT("'"&$C287&"'!"&J$2&MATCH($D287,INDIRECT("'"&$C287&"'!$A:$A"),0))} -> 1255 | K287: {=INDIRECT("'"&$C287&"'!"&K$2&MATCH($D287,INDIRECT("'"&$C287&"'!$A:$A"),0))} -> 14 | L287: {=INDIRECT("'"&$C287&"'!"&L$2&MATCH($D287,INDIRECT("'"&$C287&"'!$A:$A"),0))} -> 180
B290: Fine Tunned GPT 4.1m | C290: GPT4.1m-fine-tunned | D290: unfair_binary | E290: {=INDIRECT("'"&$C290&"'!"&E$2&MATCH($D290,INDIRECT("'"&$C290&"'!$A:$A"),0))} -> 0.82778 | F290: {=INDIRECT("'"&$C290&"'!"&F$2&MATCH($D290,INDIRECT("'"&$C290&"'!$A:$A"),0))} -> 0.86628 | G290: {=INDIRECT("'"&$C290&"'!"&G$2&MATCH($D290,INDIRECT("'"&$C290&"'!$A:$A"),0))} -> 0.84659 | J290: {=INDIRECT("'"&$C290&"'!"&J$2&MATCH($D290,INDIRECT("'"&$C290&"'!$A:$A"),0))} -> 149 | K290: {=INDIRECT("'"&$C290&"'!"&K$2&MATCH($D290,INDIRECT("'"&$C290&"'!$A:$A"),0))} -> 31 | L290: {=INDIRECT("'"&$C290&"'!"&L$2&MATCH($D290,INDIRECT("'"&$C290&"'!$A:$A"),0))} -> 23 | M290: {=INDIRECT("'"&$C290&"'!"&M$2&MATCH($D290,INDIRECT("'"&$C290&"'!$A:$A"),0))} -> 1404 | N290: {=INDIRECT("'"&$C290&"'!"&N$2&MATCH($D290,INDIRECT("'"&$C290&"'!$A:$A"),0))} -> 0.9664
B291: Fine Tunned Gemini-2.5-flash | C291: Gemini-2.5-flash-fine-tunned | D291: unfair_binary | E291: {=INDIRECT("'"&$C291&"'!"&E$2&MATCH($D291,INDIRECT("'"&$C291&"'!$A:$A"),0))} -> 0.73709 | F291: {=INDIRECT("'"&$C291&"'!"&F$2&MATCH($D291,INDIRECT("'"&$C291&"'!$A:$A"),0))} -> 0.91279 | G291: {=INDIRECT("'"&$C291&"'!"&G$2&MATCH($D291,INDIRECT("'"&$C291&"'!$A:$A"),0))} -> 0.81558 | J291: {=INDIRECT("'"&$C291&"'!"&J$2&MATCH($D291,INDIRECT("'"&$C291&"'!$A:$A"),0))} -> 157 | K291: {=INDIRECT("'"&$C291&"'!"&K$2&MATCH($D291,INDIRECT("'"&$C291&"'!$A:$A"),0))} -> 56 | L291: {=INDIRECT("'"&$C291&"'!"&L$2&MATCH($D291,INDIRECT("'"&$C291&"'!$A:$A"),0))} -> 15 | M291: {=INDIRECT("'"&$C291&"'!"&M$2&MATCH($D291,INDIRECT("'"&$C291&"'!$A:$A"),0))} -> 1379 | N291: {=INDIRECT("'"&$C291&"'!"&N$2&MATCH($D291,INDIRECT("'"&$C291&"'!$A:$A"),0))} -> 0.95582
B292: V1 Zero Shot 4.1m | C292: ZS1-Full-4.1m-21.03.26 | D292: unfair_binary | E292: {=INDIRECT("'"&$C292&"'!"&E$2&MATCH($D292,INDIRECT("'"&$C292&"'!$A:$A"),0))} -> 0.24429 | F292: {=INDIRECT("'"&$C292&"'!"&F$2&MATCH($D292,INDIRECT("'"&$C292&"'!$A:$A"),0))} -> 0.99419 | G292: {=INDIRECT("'"&$C292&"'!"&G$2&MATCH($D292,INDIRECT("'"&$C292&"'!$A:$A"),0))} -> 0.3922 | J292: {=INDIRECT("'"&$C292&"'!"&J$2&MATCH($D292,INDIRECT("'"&$C292&"'!$A:$A"),0))} -> 171 | K292: {=INDIRECT("'"&$C292&"'!"&K$2&MATCH($D292,INDIRECT("'"&$C292&"'!$A:$A"),0))} -> 529 | L292: {=INDIRECT("'"&$C292&"'!"&L$2&MATCH($D292,INDIRECT("'"&$C292&"'!$A:$A"),0))} -> 1 | M292: {=INDIRECT("'"&$C292&"'!"&M$2&MATCH($D292,INDIRECT("'"&$C292&"'!$A:$A"),0))} -> 906 | N292: {=INDIRECT("'"&$C292&"'!"&N$2&MATCH($D292,INDIRECT("'"&$C292&"'!$A:$A"),0))} -> 0.67019
B293: V2 Zero Shot 4.1m | C293: ZS2-Full-4.1m-07.04.26 | D293: unfair_binary | E293: {=INDIRECT("'"&$C293&"'!"&E$2&MATCH($D293,INDIRECT("'"&$C293&"'!$A:$A"),0))} -> 0.23662 | F293: {=INDIRECT("'"&$C293&"'!"&F$2&MATCH($D293,INDIRECT("'"&$C293&"'!$A:$A"),0))} -> 0.97674 | G293: {=INDIRECT("'"&$C293&"'!"&G$2&MATCH($D293,INDIRECT("'"&$C293&"'!$A:$A"),0))} -> 0.38095 | J293: {=INDIRECT("'"&$C293&"'!"&J$2&MATCH($D293,INDIRECT("'"&$C293&"'!$A:$A"),0))} -> 168 | K293: {=INDIRECT("'"&$C293&"'!"&K$2&MATCH($D293,INDIRECT("'"&$C293&"'!$A:$A"),0))} -> 542 | L293: {=INDIRECT("'"&$C293&"'!"&L$2&MATCH($D293,INDIRECT("'"&$C293&"'!$A:$A"),0))} -> 4 | M293: {=INDIRECT("'"&$C293&"'!"&M$2&MATCH($D293,INDIRECT("'"&$C293&"'!$A:$A"),0))} -> 893 | N293: {=INDIRECT("'"&$C293&"'!"&N$2&MATCH($D293,INDIRECT("'"&$C293&"'!$A:$A"),0))} -> 0.66024
B294: V3 Zero Shot 5.4n | C294: ZS3-Full-5.4n-14.04.26 | D294: unfair_binary | E294: {=INDIRECT("'"&$C294&"'!"&E$2&MATCH($D294,INDIRECT("'"&$C294&"'!$A:$A"),0))} -> 0.32227 | F294: {=INDIRECT("'"&$C294&"'!"&F$2&MATCH($D294,INDIRECT("'"&$C294&"'!$A:$A"),0))} -> 0.9593 | G294: {=INDIRECT("'"&$C294&"'!"&G$2&MATCH($D294,INDIRECT("'"&$C294&"'!$A:$A"),0))} -> 0.48246 | J294: {=INDIRECT("'"&$C294&"'!"&J$2&MATCH($D294,INDIRECT("'"&$C294&"'!$A:$A"),0))} -> 165 | K294: {=INDIRECT("'"&$C294&"'!"&K$2&MATCH($D294,INDIRECT("'"&$C294&"'!$A:$A"),0))} -> 347 | L294: {=INDIRECT("'"&$C294&"'!"&L$2&MATCH($D294,INDIRECT("'"&$C294&"'!$A:$A"),0))} -> 7 | M294: {=INDIRECT("'"&$C294&"'!"&M$2&MATCH($D294,INDIRECT("'"&$C294&"'!$A:$A"),0))} -> 1088 | N294: {=INDIRECT("'"&$C294&"'!"&N$2&MATCH($D294,INDIRECT("'"&$C294&"'!$A:$A"),0))} -> 0.77971
B295: V3 Zero Shot 4.1m | C295: ZS3-Full-4.1m-15.04.26 | D295: unfair_binary | E295: {=INDIRECT("'"&$C295&"'!"&E$2&MATCH($D295,INDIRECT("'"&$C295&"'!$A:$A"),0))} -> 0.34232 | F295: {=INDIRECT("'"&$C295&"'!"&F$2&MATCH($D295,INDIRECT("'"&$C295&"'!$A:$A"),0))} -> 0.9593 | G295: {=INDIRECT("'"&$C295&"'!"&G$2&MATCH($D295,INDIRECT("'"&$C295&"'!$A:$A"),0))} -> 0.50459 | J295: {=INDIRECT("'"&$C295&"'!"&J$2&MATCH($D295,INDIRECT("'"&$C295&"'!$A:$A"),0))} -> 165 | K295: {=INDIRECT("'"&$C295&"'!"&K$2&MATCH($D295,INDIRECT("'"&$C295&"'!$A:$A"),0))} -> 317 | L295: {=INDIRECT("'"&$C295&"'!"&L$2&MATCH($D295,INDIRECT("'"&$C295&"'!$A:$A"),0))} -> 7 | M295: {=INDIRECT("'"&$C295&"'!"&M$2&MATCH($D295,INDIRECT("'"&$C295&"'!$A:$A"),0))} -> 1118 | N295: {=INDIRECT("'"&$C295&"'!"&N$2&MATCH($D295,INDIRECT("'"&$C295&"'!$A:$A"),0))} -> 0.79838
B296: V4 Zero Shot 5.4n | C296: ZS4-Full-5.4n-14.04.26 | D296: unfair_binary | E296: {=INDIRECT("'"&$C296&"'!"&E$2&MATCH($D296,INDIRECT("'"&$C296&"'!$A:$A"),0))} -> 0.18874 | F296: {=INDIRECT("'"&$C296&"'!"&F$2&MATCH($D296,INDIRECT("'"&$C296&"'!$A:$A"),0))} -> 0.99419 | G296: {=INDIRECT("'"&$C296&"'!"&G$2&MATCH($D296,INDIRECT("'"&$C296&"'!$A:$A"),0))} -> 0.31725 | J296: {=INDIRECT("'"&$C296&"'!"&J$2&MATCH($D296,INDIRECT("'"&$C296&"'!$A:$A"),0))} -> 171 | K296: {=INDIRECT("'"&$C296&"'!"&K$2&MATCH($D296,INDIRECT("'"&$C296&"'!$A:$A"),0))} -> 735 | L296: {=INDIRECT("'"&$C296&"'!"&L$2&MATCH($D296,INDIRECT("'"&$C296&"'!$A:$A"),0))} -> 1 | M296: {=INDIRECT("'"&$C296&"'!"&M$2&MATCH($D296,INDIRECT("'"&$C296&"'!$A:$A"),0))} -> 700 | N296: {=INDIRECT("'"&$C296&"'!"&N$2&MATCH($D296,INDIRECT("'"&$C296&"'!$A:$A"),0))} -> 0.542
B297: V5 Zero Shot 5.4n | C297: ZS5-Full-5.4n-15.04.26 | D297: unfair_binary | E297: {=INDIRECT("'"&$C297&"'!"&E$2&MATCH($D297,INDIRECT("'"&$C297&"'!$A:$A"),0))} -> 0.2711 | F297: {=INDIRECT("'"&$C297&"'!"&F$2&MATCH($D297,INDIRECT("'"&$C297&"'!$A:$A"),0))} -> 0.97093 | G297: {=INDIRECT("'"&$C297&"'!"&G$2&MATCH($D297,INDIRECT("'"&$C297&"'!$A:$A"),0))} -> 0.42386 | J297: {=INDIRECT("'"&$C297&"'!"&J$2&MATCH($D297,INDIRECT("'"&$C297&"'!$A:$A"),0))} -> 167 | K297: {=INDIRECT("'"&$C297&"'!"&K$2&MATCH($D297,INDIRECT("'"&$C297&"'!$A:$A"),0))} -> 449 | L297: {=INDIRECT("'"&$C297&"'!"&L$2&MATCH($D297,INDIRECT("'"&$C297&"'!$A:$A"),0))} -> 5 | M297: {=INDIRECT("'"&$C297&"'!"&M$2&MATCH($D297,INDIRECT("'"&$C297&"'!$A:$A"),0))} -> 986 | N297: {=INDIRECT("'"&$C297&"'!"&N$2&MATCH($D297,INDIRECT("'"&$C297&"'!$A:$A"),0))} -> 0.71749
B298: V6 Zero Shot 5.4n | C298: ZS6-Full-5.4n-15.04.26 | D298: unfair_binary | E298: {=INDIRECT("'"&$C298&"'!"&E$2&MATCH($D298,INDIRECT("'"&$C298&"'!$A:$A"),0))} -> 0.27213 | F298: {=INDIRECT("'"&$C298&"'!"&F$2&MATCH($D298,INDIRECT("'"&$C298&"'!$A:$A"),0))} -> 0.96512 | G298: {=INDIRECT("'"&$C298&"'!"&G$2&MATCH($D298,INDIRECT("'"&$C298&"'!$A:$A"),0))} -> 0.42455 | J298: {=INDIRECT("'"&$C298&"'!"&J$2&MATCH($D298,INDIRECT("'"&$C298&"'!$A:$A"),0))} -> 166 | K298: {=INDIRECT("'"&$C298&"'!"&K$2&MATCH($D298,INDIRECT("'"&$C298&"'!$A:$A"),0))} -> 444 | L298: {=INDIRECT("'"&$C298&"'!"&L$2&MATCH($D298,INDIRECT("'"&$C298&"'!$A:$A"),0))} -> 6 | M298: {=INDIRECT("'"&$C298&"'!"&M$2&MATCH($D298,INDIRECT("'"&$C298&"'!$A:$A"),0))} -> 991 | N298: {=INDIRECT("'"&$C298&"'!"&N$2&MATCH($D298,INDIRECT("'"&$C298&"'!$A:$A"),0))} -> 0.71998
B299: V7 Zero Shot 5.4n | C299: ZS7-Full-5.4n-15.04.26 | D299: unfair_binary | E299: {=INDIRECT("'"&$C299&"'!"&E$2&MATCH($D299,INDIRECT("'"&$C299&"'!$A:$A"),0))} -> 0.28644 | F299: {=INDIRECT("'"&$C299&"'!"&F$2&MATCH($D299,INDIRECT("'"&$C299&"'!$A:$A"),0))} -> 0.98256 | G299: {=INDIRECT("'"&$C299&"'!"&G$2&MATCH($D299,INDIRECT("'"&$C299&"'!$A:$A"),0))} -> 0.44357 | J299: {=INDIRECT("'"&$C299&"'!"&J$2&MATCH($D299,INDIRECT("'"&$C299&"'!$A:$A"),0))} -> 169 | K299: {=INDIRECT("'"&$C299&"'!"&K$2&MATCH($D299,INDIRECT("'"&$C299&"'!$A:$A"),0))} -> 421 | L299: {=INDIRECT("'"&$C299&"'!"&L$2&MATCH($D299,INDIRECT("'"&$C299&"'!$A:$A"),0))} -> 3 | M299: {=INDIRECT("'"&$C299&"'!"&M$2&MATCH($D299,INDIRECT("'"&$C299&"'!$A:$A"),0))} -> 1014 | N299: {=INDIRECT("'"&$C299&"'!"&N$2&MATCH($D299,INDIRECT("'"&$C299&"'!$A:$A"),0))} -> 0.73615
B300: V8 Zero Shot Gemini 2.5 Flash | C300: ZS8-Full-Gemini2.5-flash-27.05. | D300: unfair_binary | E300: {=INDIRECT("'"&$C300&"'!"&E$2&MATCH($D300,INDIRECT("'"&$C300&"'!$A:$A"),0))} -> 0.49045 | F300: {=INDIRECT("'"&$C300&"'!"&F$2&MATCH($D300,INDIRECT("'"&$C300&"'!$A:$A"),0))} -> 0.89535 | G300: {=INDIRECT("'"&$C300&"'!"&G$2&MATCH($D300,INDIRECT("'"&$C300&"'!$A:$A"),0))} -> 0.63374 | J300: {=INDIRECT("'"&$C300&"'!"&J$2&MATCH($D300,INDIRECT("'"&$C300&"'!$A:$A"),0))} -> 154 | K300: {=INDIRECT("'"&$C300&"'!"&K$2&MATCH($D300,INDIRECT("'"&$C300&"'!$A:$A"),0))} -> 160 | L300: {=INDIRECT("'"&$C300&"'!"&L$2&MATCH($D300,INDIRECT("'"&$C300&"'!$A:$A"),0))} -> 18 | M300: {=INDIRECT("'"&$C300&"'!"&M$2&MATCH($D300,INDIRECT("'"&$C300&"'!$A:$A"),0))} -> 1275 | N300: {=INDIRECT("'"&$C300&"'!"&N$2&MATCH($D300,INDIRECT("'"&$C300&"'!$A:$A"),0))} -> 0.88923
B301: V9 Zero Shot Gemini 3.1 Pro | C301: ZS9-Full-Gemini3.1-pro-27.05.26 | D301: unfair_binary | E301: {=INDIRECT("'"&$C301&"'!"&E$2&MATCH($D301,INDIRECT("'"&$C301&"'!$A:$A"),0))} -> 0.57509 | F301: {=INDIRECT("'"&$C301&"'!"&F$2&MATCH($D301,INDIRECT("'"&$C301&"'!$A:$A"),0))} -> 0.91279 | G301: {=INDIRECT("'"&$C301&"'!"&G$2&MATCH($D301,INDIRECT("'"&$C301&"'!$A:$A"),0))} -> 0.70562 | J301: {=INDIRECT("'"&$C301&"'!"&J$2&MATCH($D301,INDIRECT("'"&$C301&"'!$A:$A"),0))} -> 157 | K301: {=INDIRECT("'"&$C301&"'!"&K$2&MATCH($D301,INDIRECT("'"&$C301&"'!$A:$A"),0))} -> 116 | L301: {=INDIRECT("'"&$C301&"'!"&L$2&MATCH($D301,INDIRECT("'"&$C301&"'!$A:$A"),0))} -> 15 | M301: {=INDIRECT("'"&$C301&"'!"&M$2&MATCH($D301,INDIRECT("'"&$C301&"'!$A:$A"),0))} -> 1319 | N301: {=INDIRECT("'"&$C301&"'!"&N$2&MATCH($D301,INDIRECT("'"&$C301&"'!$A:$A"),0))} -> 0.91848
... B312: V8 Few Shot Gemini 2.5 Flash | C312: FS8-Full-Gemini-2.5-flash-27.05 | D312: unfair_binary | E312: {=INDIRECT("'"&$C312&"'!"&E$2&MATCH($D312,INDIRECT("'"&$C312&"'!$A:$A"),0))} -> 0.51803 | F312: {=INDIRECT("'"&$C312&"'!"&F$2&MATCH($D312,INDIRECT("'"&$C312&"'!$A:$A"),0))} -> 0.9186 | G312: {=INDIRECT("'"&$C312&"'!"&G$2&MATCH($D312,INDIRECT("'"&$C312&"'!$A:$A"),0))} -> 0.66247 | J312: {=INDIRECT("'"&$C312&"'!"&J$2&MATCH($D312,INDIRECT("'"&$C312&"'!$A:$A"),0))} -> 158 | K312: {=INDIRECT("'"&$C312&"'!"&K$2&MATCH($D312,INDIRECT("'"&$C312&"'!$A:$A"),0))} -> 147 | L312: {=INDIRECT("'"&$C312&"'!"&L$2&MATCH($D312,INDIRECT("'"&$C312&"'!$A:$A"),0))} -> 14 | M312: {=INDIRECT("'"&$C312&"'!"&M$2&MATCH($D312,INDIRECT("'"&$C312&"'!$A:$A"),0))} -> 1288 | N312: {=INDIRECT("'"&$C312&"'!"&N$2&MATCH($D312,INDIRECT("'"&$C312&"'!$A:$A"),0))} -> 0.89981

Sheet Prompts
A1: ZS1 | B1: ZS2 | C1: ZS3 | D1: ZS4 | E1: ZS5 | F1: ZS6 | G1: ZS7 | H1: FS1 (ZS1) | I1: FS3 (ZS1) | J1: FS4 (ZS3)
A2: ## ROLE | B2: ## ROLE | C2: ## ROLE | D2: ## ROLE | E2: ## ROLE | F2: ## ROLE | G2: ## ROLE | H2: ## ROLE | I2: # ROLE | J2: ## ROLE
A3: You are a legal expert specializing in European Consumer Law, specifically Directive 93/13/EEC. Your task is to analyze Terms of Service (TOS) clauses for "significant imbalances" between the rights and obligations of the parties. | B3: You are a legal expert specializing in European Consumer Law, specifically Directive 93/13/EEC. Your task is to analyze Terms of Service (TOS) clauses for "significant imbalances" between the rights and obligations of the parties. | C3: You are a legal expert specializing in European Consumer Law, specifically Directive (EU) 93/13/ECC . Your task is to analyze Terms of Service (TOS) clauses for "significant imbalances" between the rights and obligations of the parties. | D3: You are a legal expert specializing in European Consumer Law, with a focus on Directive (EU) 2019/2161 . Your primary objective is to evaluate whether Terms of Service (TOS) clauses create a "significant imbalance" between the rights of the service provider (provider) and the obligations of the consumer. | E3: You are a legal expert specializing in European Consumer Law, specifically Directive (EU) 93/13/ECC . Your task is to analyze Terms of Service (TOS) clauses for "significant imbalances" between the rights and obligations of the parties. | F3: You are a legal expert specializing in European Consumer Law, specifically Directive (EU) 93/13/ECC . Your task is to analyze Terms of Service (TOS) clauses for "significant imbalances" between the rights and obligations of the parties. | G3: You are a legal expert specializing in European Consumer Law, specifically Directive (EU) 93/13/ECC . Your task is to analyze Terms of Service (TOS) clauses for "significant imbalances" between the rights and obligations of the parties. | H3: You are a legal expert specializing in European Consumer Law, specifically Directive 93/13/EEC. Your task is to analyze Terms of Service (TOS) clauses for "significant imbalances" between the rights and obligations of the parties. | I3: You are a legal expert specializing in European Consumer Law, specifically Directive 93/13/EEC. Your task is to analyze Terms of Service (TOS) clauses for "significant imbalances" between the rights and obligations of the parties. | J3: You are a legal expert specializing in European Consumer Law, specifically Directive (EU) 93/13/ECC . Your task is to analyze Terms of Service (TOS) clauses for "significant imbalances" between the rights and obligations of the parties.
A5: ## Task: | B5: ## Task: | C5: ## Task: | D5: ## Task: | E5: ## Task: | F5: ## Task: | G5: ## Task: | H5: ## Task: | I5: ## Task: | J5: ## Task:
A6: Analyze the provided Terms of Service (TOS) clause: | B6: Analyze the provided Terms of Service (TOS) clause: | C6: Analyze the provided Terms of Service (TOS) clause: | D6: Analyze the provided Terms of Service (TOS) clause to determine if it maintains a fair equilibrium or is unfair: | E6: Analyze the provided Terms of Service (TOS) clause: | F6: Analyze the provided Terms of Service (TOS) clause: | G6: Analyze the provided Terms of Service (TOS) clause: | H6: Analyze the provided Terms of Service (TOS) clause: | I6: Analyze the provided Terms of Service (TOS) clause: | J6: Analyze the provided Terms of Service (TOS) clause:
A7: - If the clause is balanced and legally sound, label it **[8]**. | B7: - If the clause is balanced and legally sound, label it **[8]**. | C7: - If the clause is balanced and legally sound, label it **[8]**. | D7: - If the clause is unfair, label ALL applicable categories of unfairness from **[0-7]**. | E7: - If the clause is balanced and legally sound, label it **[8]**. | F7: - If the clause is unfair, identify ALL applicable categories from **[0-7]**. | G7: - If the clause is unfair, identify ALL applicable categories from **[0-7]**. | H7: - If the clause is balanced and legally sound, label it **[8]**. | I7: - If the clause is balanced and legally sound, label it **[8]**. | J7: - If the clause is balanced and legally sound, label it **[8]**.
A8: - If the clause is unfair, identify ALL applicable categories from **[0-7]**. | B8: - If the clause is unfair, identify ALL applicable categories from **[0-7]**. | C8: - If the clause is unfair, identify ALL applicable categories from **[0-7]**. | D8: - If the clause is fair, balanced and preserves the consumer's legal standing and contains no categories of unfairness 0-7, label it **[8]**. | E8: - If the clause is unfair, identify ALL applicable categories from **[0-7]**. | F8: - If the clause is fair, label it **[8]**. | G8: - If the clause is balanced, fair and legally sound, label it **[8]**. | H8: - If the clause is unfair, identify ALL applicable categories from **[0-7]**. | I8: - If the clause is unfair, identify ALL applicable categories from **[0-7]**. | J8: - If the clause is unfair, identify ALL applicable categories from **[0-7]**.
A9: - **Important**: If any category from 0-7 applies, do NOT include [8] in the label. | B9: - **Important**: If any category from 0-7 applies, do NOT include [8] in the label. | C9: - **Important**: If any category from 0-7 applies, do NOT include [8] in the label. | E9: - **Important**: If any category from 0-7 applies, do NOT include [8] in the label. | F9: - **Important**: If any category from 0-7 applies, do NOT include [8] in the label. | G9: - **Important**: If any category from 0-7 applies, do NOT include [8] in the label. | H9: - **Important**: If any category from 0-7 applies, do NOT include [8] in the label. | I9: - **Important**: If any category from 0-7 applies, do NOT include [8] in the label. | J9: - **Important**: If any category from 0-7 applies, do NOT include [8] in the label.
A11: ## LEGAL CATEGORIES & CRITERIA | B11: -------------------------------------------------------------------------------------------------------------------------------------------------------------------------- | C11: ## LEGAL CATEGORIES & CRITERIA | D11: ## FAIRNESS VS. UNFAIRNESS CRITERIA The following is a list of categories with the detail of what is considered Unfair and Fair. | E11: ## LEGAL CATEGORIES & CRITERIA | F11: ## LEGAL CATEGORIES & CRITERIA | G11: ## LEGAL CATEGORIES & CRITERIA | H11: ## LEGAL CATEGORIES & CRITERIA | I11: ## LEGAL CATEGORIES & CRITERIA | J11: ## LEGAL CATEGORIES & CRITERIA
A12: ### **0-Limitation of Liability:** Covers clauses excluding or restricting a seller's legal liability for non-performance or injury, which is unfair when it creates a significant imbalance by stripping consumers of compensation rights for death or gross negligence, but remains fair if it is transparent, proportional, and explicitly protects mandatory statutory rights. | C12: ### **0-Limitation of Liability:** Covers clauses excluding or restricting a seller's legal liability for non-performance or injury, which is unfair when it creates a significant imbalance by stripping consumers of compensation rights for death or gross negligence, but remains fair if it is transparent, proportional, and explicitly protects mandatory statutory rights. Do not assign [0] for warranty language (for example, "as is" or "no warranty") or third-party resource disclaimers unless the clause also expressly excludes or caps the provider's liability for user damages, losses, or compensation. | D12: ### **0. Limitation of Liability** Unfair: Excludes or restricts provider liability for non-performance, personal injury, or gross negligence. Fair: Clauses that are transparent, proportional, and explicitly protect the consumer's mandatory statutory rights. | E12: ### **0. Limitation of Liability** Unfair: Excludes or restricts provider liability for non-performance, personal injury, or gross negligence. Fair: Clauses that are transparent, proportional, and explicitly protect the consumer's mandatory statutory rights. | F12: ### **0-Limitation of Liability** - Definition: Provider liability to user is limited - Unfair: Excludes or restricts provider liability for non-performance, personal injury, death, or gross negligence when it creates a significant imbalance by stripping consumers of compensation rights. - Fair: Clauses that are transparent, proportional, and explicitly protect the consumer's mandatory statutory rights. - Note: Do not assign [0] for warranty language (for example, "as is" or "no warranty") or third-party resource disclaimers unless the clause also expressly excludes or caps the provider's liability for user damages, losses, or compensation. | G12: ### **0.Limitation of Liability** - Definition: Provider liability to user is limited - Unfair: Excludes or restricts provider liability for non-performance, personal injury, death, or gross negligence when it creates a significant imbalance by stripping consumers of compensation rights. - Fair: Clauses that are transparent, proportional, and explicitly protect the consumer's mandatory statutory rights. - Note: Do not assign [0] for warranty language (for example, "as is" or "no warranty") or third-party resource disclaimers unless the clause also expressly excludes or caps the provider's liability for user damages, losses, or compensation. | H12: ### **0-Limitation of Liability:** Covers clauses excluding or restricting a seller's legal liability for non-performance or injury, which is unfair when it creates a significant imbalance by stripping consumers of compensation rights for death or gross negligence, but remains fair if it is transparent, proportional, and explicitly protects mandatory statutory rights. | I12: ### **0-Limitation of Liability:** Covers clauses excluding or restricting a seller's legal liability for non-performance or injury, which is unfair when it creates a significant imbalance by stripping consumers of compensation rights for death or gross negligence, but remains fair if it is transparent, proportional, and explicitly protects mandatory statutory rights. Do not assign [0] for warranty language (for example, "as is" or "no warranty") or third-party resource disclaimers unless the clause also expressly excludes or caps the provider's liability for user damages, losses, or compensation. | J12: ### **0-Limitation of Liability:** Covers clauses excluding or restricting a seller's legal liability for non-performance or injury, which is unfair when it creates a significant imbalance by stripping consumers of compensation rights for death or gross negligence, but remains fair if it is transparent, proportional, and explicitly protects mandatory statutory rights. Do not assign [0] for warranty language (for example, "as is" or "no warranty") or third-party resource disclaimers unless the clause also expressly excludes or caps the provider's liability for user damages, losses, or compensation.
B13: ## LEGAL CATEGORIES & DEFINITIONS
A14: ### **1-Unilateral Termination:** Involves terms allowing a seller to dissolve the contract at will, which is considered unfair when it lacks reasonable notice or reciprocal rights for the consumer, but can be fair if the contract specifies objective grounds for termination and provides a sufficient notice period. | B14: ### **0-Limitation of Liability:** | C14: ### **1-Unilateral Termination:** Involves terms allowing a seller to dissolve the contract at will, which is considered unfair when it lacks reasonable notice or reciprocal rights for the consumer, but can be fair if the contract specifies objective grounds for termination and provides a sufficient notice period. Clauses that let the provider terminate or restrict access unilaterally are generally [1], even when tied to alleged misuse or policy violations, unless balanced safeguards are explicit. | D14: ### **1. Unilateral Termination** Definition: Terms allowing the provider to dissolve the contract at will. Unfair: Allowing the provider to dissolve the contract "at will" or without reasonable notice or reciprocal rights for the consumer. Fair: Specifying objective grounds for termination and providing a sufficient notice period for the consumer to react. | E14: ### **1. Unilateral Termination** Definition: Terms allowing the provider to dissolve the contract at will. Unfair: Allowing the provider to dissolve the contract "at will" or without reasonable notice or reciprocal rights for the consumer. Fair: Specifying objective grounds for termination and providing a sufficient notice period for the consumer to react. | F14: ### **1-Unilateral Termination** Definition: Terms allowing the provider to dissolve the contract at will. Unfair: Termination with no notice or insufficient notice or where reciprocal rights are not provided for the consumer, even if the user has violated the agreement. Fair: Specifying objective grounds for termination and providing a sufficient notice period. | G14: ### **1.Unilateral Termination** Definition: Terms allowing the provider to dissolve the contract at will. Unfair: Termination with no notice or insufficient notice or where reciprocal rights are not provided for the consumer, even if the user has violated the agreement. Fair: Specifying objective grounds for termination and providing a sufficient notice period. | H14: ### **1-Unilateral Termination:** Involves terms allowing a seller to dissolve the contract at will, which is considered unfair when it lacks reasonable notice or reciprocal rights for the consumer, but can be fair if the contract specifies objective grounds for termination and provides a sufficient notice period. | I14: ### **1-Unilateral Termination:** Involves terms allowing a seller to dissolve the contract at will, which is considered unfair when it lacks reasonable notice or reciprocal rights for the consumer, but can be fair if the contract specifies objective grounds for termination and provides a sufficient notice period. Clauses that let the provider terminate or restrict access unilaterally are generally [1], even when tied to alleged misuse or policy violations, unless balanced safeguards are explicit. | J14: ### **1-Unilateral Termination:** Involves terms allowing a seller to dissolve the contract at will, which is considered unfair when it lacks reasonable notice or reciprocal rights for the consumer, but can be fair if the contract specifies objective grounds for termination and provides a sufficient notice period. Clauses that let the provider terminate or restrict access unilaterally are generally [1], even when tied to alleged misuse or policy violations, unless balanced safeguards are explicit.
B15: **Definition**: In the context of a consumer service contract, a **Limitation of Liability** clause is a legal provision that seeks to restrict the amount and types of compensation (damages) a consumer can recover from a service provider in the event of a breach of contract, negligence, or other legal failures. While some limitations are standard, they become "unfair" when they create a significant imbalance in the rights and obligations of the parties to the detriment of the consumer.
A16: ### **2-Unilateral Change:** Identifies provisions enabling the seller to alter contract terms or prices without consent, which is unfair if it lacks a valid, pre-specified reason, but is considered fair if the seller provides advance notice, a valid justification, and the right for the consumer to terminate the contract immediately without penalty. | C16: ### **2-Unilateral Change:** Identifies provisions enabling the seller to alter contract terms or prices without consent, which is unfair if it lacks a valid, pre-specified reason, but is considered fair if the seller provides advance notice, a valid justification, and the right for the consumer to terminate the contract immediately without penalty. Notice alone does not automatically make a unilateral-change clause [8] in this dataset. | D16: ### **2. Unilateral Change** Unfair: Altering terms or prices without a valid, pre-specified reason or the consumer's consent. Fair: Providing advance notice, valid justification, and the right for the consumer to terminate the contract immediately without penalty. | E16: ### **2. Unilateral Change** Unfair: Altering terms or prices without a valid, pre-specified reason or the consumer's consent. Fair: Providing advance notice, valid justification, and the right for the consumer to terminate the contract immediately without penalty. | F16: ### **2-Unilateral Change** Unfair: Altering terms or prices without a valid, pre-specified reason or the consumer's consent. Fair: Providing advance notice, valid justification, and the right for the consumer to terminate the contract immediately without penalty. | G16: ### **2.Unilateral Change** Unfair: Altering terms or prices without a valid, pre-specified reason or the consumer's consent. Fair: Providing advance notice, valid justification, and the right for the consumer to terminate the contract immediately without penalty. | H16: ### **2-Unilateral Change:** Identifies provisions enabling the seller to alter contract terms or prices without consent, which is unfair if it lacks a valid, pre-specified reason, but is considered fair if the seller provides advance notice, a valid justification, and the right for the consumer to terminate the contract immediately without penalty. | I16: ### **2-Unilateral Change:** Identifies provisions enabling the seller to alter contract terms or prices without consent, which is unfair if it lacks a valid, pre-specified reason, but is considered fair if the seller provides advance notice, a valid justification, and the right for the consumer to terminate the contract immediately without penalty. Notice alone does not automatically make a unilateral-change clause [8] in this dataset. | J16: ### **2-Unilateral Change:** Identifies provisions enabling the seller to alter contract terms or prices without consent, which is unfair if it lacks a valid, pre-specified reason, but is considered fair if the seller provides advance notice, a valid justification, and the right for the consumer to terminate the contract immediately without penalty. Notice alone does not automatically make a unilateral-change clause [8] in this dataset.
B17: **Characteristics**:
A18: ### **3-Content Removal:** Identifies clauses that grant the provider the right to delete, hide, or restrict access to content uploaded by the user. Such terms are classified as unfair when they allow for arbitrary removal without a specified valid reason or notice, as this creates a significant imbalance in the rights of the parties. To be considered fair, the term must be transparent and specify objective grounds for removal, ensuring the consumer is provided with a clear legal rationale for the provider's actions and accompanied by a notification and appeal process. | B18: - **Broad and Blanket Exclusions**: The clause attempts to exclude liability for any loss or damage "howsoever arising," effectively stripping the consumer of any legal recourse regardless of the provider's level of fault. | C18: ### **3-Content Removal:** Identifies clauses that grant the provider the right to delete, hide, or restrict access to content uploaded by the user. Such terms are classified as unfair when they allow for arbitrary removal without a specified valid reason or notice, as this creates a significant imbalance in the rights of the parties. To be considered fair, the term must be transparent and specify objective grounds for removal, ensuring the consumer is provided with a clear legal rationale for the provider's actions and accompanied by a notification and appeal process. | D18: ### **3. Content Removal** Unfair: Granting the provider arbitrary rights to delete or hide user content without a clear reason or notice. Fair: Specifying objective grounds for removal and offering a transparent notification and appeal process. | E18: ### **3. Content Removal** Unfair: Granting the provider arbitrary rights to delete or hide user content without a clear reason or notice. Fair: Specifying objective grounds for removal and offering a transparent notification and appeal process. | F18: ### **3-Content Removal** Unfair: Granting the provider arbitrary rights to delete or hide user content without a clear reason or notice. Fair: Specifying objective grounds for removal and offering a transparent notification and appeal process. | G18: ### **3.Content Removal** Unfair: Granting the provider arbitrary rights to delete or hide user content without a clear reason or notice. Fair: Specifying objective grounds for removal and offering a transparent notification and appeal process. | H18: ### **3-Content Removal:** Identifies clauses that grant the provider the right to delete, hide, or restrict access to content uploaded by the user. Such terms are classified as unfair when they allow for arbitrary removal without a specified valid reason or notice, as this creates a significant imbalance in the rights of the parties. To be considered fair, the term must be transparent and specify objective grounds for removal, ensuring the consumer is provided with a clear legal rationale for the provider's actions and accompanied by a notification and appeal process. | I18: ### **3-Content Removal:** Identifies clauses that grant the provider the right to delete, hide, or restrict access to content uploaded by the user. Such terms are classified as unfair when they allow for arbitrary removal without a specified valid reason or notice, as this creates a significant imbalance in the rights of the parties. To be considered fair, the term must be transparent and specify objective grounds for removal, ensuring the consumer is provided with a clear legal rationale for the provider's actions and accompanied by a notification and appeal process. | J18: ### **3-Content Removal:** Identifies clauses that grant the provider the right to delete, hide, or restrict access to content uploaded by the user. Such terms are classified as unfair when they allow for arbitrary removal without a specified valid reason or notice, as this creates a significant imbalance in the rights of the parties. To be considered fair, the term must be transparent and specify objective grounds for removal, ensuring the consumer is provided with a clear legal rationale for the provider's actions and accompanied by a notification and appeal process.
B19: - **Arbitrary or Insignificant Liability Caps**: The provider limits their total financial responsibility to an incredibly low or arbitrary sum (such as $100 or the price of a single order) that does not reflect the actual harm a consumer might suffer.
A20: ### **4-Contract by Using:** Identifies 'browse-wrap' provisions where the mere use is deemed acceptance of terms, which is unfair under Directive 93/13/EEC as it creates a significant imbalance by binding consumers without informed consent or a genuine opportunity to review the obligations, but it becomes fair when acceptance is conditioned on a clear, affirmative action—like a 'click-wrap' agreement—performed after the consumer has been presented with the terms in a transparent manner. | B20: - **Exclusion of Foreseeable Indirect Losses**: The terms bar consumers from seeking compensation for "consequential," "indirect," or "incidental" damages, such as the loss of data, personal reputation, or goodwill, even when these losses are a direct result of the provider's failure. | C20: ### **4-Contract by Using:** Identifies 'browse-wrap' provisions where the mere use is deemed acceptance of terms, which is unfair under Directive 93/13/EEC as it creates a significant imbalance by binding consumers without informed consent or a genuine opportunity to review the obligations, but it becomes fair when acceptance is conditioned on a clear, affirmative action—like a 'click-wrap' agreement—performed after the consumer has been presented with the terms in a transparent manner. If a clause gives a clear right to reject changes by stopping use or terminating without penalty, prefer [8] over [4]. | D20: ### **4. Contract by Using** Unfair: "Browse-wrap" agreements where mere use is deemed acceptance, binding consumers without informed consent. Fair: "Click-wrap" agreements where acceptance is an affirmative action taken after terms are clearly presented. | E20: ### **4. Contract by Using** Unfair: "Browse-wrap" agreements where mere use is deemed acceptance, binding consumers without informed consent. Fair: "Click-wrap" agreements where acceptance is an affirmative action taken after terms are clearly presented. | F20: ### **4-Contract by Using** Unfair: "Browse-wrap" agreements where mere use is deemed acceptance, binding consumers without informed consent. Fair: "Click-wrap" agreements where acceptance is an affirmative action taken after terms are clearly presented. | G20: ### **4-Contract by Using:** Identifies 'browse-wrap' provisions where the mere use is deemed acceptance of terms, which is unfair under Directive 93/13/EEC as it creates a significant imbalance by binding consumers without informed consent or a genuine opportunity to review the obligations, but it becomes fair when acceptance is conditioned on a clear, affirmative action—like a 'click-wrap' agreement—performed after the consumer has been presented with the terms in a transparent manner. | H20: ### **4-Contract by Using:** Identifies 'browse-wrap' provisions where the mere use is deemed acceptance of terms, which is unfair under Directive 93/13/EEC as it creates a significant imbalance by binding consumers without informed consent or a genuine opportunity to review the obligations, but it becomes fair when acceptance is conditioned on a clear, affirmative action—like a 'click-wrap' agreement—performed after the consumer has been presented with the terms in a transparent manner. | I20: ### **4-Contract by Using:** Identifies 'browse-wrap' provisions where the mere use is deemed acceptance of terms, which is unfair under Directive 93/13/EEC as it creates a significant imbalance by binding consumers without informed consent or a genuine opportunity to review the obligations, but it becomes fair when acceptance is conditioned on a clear, affirmative action—like a 'click-wrap' agreement—performed after the consumer has been presented with the terms in a transparent manner. If a clause gives a clear right to reject changes by stopping use or terminating without penalty, prefer [8] over [4]. | J20: ### **4-Contract by Using:** Identifies 'browse-wrap' provisions where the mere use is deemed acceptance of terms, which is unfair under Directive 93/13/EEC as it creates a significant imbalance by binding consumers without informed consent or a genuine opportunity to review the obligations, but it becomes fair when acceptance is conditioned on a clear, affirmative action—like a 'click-wrap' agreement—performed after the consumer has been presented with the terms in a transparent manner. If a clause gives a clear right to reject changes by stopping use or terminating without penalty, prefer [8] over [4].
B21: - **Disclaiming Responsibility for Third Parties**: The clause absolves the service provider of any liability for the conduct, errors, or omissions of third-party partners, advertisers, or other users, even if the provider facilitated those interactions.
A22: ### **5-Choice of Law:** Designates the legal system governing the contract, which is unfair if it selects a foreign law to deprive consumers of the mandatory protections of their home country, but is fair if it explicitly preserves the consumer's right to their local mandatory legal safeguards. | B22: - **No Accountability for Service Reliability**: The provider claims no responsibility for service interruptions, technical errors, inaccuracies, or the complete unavailability of the service, regardless of the cause or duration. | C22: ### **5-Choice of Law:** Designates the legal system governing the contract, which is unfair if it selects a foreign law to deprive consumers of the mandatory protections of their home country, but is fair if it explicitly preserves the consumer's right to their local mandatory legal safeguards. | D22: ### **5. Choice of Law** Unfair: Selecting a foreign legal system specifically to deprive consumers of their home country’s mandatory protections. Fair: Explicitly preserving the consumer’s right to rely on their local mandatory legal safeguards. | E22: ### **5. Choice of Law** Unfair: Selecting a foreign legal system specifically to deprive consumers of their home country’s mandatory protections. Fair: Explicitly preserving the consumer’s right to rely on their local mandatory legal safeguards. | F22: ### **5-Choice of Law** Unfair: Selecting a foreign legal system specifically to deprive consumers of their home country’s mandatory protections. Fair: Explicitly preserving the consumer’s right to rely on their local mandatory legal safeguards. | G22: ### **5-Choice of Law:** Designates the legal system governing the contract, which is unfair if it selects a foreign law to deprive consumers of the mandatory protections of their home country, but is fair if it explicitly preserves the consumer's right to their local mandatory legal safeguards. | H22: ### **5-Choice of Law:** Designates the legal system governing the contract, which is unfair if it selects a foreign law to deprive consumers of the mandatory protections of their home country, but is fair if it explicitly preserves the consumer's right to their local mandatory legal safeguards. | I22: ### **5-Choice of Law:** Designates the legal system governing the contract, which is unfair if it selects a foreign law to deprive consumers of the mandatory protections of their home country, but is fair if it explicitly preserves the consumer's right to their local mandatory legal safeguards. | J22: ### **5-Choice of Law:** Designates the legal system governing the contract, which is unfair if it selects a foreign law to deprive consumers of the mandatory protections of their home country, but is fair if it explicitly preserves the consumer's right to their local mandatory legal safeguards.
B23: - **Absolute Waiver of Refund Rights**: The terms state that the consumer is not entitled to a refund for any reason, including instances where the account is closed involuntarily or the service is not provided as promised.
A24: ### **6-Jurisdiction:** Specifies the court location for disputes, which is unfair if it forces consumers to litigate in a distant or inconvenient forum thereby hindering access to justice, but is fair if it allows the consumer to bring legal proceedings in the courts of their own domicile. | B24: - **Shielding Against Negligence**: The clause attempts to protect the provider from liability even in cases of their own negligence, "gross negligence," or "willful misconduct," which often exceeds what is legally permissible in consumer protection law. | C24: ### **6-Jurisdiction:** Specifies the court location for disputes, which is unfair if it forces consumers to litigate in a distant or inconvenient forum thereby hindering access to justice, but is fair if it allows the consumer to bring legal proceedings in the courts of their own domicile. | D24: ### **6. Jurisdiction** Unfair: Forcing consumers to litigate in a distant or inconvenient forum, effectively hindering their access to justice. Fair: Allowing the consumer to bring legal proceedings in the courts of their own domicile. | E24: ### **6. Jurisdiction** Unfair: Forcing consumers to litigate in a distant or inconvenient forum, effectively hindering their access to justice. Fair: Allowing the consumer to bring legal proceedings in the courts of their own domicile. | F24: ### **6-Jurisdiction** Unfair: Forcing consumers to litigate in a distant or inconvenient forum, effectively hindering their access to justice. Fair: Allowing the consumer to bring legal proceedings in the courts of their own domicile. | G24: ### **6-Jurisdiction:** Specifies the court location for disputes, which is unfair if it forces consumers to litigate in a distant or inconvenient forum thereby hindering access to justice, but is fair if it allows the consumer to bring legal proceedings in the courts of their own domicile. | H24: ### **6-Jurisdiction:** Specifies the court location for disputes, which is unfair if it forces consumers to litigate in a distant or inconvenient forum thereby hindering access to justice, but is fair if it allows the consumer to bring legal proceedings in the courts of their own domicile. | I24: ### **6-Jurisdiction:** Specifies the court location for disputes, which is unfair if it forces consumers to litigate in a distant or inconvenient forum thereby hindering access to justice, but is fair if it allows the consumer to bring legal proceedings in the courts of their own domicile. | J24: ### **6-Jurisdiction:** Specifies the court location for disputes, which is unfair if it forces consumers to litigate in a distant or inconvenient forum thereby hindering access to justice, but is fair if it allows the consumer to bring legal proceedings in the courts of their own domicile.
B25: - **Vague "Force Majeure" Overreach**: The provider uses events beyond their "reasonable control" as a blanket excuse to avoid liability for any failure to perform their core contractual obligations.
A26: ### **7-Arbitration:** Requires disputes to be settled via private arbitration, which is unfair if it is mandatory and binding—thereby hindering the consumer's right to legal action in court—but is fair if it is an optional, low-cost, and non-binding alternative that does not preclude judicial remedies. | C26: ### **7-Arbitration:** Requires disputes to be settled via private arbitration, which is unfair if it is mandatory and binding—thereby hindering the consumer's right to legal action in court—but is fair if it is an optional, low-cost, and non-binding alternative that does not preclude judicial remedies. If users can opt out or arbitration is not mandatory, prefer [8] over [7]. Also, arbitration procedural details alone (administrator, rules, venue mechanics, fee allocation, or FAA-governance wording) are [8] unless the clause imposes mandatory binding arbitration as the dispute forum. | D26: ### **7. Arbitration** Unfair: Imposing mandatory, binding arbitration that prevents the consumer from seeking remedies in a court of law. Fair: Offering arbitration as an optional, low-cost, and non-binding alternative. | E26: ### **7. Arbitration** Unfair: Imposing mandatory, binding arbitration that prevents the consumer from seeking remedies in a court of law. Fair: Offering arbitration as an optional, low-cost, and non-binding alternative. | F26: ### **7-Arbitration** Unfair: Imposing mandatory, binding arbitration that prevents the consumer from seeking remedies in a court of law. Fair: Offering arbitration as an optional, low-cost, and non-binding alternative. | G26: ### **7-Arbitration:** Requires disputes to be settled via private arbitration, which is unfair if it is mandatory and binding—thereby hindering the consumer's right to legal action in court—but is fair if it is an optional, low-cost, and non-binding alternative that does not preclude judicial remedies. If users can opt out or arbitration is not mandatory, prefer [8] over [7]. Also, arbitration procedural details alone (administrator, rules, venue mechanics, fee allocation, or FAA-governance wording) are [8] unless the clause imposes mandatory binding arbitration as the dispute forum. | H26: ### **7-Arbitration:** Requires disputes to be settled via private arbitration, which is unfair if it is mandatory and binding—thereby hindering the consumer's right to legal action in court—but is fair if it is an optional, low-cost, and non-binding alternative that does not preclude judicial remedies. | I26: ### **7-Arbitration:** Requires disputes to be settled via private arbitration, which is unfair if it is mandatory and binding—thereby hindering the consumer's right to legal action in court—but is fair if it is an optional, low-cost, and non-binding alternative that does not preclude judicial remedies. If users can opt out or arbitration is not mandatory, prefer [8] over [7]. Also, arbitration procedural details alone (administrator, rules, venue mechanics, fee allocation, or FAA-governance wording) are [8] unless the clause imposes mandatory binding arbitration as the dispute forum. | J26: ### **7-Arbitration:** Requires disputes to be settled via private arbitration, which is unfair if it is mandatory and binding—thereby hindering the consumer's right to legal action in court—but is fair if it is an optional, low-cost, and non-binding alternative that does not preclude judicial remedies. If users can opt out or arbitration is not mandatory, prefer [8] over [7]. Also, arbitration procedural details alone (administrator, rules, venue mechanics, fee allocation, or FAA-governance wording) are [8] unless the clause imposes mandatory binding arbitration as the dispute forum.
B27: ### **1-Unilateral Termination:**
A28: ### **8-Fair:** This category is a catch-all for any clause that is balanced, transparent, and does not meet the criteria for any of the unfair categories (0–7). Use this label only if no unfair elements are present. | B28: **Definition**: In the context of a consumer service contract, **Unilateral Termination** refers to a contractual provision that grants the service provider the right to end the agreement or discontinue services to a user without the user's mutual consent. While such clauses are common, they become problematic when they allow the provider to sever the relationship arbitrarily, without sufficient justification, or without following a fair process. | C28: ### **8-Fair:** This category is a catch-all for any clause that is balanced, transparent, and does not meet the criteria for any of the unfair categories (0–7). Use this label only if no unfair elements are present. | E28: ### **8-Fair:** This category is a catch-all for any clause that is balanced, transparent, and does not meet the criteria for any of the unfair categories (0–7). Use this label only if no unfair elements are present. | F28: ### **8-Fair:** This category is a catch-all for any clause that is balanced, transparent, and does not meet the criteria for any of the unfair categories (0–7). Use this label only if no unfair elements are present. | G28: ### **8.Fair:** This category is a catch-all for any clause that is balanced, transparent, and does not meet the criteria for any of the unfair categories (0–7). Use this label only if no unfair elements are present. | H28: ### **8-Fair:** This category is a catch-all for any clause that is balanced, transparent, and does not meet the criteria for any of the unfair categories (0–7). Use this label only if no unfair elements are present. | I28: ### **8-Fair:** This category is a catch-all for any clause that is balanced, transparent, and does not meet the criteria for any of the unfair categories (0–7). Use this label only if no unfair elements are present. | J28: ### **8-Fair:** This category is a catch-all for any clause that is balanced, transparent, and does not meet the criteria for any of the unfair categories (0–7). Use this label only if no unfair elements are present.
A30: ------------------------------------------------------------------------------------------ | B30: **Characteristics**: | C30: ------------------------------------------------------------------------------------------ | D30: ------------------------------------------------------------------------------------------ | E30: ------------------------------------------------------------------------------------------ | F30: ------------------------------------------------------------------------------------------ | G30: ------------------------------------------------------------------------------------------ | H30: ------------------------------------------------------------------------------------------ | I30: ------------------------------------------------------------------------------------------ | J30: ------------------------------------------------------------------------------------------
B31: - **Absence of Prior Notice**: The clause allows the service provider to terminate the user's account or access "immediately" or "without notice," leaving the consumer with no time to mitigate losses or retrieve personal data.
A32: ## OUTPUT INSTRUCTIONS | B32: - **Unfettered and Sole Discretion**: The provider reserves the "sole discretion" to terminate the contract for "any reason" or "no reason at all," creating a significant power imbalance where the user has no contractual security. | C32: ## OUTPUT INSTRUCTIONS | D32: ## OUTPUT INSTRUCTIONS | E32: ## OUTPUT INSTRUCTIONS | F32: ## OUTPUT INSTRUCTIONS | G32: ## OUTPUT INSTRUCTIONS | H32: ## EXAMPLES | I32: ## EXAMPLES | J32: ## EXAMPLES
A33: {=- Return ONLY valid JSON.} -> #NAME? | B33: - **Vague or Subjective Grounds**: Termination is based on broad or ill-defined criteria, such as "misusing" the service, behaving "inappropriately," or violating the "spirit" of the agreement, which are all open to the provider's subjective interpretation. | C33: - Return ONLY valid JSON. | D33: - Return ONLY valid JSON. | E33: - Return ONLY valid JSON. | F33: - Return ONLY valid JSON. | G33: - Return ONLY valid JSON. | H33: Input: "tinder shall have no liability to you or any third party in the event that tinder exercises any such rights ." | I33: Input: "tinder shall have no liability to you or any third party in the event that tinder exercises any such rights ." | J33: Input: "tinder shall have no liability to you or any third party in the event that tinder exercises any such rights ."
A34: - No conversational filler or markdown formatting outside the JSON. | B34: - **Lack of a Refund Mechanism**: The provider asserts the right to terminate the account without providing a refund for pre-paid services, active subscriptions, or digital purchases made by the user. | C34: - No conversational filler or markdown formatting outside the JSON. | D34: - No conversational filler or markdown formatting outside the JSON. | E34: - No conversational filler or markdown formatting outside the JSON. | F34: - No conversational filler or markdown formatting outside the JSON. | G34: - No conversational filler or markdown formatting outside the JSON. | H34: Output: {"label": "[0]"} | I34: Output: {"label": "[0]"} | J34: Output: {"label": "[0]"}
A35: - Field "label": Respond ONLY with the exact number(s) in brackets, (e.g., [8] for fair, or [1, 6] if multiple unfair categories apply). | B35: - **No Opportunity to Remedy a Breach**: The clause permits permanent termination for a first-time or minor infraction without giving the user a chance to explain the situation or correct the behavior. | C35: - Field "label": Respond ONLY with the exact number(s) in brackets, (e.g., [8] for fair, or [1, 6] if multiple unfair categories apply). | D35: - Field "label": Respond ONLY with the exact number(s) in brackets, (e.g., [8] for fair, or [1, 6] if multiple unfair categories apply). | E35: - Field "label": Respond ONLY with the exact number(s) in brackets, (e.g., [8] for fair, or [1, 6] if multiple unfair categories apply). | F35: - Field "label": Respond ONLY with the exact number(s) in brackets, (e.g., [8] for fair, or [1, 6] if multiple unfair categories apply). | G35: - Field "label": Respond ONLY with the exact number(s) in brackets, (e.g., [8] for fair, or [1, 6] if multiple unfair categories apply).
A36: - Field "legal_rationale": A single, concise sentence explaining the legal reasoning for the classification (e.g., citing the specific imbalance for 0-7, or the presence of balanced protections for 8). | B36: - **Termination for Commercial Viability**: The provider reserves the right to stop providing the service simply because it is "no longer commercially viable," effectively allowing them to escape their obligations to existing customers for purely financial reasons. | C36: - Field "legal_rationale": A single, concise sentence explaining the legal reasoning for the classification (e.g., citing the specific imbalance for 0-7, or the presence of balanced protections for 8). | D36: - Field "legal_rationale": A single, concise sentence explaining the legal reasoning for the classification (e.g., citing the specific imbalance for 0-7, or the presence of balanced protections for 8). | E36: - Field "legal_rationale": A single, concise sentence explaining the legal reasoning for the classification (e.g., citing the specific imbalance for 0-7, or the presence of balanced protections for 8). | F36: - Field "legal_rationale": A single, concise sentence explaining the legal reasoning for the classification (e.g., citing the specific imbalance for 0-7, or the presence of balanced protections for 8). | G36: - Field "legal_rationale": A single, concise sentence explaining the legal reasoning for the classification (e.g., citing the specific imbalance for 0-7, or the presence of balanced protections for 8). | H36: Input: "tinder may terminate your account at any time without notice if it believes that you have violated this agreement ." | I36: Input: "tinder may terminate your account at any time without notice if it believes that you have violated this agreement ." | J36: Input: "tinder may terminate your account at any time without notice if it believes that you have violated this agreement ."
A37: - Example: `{"label": "[2]", "legal_rationale": "The clause allows for price increases without providing a valid reason or the right to terminate."}` | B37: - **Arbitrary Inactivity Rules**: The clause allows for the termination of "dormant" accounts based on periods of inactivity that may not be clearly defined or communicated to the user in advance. | C37: - Example: `{"label": "[2]", "legal_rationale": "The clause allows for price increases without providing a valid reason or the right to terminate."}` | D37: - Example: `{"label": "[2]", "legal_rationale": "The clause allows for price increases without providing a valid reason or the right to terminate."}` | E37: - Example: `{"label": "[2]", "legal_rationale": "The clause allows for price increases without providing a valid reason or the right to terminate."}` | F37: - Example: `{"label": "[2]", "legal_rationale": "The clause allows for price increases without providing a valid reason or the right to terminate."}` | G37: - Example: `{"label": "[2]", "legal_rationale": "The clause allows for price increases without providing a valid reason or the right to terminate."}` | H37: Output: {"label": "[1]"} | I37: Output: {"label": "[1]"} | J37: Output: {"label": "[1]"}
B38: - **Disproportionate Responses to Conduct**: The provider claims the right to terminate an account based on actions occurring "off the service" or for behavior toward employees that is subjectively deemed "offensive," without providing a transparent standard for such judgments.
H39: Input: "we may make changes to this agreement and to the services from time to time ." | I39: Input: "the company may investigate and take any available legal action in response to illegal and / or unauthorized uses of the service , including termination of your account ." | J39: Input: "the company may investigate and take any available legal action in response to illegal and / or unauthorized uses of the service , including termination of your account ."
B40: ### **2-Unilateral Change:** | H40: Output: {"label": "[2]"} | I40: Output: {"label": "[1]"} | J40: Output: {"label": "[1]"}
B41: **Definition**: In a consumer service contract, a **Unilateral Change** (also known as a unilateral modification) is a contractual provision that allows one party?typically the service provider?to change the terms of the agreement, the price, or the nature of the services offered without requiring the contemporaneous agreement or signature of the other party (the consumer). In these arrangements, the provider reserves the right to modify the "rules of the game" after the initial contract has already been formed.
H42: Input: "we may delete any content , in whole or in part , that in our sole judgment violates this agreement or may harm the reputation of the service ." | I42: Input: "we may make changes to this agreement and to the services from time to time ." | J42: Input: "we may make changes to this agreement and to the services from time to time ."
B43: **Characteristics**: | H43: Output: {"label": "[3]"} | I43: Output: {"label": "[2]"} | J43: Output: {"label": "[2]"}
B44: - **Shifting the Burden of Monitoring**: The clause places the responsibility on the consumer to "regularly check" a website or app for updates, rather than the provider taking the initiative to notify the consumer directly of changes.
B45: - **Absolute and Unfettered Discretion**: The provider reserves the right to make changes at its "sole discretion" or "as it sees fit," without any objective criteria or limitations on what can be changed. | H45: Input: "if you continue to use the services after the changes become effective , then you agree to the revised agreement ." | I45: Input: "we may delete any content , in whole or in part , that in our sole judgment violates this agreement or may harm the reputation of the service ." | J45: Input: "we may delete any content , in whole or in part , that in our sole judgment violates this agreement or may harm the reputation of the service ."
B46: - **Lack of Specific Notice Periods**: Changes are often stated to take effect "from time to time" or "at any time," providing no minimum lead time for the consumer to adjust to the new terms before they become binding. | H46: Output: {"label": "[4]"} | I46: Output: {"label": "[3]"} | J46: Output: {"label": "[3]"}
B47: - **Immediate Binding Effect**: The clause stipulates that mere continued use of the service after a change is posted constitutes acceptance, effectively forcing a "take-it-or-leave-it" scenario where the consumer's silence is treated as consent.
B48: - **No Right to Terminate without Penalty**: These clauses frequently fail to offer the consumer a clear path to cancel the contract without fees or penalties if they do not agree to the new, modified terms. | H48: Input: "this policy and consent forms part of our website terms of use and as such it shall be governed by and construed in accordance with the laws of england and wales ." | I48: Input: "if you continue to use the services after the changes become effective , then you agree to the revised agreement ." | J48: Input: "if you continue to use the services after the changes become effective , then you agree to the revised agreement ."
B49: - **Vulnerability of Paid Features**: The provider grants itself the power to "eliminate," "modify," or "regulate" virtual items or paid services at any time, potentially stripping the consumer of the value they have already paid for. | H49: Output: {"label": "[5]"} | I49: Output: {"label": "[4]"} | J49: Output: {"label": "[4]"}
B50: - **Opaque Communication Methods**: The provider maintains the right to choose the method of notification "in its sole discretion," which may involve burying updates in obscure sections of a website rather than using direct electronic mail.
H51: Input: "you and youtube agree to submit to the exclusive jurisdiction of the courts of england to resolve any legal matter arising from the terms ." | I51: Input: "by creating a tinder account or by using the tinder imessage app ( `` tinder stacks '' ) , whether through a mobile device , mobile application or computer ( collectively , the `` service '' ) you agree to be bound by ( i ) these terms of use , ( ii ) our privacy policy and safety tips , each of which is incorporated by reference into this agreement , and ( iii ) any terms disclosed and agreed to by you if you purchase additional features , products or services we offer on the service ( collectively , this `` agreement '' ) ." | J51: Input: "by creating a tinder account or by using the tinder imessage app ( `` tinder stacks '' ) , whether through a mobile device , mobile application or computer ( collectively , the `` service '' ) you agree to be bound by ( i ) these terms of use , ( ii ) our privacy policy and safety tips , each of which is incorporated by reference into this agreement , and ( iii ) any terms disclosed and agreed to by you if you purchase additional features , products or services we offer on the service ( collectively , this `` agreement '' ) ."
B52: ### **3-Content Removal:** | H52: Output: {"label": "[6]"} | I52: Output: {"label": "[4]"} | J52: Output: {"label": "[4]"}
B53: **Definition**: In the context of a consumer service contract, **Content Removal** refers to the contractual right reserved by a service provider to delete, block, disable access to, or modify any information, media, or data uploaded by a user. This encompasses a wide range of "user-generated content," including photos, comments, messages, reviews, account profiles, and virtual items. These clauses establish the conditions under which a provider may unilaterally intervene to restrict the visibility or existence of a consumer's digital contributions on their platform.
H54: Input: "the exclusive means of resolving any dispute or claim arising out of or relating to this agreement ( including any alleged breach thereof ) or the service shall be binding arbitration administered by the american arbitration association under the consumer arbitration rules ." | I54: Input: "this policy and consent forms part of our website terms of use and as such it shall be governed by and construed in accordance with the laws of england and wales ." | J54: Input: "this policy and consent forms part of our website terms of use and as such it shall be governed by and construed in accordance with the laws of england and wales ."
B55: **Characteristics**: | H55: Output: {"label": "[7]"} | I55: Output: {"label": "[5]"} | J55: Output: {"label": "[5]"}
B56: - **The provider claims absolute and unfettered discretion**. Clauses are unfair when they allow the provider to remove content based on their "sole judgment," "absolute discretion," or "sole discretion," effectively removing any objective standard or requirement for proof of a violation.
B57: - **The grounds for removal are vague or subjective**. Unfairness arises when removal is permitted for content deemed "otherwise objectionable," "unacceptable," "inappropriate," or "harmful to the reputation of the service," as these terms are not clearly defined and are open to arbitrary interpretation. | H57: Input: "we may alter , suspend or discontinue any aspect of the service at any time , including the availability of any service feature , database or content ." | I57: Input: "you and youtube agree to submit to the exclusive jurisdiction of the courts of england to resolve any legal matter arising from the terms ." | J57: Input: "you and youtube agree to submit to the exclusive jurisdiction of the courts of england to resolve any legal matter arising from the terms ."
B58: - **Removal can occur without prior notice**. Clauses that permit the deletion or blocking of content "without notice" or "without prior notice" are unfair because they deprive the consumer of the chance to rectify an issue or save a copy of their data before it is lost. | H58: Output: {"label": "[1, 2]"} | I58: Output: {"label": "[6]"} | J58: Output: {"label": "[6]"}
B59: - **The provider is not required to provide a reason**. It is considered unfair when a contract states that content may be removed for "any reason" or "no reason at all," creating a significant imbalance where the consumer has no way to understand or challenge the action.
B60: - **The provider disclaims all responsibility for data loss**. Clauses are unfair if they state the provider has "no obligation to store or retain" user content and place the entire burden of data backup on the consumer, often while simultaneously making that data inaccessible. | H60: Input: "to the extent permitted by law , these terms and conditions and the provision of our services shall be governed by and construed in accordance with dutch law and any dispute arising out of these general terms and conditions and our services shall exclusively be submitted to the competent courts in amsterdam , the netherlands ." | I60: Input: "the exclusive means of resolving any dispute or claim arising out of or relating to this agreement ( including any alleged breach thereof ) or the service shall be binding arbitration administered by the american arbitration association under the consumer arbitration rules ." | J60: Input: "the exclusive means of resolving any dispute or claim arising out of or relating to this agreement ( including any alleged breach thereof ) or the service shall be binding arbitration administered by the american arbitration association under the consumer arbitration rules ."
B61: - **The right to modify content is overly broad**. An unfair clause grants the provider the power not just to remove, but to "edit," "modify," or "adjust" user-generated content (such as reviews or messages) at will, which can fundamentally change the meaning of the consumer's original contribution. | H61: Output: {"label": "[5, 6]"} | I61: Output: {"label": "[7]"} | J61: Output: {"label": "[7]"}
B62: - **User identifiers can be reclaimed arbitrarily**. Clauses that allow a provider to "reclaim" or "remove" a username or identifier at any time for any reason are unfair, as they ignore the personal or commercial value a user may have built around that identity.
B63: - **Access is terminated immediately upon account suspension**. It is unfair for a clause to dictate that all user content and files will be permanently deleted or made inaccessible immediately upon account termination without providing a grace period for data retrieval. | H63: Input: "unless we make a change for legal or administrative reasons , we will provide reasonable advance notice before the updated terms become effective ." | I63: Input: "we may alter , suspend or discontinue any aspect of the service at any time , including the availability of any service feature , database or content ." | J63: Input: "we may alter , suspend or discontinue any aspect of the service at any time , including the availability of any service feature , database or content ."
H64: Output: {"label": "[8]"} | I64: Output: {"label": "[1, 2]"} | J64: Output: {"label": "[1, 2]"}
B65: ### **4-Contract by Using:**
B66: **Definition**: In the context of consumer service contracts, a **Contract by Using** (often referred to as a "browse-wrap" agreement) is a legal arrangement where a consumer is deemed to have accepted the terms and conditions of a service simply by performing an action, such as accessing a website, downloading an app, or continuing to use a service after an update. Unlike "click-wrap" agreements, which require a user to check a box or click an "I Agree" button, a contract by using relies on inferred consent through behavior. | H66: Input: "if you do not agree to any modifications , you should terminate your use of the service ." | I66: Input: "to the extent permitted by law , these terms and conditions and the provision of our services shall be governed by and construed in accordance with dutch law and any dispute arising out of these general terms and conditions and our services shall exclusively be submitted to the competent courts in amsterdam , the netherlands ." | J66: Input: "to the extent permitted by law , these terms and conditions and the provision of our services shall be governed by and construed in accordance with dutch law and any dispute arising out of these general terms and conditions and our services shall exclusively be submitted to the competent courts in amsterdam , the netherlands ."
H67: Output: {"label": "[8]"} | I67: Output: {"label": "[5, 6]"} | J67: Output: {"label": "[5, 6]"}
B68: **Characteristics**:
B69: - **Substitution of Passive Action for Explicit Consent**: The clause deems the mere act of accessing, browsing, or downloading a service as a legally binding agreement, bypassing the need for a clear and affirmative expression of the consumer's intent to be bound. | H69: Input: "price changes for paid subscriptions will take effect at the start of the next subscription period following the date of the price change ." | I69: Input: "if you and a disputed party do not resolve any dispute by informal negotiation or in small claims court , any other effort to resolve the dispute will be conducted exclusively by binding arbitration governed by the united states federal arbitration act ( `` faa '' ) ." | J69: Input: "if you and a disputed party do not resolve any dispute by informal negotiation or in small claims court , any other effort to resolve the dispute will be conducted exclusively by binding arbitration governed by the united states federal arbitration act ( `` faa '' ) ."
B70: - **Unilateral and Automatic Acceptance of Amendments**: The clause dictates that any future modifications to the terms are automatically accepted by the consumer through their continued use of the service, often without requiring the provider to proactively notify the user of the specific changes. | H70: Output: {"label": "[8]"} | I70: Output: {"label": "[7]"} | J70: Output: {"label": "[7]"}
B71: - **Presumptive Understanding of Complex Terms**: The clause asserts that the consumer has read and understood all terms, privacy policies, and external guidelines simply by using the platform, regardless of the complexity or length of those documents.
B72: - **Binding to Undisclosed or Third-Party Terms**: The clause may force the consumer to agree to the terms and privacy policies of third-party providers integrated into the service without providing a distinct opportunity to review or accept those separate agreements. | H72: Input: "no arbitration or proceeding will be combined with another without the prior written consent of all parties to all affected arbitrations or proceedings ." | I72: Input: "generally , we do not moderate any interactive service we provide although we may remove content in contravention of these terms of use as set out in section 6 ." | J72: Input: "generally , we do not moderate any interactive service we provide although we may remove content in contravention of these terms of use as set out in section 6 ."
B73: - **Incorporation of High-Stakes Legal Waivers via Usage**: The clause binds the consumer to significant legal conditions, such as mandatory arbitration or data transfer consents, through routine usage rather than through a dedicated and prominent acceptance process. | H73: Output: {"label": "[8]"} | I73: Output: {"label": "[3]"} | J73: Output: {"label": "[3]"}
B74: - **Bypassing Consumer Withdrawal Rights**: The clause may state that the provision of services or digital items commences immediately upon use or purchase, which can unfairly restrict the consumer's ability to exercise a "cooling-off" period or a right to withdraw from the contract.
H75: ------------------------------------------------------------------------------------------ | I75: Input: "unless we make a change for legal or administrative reasons , we will provide reasonable advance notice before the updated terms become effective ." | J75: Input: "unless we make a change for legal or administrative reasons , we will provide reasonable advance notice before the updated terms become effective ."
B76: ### **5-Choice of Law:** | I76: Output: {"label": "[8]"} | J76: Output: {"label": "[8]"}
B77: **Definition**: In the context of a consumer service contract, a **Choice of Law** clause is a provision where the service provider specifies which countryfs or state's laws will be used to interpret the agreement and resolve any legal disputes. Because these contracts are usually "contracts of adhesion" (non-negotiable terms drafted by the provider), the choice of law is typically dictated by the company rather than being a mutual agreement. It determines which jurisdiction's consumer protection statutes apply, affecting the consumer's ability to seek remedies or assert their legal rights. | H77: ## OUTPUT INSTRUCTIONS
H78: {=- Return ONLY valid JSON.} -> #NAME? | I78: Input: "if you do not agree to any modifications , you should terminate your use of the service ." | J78: Input: "if you do not agree to any modifications , you should terminate your use of the service ."
B79: **Characteristics**: | H79: - No conversational filler or markdown formatting outside the JSON. | I79: Output: {"label": "[8]"} | J79: Output: {"label": "[8]"}
B80: - **Explicit Exclusion of Conflict of Law Principles**: Almost all unfair clauses include phrases like "without regard to its conflict of law principles" or "excluding its choice of law rules." This is unfair because conflict of law rules are the very legal mechanisms that would normally allow a consumer's local, more protective laws to take precedence over the company's chosen law. | H80: - Field "label": Respond ONLY with the exact number(s) in brackets, (e.g., [8] for fair, or [1, 6] if multiple unfair categories apply).
B81: - **Imposition of a Foreign Jurisdiction on Global Users**: These clauses often mandate that a single jurisdiction's law (e.g., California, Texas, or Finland) applies to all users worldwide. This is unfair as it forces consumers to adhere to a legal system that is foreign to them and may offer significantly fewer protections than the laws of their home country. | H81: - Field "legal_rationale": A single, concise sentence explaining the legal reasoning for the classification (e.g., citing the specific imbalance for 0-7, or the presence of balanced protections for 8). | I81: Input: "if you do not agree to the modified terms for a service , you should discontinue your use of that service ." | J81: Input: "if you do not agree to the modified terms for a service , you should discontinue your use of that service ."
B82: - **Waiver of Mandatory International Protections**: Some clauses specifically exclude international treaties, such as the United Nations Convention on Contracts for the International Sale of Goods, which are designed to provide a baseline of fairness in cross-border transactions. | H82: - Example: `{"label": "[2]", "legal_rationale": "The clause allows for price increases without providing a valid reason or the right to terminate."}` | I82: Output: {"label": "[8]"} | J82: Output: {"label": "[8]"}
B83: - **Creation of Legal Complexity and Confusion**: Unfair clauses often mix different legal standards (e.g., applying the Federal Arbitration Act for one part of the contract and the laws of a specific state for another). This creates a "legal maze" that makes it nearly impossible for an average consumer to understand which rights they have and how to enforce them.
B84: - **Deprivation of Local Mandatory Consumer Rights**: By designating a specific law as "exclusive," these clauses attempt to bypass mandatory local consumer protection statutes (such as cooling-off periods or specific warranty rights) that are legally required in the consumer's place of residence. | I84: Input: "if you do n't agree to the new terms , you must stop using the services , close your microsoft account and/or skype account and , if you are a parent or guardian , help your minor child close his or her microsoft account or skype account ." | J84: Input: "if you do n't agree to the new terms , you must stop using the services , close your microsoft account and/or skype account and , if you are a parent or guardian , help your minor child close his or her microsoft account or skype account ."
B85: - **Lack of Proximity and Accessibility**: Forcing a consumer to resolve a dispute based on the laws of a distant jurisdiction (like a European user being governed by the laws of Delaware or Israel) creates a massive barrier to justice, as the consumer would likely need to hire specialized foreign counsel to interpret their rights. | I85: Output: {"label": "[8]"} | J85: Output: {"label": "[8]"}
B87: ### **6-Jurisdiction:** | I87: Input: "if you do not wish to accept these changes , you are entitled to terminate your subscription , with effect from the date on which the changes are due to take effect ." | J87: Input: "if you do not wish to accept these changes , you are entitled to terminate your subscription , with effect from the date on which the changes are due to take effect ."
B88: **Definition**: In the context of a consumer service contract, **Jurisdiction** refers to the legal authority of a specific court or judicial system to hear and decide a legal dispute between the service provider and the consumer. It establishes the "legal home" for any potential litigation, determining which geographical location (venue) and which court system have the power to issue binding judgments. | I88: Output: {"label": "[8]"} | J88: Output: {"label": "[8]"}
B90: **Characteristics**: | I90: Input: "you understand and agree that youtube will treat your use of the service as acceptance of the terms from that point onwards ." | J90: Input: "you understand and agree that youtube will treat your use of the service as acceptance of the terms from that point onwards ."
B91: - **Mandatory litigation in a distant or foreign forum**: The clause forces consumers to resolve disputes in a specific location that is often thousands of miles away or in a different country (e.g., forcing a global user to litigate exclusively in "Santa Clara County, California" or "England and Wales"), creating a physical and financial barrier to justice. | I91: Output: {"label": "[8]"} | J91: Output: {"label": "[8]"}
B92: - **Imposition of "Exclusive" jurisdiction**: The use of restrictive language such as "exclusively," "must be brought," or "only in" prevents the consumer from seeking redress in their own local or national courts, even if the service was provided in their home region.
B93: - **Forced waiver of procedural objections**: The clause requires consumers to "waive any and all objections" to the venue or the "inconvenience of the forum," effectively stripping them of the legal right to argue that a court is too far away or inappropriate for the case. | I93: Input: "either you or we may start arbitration proceedings ." | J93: Input: "either you or we may start arbitration proceedings ."
B94: - **Irrevocable and pre-emptive consent**: Consumers are required to "irrevocably agree" or "consent" to a specific jurisdiction at the time of signing the contract, long before a dispute exists, leaving them no room to negotiate a more reasonable location later. | I94: Output: {"label": "[8]"} | J94: Output: {"label": "[8]"}
B95: - **Asymmetrical rights (Lack of Mutuality)**: The clause may restrict the consumer to a single specific court while explicitly allowing the company the freedom to seek legal remedies (such as injunctions) in "any jurisdiction" it chooses.
B96: - **Complex conditional barriers**: The jurisdiction clause often acts as a secondary trap, stating that if a primary (and often equally unfair) arbitration agreement is found unenforceable, the consumer is still forced into the companyfs preferred distant court. | I96: Input: "if you do so , neither we nor you can require the other party to participate in an arbitration proceeding ." | J96: Input: "if you do so , neither we nor you can require the other party to participate in an arbitration proceeding ."
B97: - **Submission to foreign legal standards**: By forcing jurisdiction in a specific region, the clause often implicitly subjects the consumer to foreign laws (e.g., "the laws of England and Wales shall govern"), which may offer fewer protections than the consumer's local consumer rights legislation. | I97: Output: {"label": "[8]"} | J97: Output: {"label": "[8]"}
B99: ### **7-Arbitration:** | I99: Input: "for the avoidance of doubt , the choice of texas governing law shall not supersede any mandatory consumer protection legislation in such jurisdictions ." | J99: Input: "for the avoidance of doubt , the choice of texas governing law shall not supersede any mandatory consumer protection legislation in such jurisdictions ."
B100: **Definition**: In the context of a consumer service contract (such as a Terms of Service or EULA), **Arbitration** is a private dispute resolution mechanism where a neutral third party, called an arbitrator, is appointed to hear a case and make a final, binding decision. Unlike a public court proceeding, arbitration takes place outside the judicial system. By agreeing to an arbitration clause, a consumer typically gives up their right to sue the company in a court of law and forfeits the right to have their case decided by a judge or jury. | I100: Output: {"label": "[8]"} | J100: Output: {"label": "[8]"}
B102: **Characteristics**: | I102: Input: "price changes for paid subscriptions will take effect at the start of the next subscription period following the date of the price change ." | J102: Input: "price changes for paid subscriptions will take effect at the start of the next subscription period following the date of the price change ."
B103: - **The clause mandates a class action waiver**, which prevents consumers from joining together to challenge widespread corporate misconduct and forces them to pursue small claims individually at a high personal cost. | I103: Output: {"label": "[8]"} | J103: Output: {"label": "[8]"}
B104: - **The clause establishes arbitration as the "exclusive means" of resolution**, effectively stripping the consumer of their constitutional right to a trial by jury or access to a public judge.
B105: - **The clause includes an "inconvenient forum" provision**, requiring the consumer to travel to a distant or international location (such as a different state or even a different country like Finland) to resolve their dispute. | I105: Input: "no arbitration or proceeding will be combined with another without the prior written consent of all parties to all affected arbitrations or proceedings ." | J105: Input: "no arbitration or proceeding will be combined with another without the prior written consent of all parties to all affected arbitrations or proceedings ."
B106: - **The clause creates a "unilateral carve-out" for the company**, where the service provider retains the right to go to court for issues like intellectual property protection while forcing all consumer-initiated complaints into private arbitration. | I106: Output: {"label": "[8]"} | J106: Output: {"label": "[8]"}
B107: - **The clause emphasizes that the decision is "final and binding,"** which severely limits or completely eliminates the consumer's ability to appeal a potentially incorrect or biased decision.
...

Sheet ZS13-Full-Gemini-3.1-Pro-27.05.
A1: Category | B1: Precision | C1: Recall | D1: F1 (Macro) | E1: F1 (Micro) | F1: Support | G1: TP | H1: FP | I1: FN | J1: TN | K1: Accuracy | L1: invalid_prediction_count | M1: invalid_prediction_rate
A2: All | B2: 0.79015 | C2: 0.80136 | D2: 0.63136 | E2: 0.79571 | F2: 1607 | K2: 0.78967 | L2: 1 | M2: 0.00062
A3: 0 | B3: 0.21935 | C3: 0.89474 | D3: 0.35233 | F3: 38 | G3: 34 | H3: 121 | I3: 4
A4: 1 | B4: 0.64583 | C4: 0.81579 | D4: 0.72093 | F4: 38 | G4: 31 | H4: 17 | I4: 7
A5: 2 | B5: 0.41892 | C5: 0.81579 | D5: 0.55357 | F5: 38 | G5: 31 | H5: 43 | I5: 7
A6: 3 | B6: 0.52 | C6: 1 | D6: 0.68421 | F6: 13 | G6: 13 | H6: 12 | I6: 0
A7: 4 | B7: 0.48936 | C7: 1 | D7: 0.65714 | F7: 23 | G7: 23 | H7: 24 | I7: 0
A8: 5 | B8: 0.8 | C8: 0.92308 | D8: 0.85714 | F8: 13 | G8: 12 | H8: 3 | I8: 1
A9: 6 | B9: 0.7619 | C9: 1 | D9: 0.86486 | F9: 16 | G9: 16 | H9: 5 | I9: 0
A10: 7 | B10: 0.06034 | C10: 1 | D10: 0.11382 | F10: 7 | G10: 7 | H10: 109 | I10: 0
A11: 8 | B11: 0.99038 | C11: 0.78885 | D11: 0.8782 | F11: 1435 | G11: 1132 | H11: 11 | I11: 303
A12: unfair_binary | B12: 0.34773 | C12: 0.93605 | D12: 0.50709 | G12: 161 | H12: 302 | I12: 11 | J12: 1133 | K12: 0.80523

Sheet ZS12-Full-4.1m-27.05.26
A1: Category | B1: Precision | C1: Recall | D1: F1 (Macro) | E1: F1 (Micro) | F1: Support | G1: TP | H1: FP | I1: FN | J1: TN | K1: Accuracy | L1: invalid_prediction_count | M1: invalid_prediction_rate
A2: All | B2: 0.68127 | C2: 0.70019 | D2: 0.44107 | E2: 0.6906 | F2: 1607 | K2: 0.68575 | L2: 0 | M2: 0
A3: 0 | B3: 0.19792 | C3: 1 | D3: 0.33043 | F3: 38 | G3: 38 | H3: 154 | I3: 0
A4: 1 | B4: 0.41333 | C4: 0.81579 | D4: 0.54867 | F4: 38 | G4: 31 | H4: 44 | I4: 7
A5: 2 | B5: 0.27358 | C5: 0.76316 | D5: 0.40278 | F5: 38 | G5: 29 | H5: 77 | I5: 9
A6: 3 | B6: 0.2549 | C6: 1 | D6: 0.40625 | F6: 13 | G6: 13 | H6: 38 | I6: 0
A7: 4 | B7: 0.21622 | C7: 0.69565 | D7: 0.3299 | F7: 23 | G7: 16 | H7: 58 | I7: 7
A8: 5 | B8: 0.28261 | C8: 1 | D8: 0.44068 | F8: 13 | G8: 13 | H8: 33 | I8: 0
A9: 6 | B9: 0.41026 | C9: 1 | D9: 0.58182 | F9: 16 | G9: 16 | H9: 23 | I9: 0
A10: 7 | B10: 0.06542 | C10: 1 | D10: 0.12281 | F10: 7 | G10: 7 | H10: 100 | I10: 0
A11: 8 | B11: 0.9959 | C11: 0.67735 | D11: 0.8063 | F11: 1435 | G11: 972 | H11: 4 | I11: 463
A12: unfair_binary | B12: 0.26624 | C12: 0.97674 | D12: 0.41843 | G12: 168 | H12: 463 | I12: 4 | J12: 972 | K12: 0.7094

Sheet ZS11-Full-Gemini-2.5-flash-27.0
A1: Category | B1: Precision | C1: Recall | D1: F1 (Macro) | E1: F1 (Micro) | F1: Support | G1: TP | H1: FP | I1: FN | J1: TN | K1: Accuracy | L1: invalid_prediction_count | M1: invalid_prediction_rate
A2: All | B2: 0.77171 | C2: 0.78408 | D2: 0.57518 | E2: 0.77785 | F2: 1607 | K2: 0.76851 | L2: 24 | M2: 0.01493
A3: 0 | B3: 0.18229 | C3: 0.92105 | D3: 0.30435 | F3: 38 | G3: 35 | H3: 157 | I3: 3
A4: 1 | B4: 0.64286 | C4: 0.71053 | D4: 0.675 | F4: 38 | G4: 27 | H4: 15 | I4: 11
A5: 2 | B5: 0.37363 | C5: 0.89474 | D5: 0.52713 | F5: 38 | G5: 34 | H5: 57 | I5: 4
A6: 3 | B6: 0.33333 | C6: 0.92308 | D6: 0.4898 | F6: 13 | G6: 12 | H6: 24 | I6: 1
A7: 4 | B7: 0.4878 | C7: 0.86957 | D7: 0.625 | F7: 23 | G7: 20 | H7: 21 | I7: 3
A8: 5 | B8: 0.66667 | C8: 0.92308 | D8: 0.77419 | F8: 13 | G8: 12 | H8: 6 | I8: 1
A9: 6 | B9: 0.625 | C9: 0.9375 | D9: 0.75 | F9: 16 | G9: 15 | H9: 9 | I9: 1
A10: 7 | B10: 0.08974 | C10: 1 | D10: 0.16471 | F10: 7 | G10: 7 | H10: 71 | I10: 0
A11: 8 | B11: 0.98578 | C11: 0.77282 | D11: 0.86641 | F11: 1435 | G11: 1109 | H11: 16 | I11: 326
A12: unfair_binary | B12: 0.33987 | C12: 0.90698 | D12: 0.49445 | G12: 156 | H12: 303 | I12: 16 | J12: 1132 | K12: 0.80149

Sheet ZS9-Full-Gemini3.1-pro-27.05.26
A1: Category | B1: Precision | C1: Recall | D1: F1 (Macro) | E1: F1 (Micro) | F1: Support | G1: TP | H1: FP | I1: FN | J1: TN | K1: Accuracy | L1: invalid_prediction_count | M1: invalid_prediction_rate
A2: All | B2: 0.90698 | C2: 0.91425 | D2: 0.71753 | E2: 0.9106 | F2: 1607 | K2: 0.90666 | L2: 0 | M2: 0
A3: 0 | B3: 0.44928 | C3: 0.81579 | D3: 0.57944 | F3: 38 | G3: 31 | H3: 38 | I3: 7
A4: 1 | B4: 0.61111 | C4: 0.86842 | D4: 0.71739 | F4: 38 | G4: 33 | H4: 21 | I4: 5
A5: 2 | B5: 0.5 | C5: 0.86842 | D5: 0.63462 | F5: 38 | G5: 33 | H5: 33 | I5: 5
A6: 3 | B6: 0.59091 | C6: 1 | D6: 0.74286 | F6: 13 | G6: 13 | H6: 9 | I6: 0
A7: 4 | B7: 0.56757 | C7: 0.91304 | D7: 0.7 | F7: 23 | G7: 21 | H7: 16 | I7: 2
A8: 5 | B8: 0.84615 | C8: 0.84615 | D8: 0.84615 | F8: 13 | G8: 11 | H8: 2 | I8: 2
A9: 6 | B9: 0.84211 | C9: 1 | D9: 0.91429 | F9: 16 | G9: 16 | H9: 3 | I9: 0
A10: 7 | B10: 0.25 | C10: 0.71429 | D10: 0.37037 | F10: 7 | G10: 5 | H10: 15 | I10: 2
A11: 8 | B11: 0.98876 | C11: 0.91916 | D11: 0.95269 | F11: 1435 | G11: 1319 | H11: 15 | I11: 116
A12: unfair_binary | B12: 0.57509 | C12: 0.91279 | D12: 0.70562 | G12: 157 | H12: 116 | I12: 15 | J12: 1319 | K12: 0.91848

Sheet ZS8-Full-Gemini2.5-flash-27.05.
A1: Category | B1: Precision | C1: Recall | D1: F1 (Macro) | E1: F1 (Micro) | F1: Support | G1: TP | H1: FP | I1: FN | J1: TN | K1: Accuracy | L1: invalid_prediction_count | M1: invalid_prediction_rate
A2: All | B2: 0.87805 | C2: 0.86613 | D2: 0.6782 | E2: 0.87205 | F2: 1607 | K2: 0.85812 | L2: 33 | M2: 0.02054
A3: 0 | B3: 0.425 | C3: 0.89474 | D3: 0.57627 | F3: 38 | G3: 34 | H3: 46 | I3: 4
A4: 1 | B4: 0.58333 | C4: 0.73684 | D4: 0.65116 | F4: 38 | G4: 28 | H4: 20 | I4: 10
A5: 2 | B5: 0.45833 | C5: 0.86842 | D5: 0.6 | F5: 38 | G5: 33 | H5: 39 | I5: 5
A6: 3 | B6: 0.43333 | C6: 1 | D6: 0.60465 | F6: 13 | G6: 13 | H6: 17 | I6: 0
A7: 4 | B7: 0.42857 | C7: 0.91304 | D7: 0.58333 | F7: 23 | G7: 21 | H7: 28 | I7: 2
A8: 5 | B8: 1 | C8: 0.92308 | D8: 0.96 | F8: 13 | G8: 12 | H8: 0 | I8: 1
A9: 6 | B9: 0.83333 | C9: 0.9375 | D9: 0.88235 | F9: 16 | G9: 15 | H9: 3 | I9: 1
A10: 7 | B10: 0.2 | C10: 0.85714 | D10: 0.32432 | F10: 7 | G10: 6 | H10: 24 | I10: 1
A11: 8 | B11: 0.98571 | C11: 0.86551 | D11: 0.92171 | F11: 1435 | G11: 1242 | H11: 18 | I11: 193
A12: unfair_binary | B12: 0.49045 | C12: 0.89535 | D12: 0.63374 | G12: 154 | H12: 160 | I12: 18 | J12: 1275 | K12: 0.88923

Sheet ZS7-Full-5.4n-15.04.26
A1: Category | B1: Precision | C1: Recall | D1: F1 (Macro) | E1: F1 (Micro) | F1: Support | G1: TP | H1: FP | I1: FN | J1: TN | K1: Accuracy | L1: invalid_prediction_count | M1: invalid_prediction_rate
A2: All | B2: 0.72297 | C2: 0.7261 | D2: 0.49403 | E2: 0.72453 | F2: 1607 | K2: 0.71686 | L2: 0 | M2: 0
A3: 0 | B3: 0.21765 | C3: 0.97368 | D3: 0.35577 | F3: 38 | G3: 37 | H3: 133 | I3: 1
A4: 1 | B4: 0.55102 | C4: 0.71053 | D4: 0.62069 | F4: 38 | G4: 27 | H4: 22 | I4: 11
A5: 2 | B5: 0.37975 | C5: 0.78947 | D5: 0.51282 | F5: 38 | G5: 30 | H5: 49 | I5: 8
A6: 3 | B6: 0.18841 | C6: 1 | D6: 0.31707 | F6: 13 | G6: 13 | H6: 56 | I6: 0
A7: 4 | B7: 0.17949 | C7: 0.91304 | D7: 0.3 | F7: 23 | G7: 21 | H7: 96 | I7: 2
A8: 5 | B8: 0.375 | C8: 0.92308 | D8: 0.53333 | F8: 13 | G8: 12 | H8: 20 | I8: 1
A9: 6 | B9: 0.66667 | C9: 1 | D9: 0.8 | F9: 16 | G9: 16 | H9: 8 | I9: 0
A10: 7 | B10: 0.09859 | C10: 1 | D10: 0.17949 | F10: 7 | G10: 7 | H10: 64 | I10: 0
A11: 8 | B11: 0.99705 | C11: 0.70662 | D11: 0.82708 | F11: 1435 | G11: 1014 | H11: 3 | I11: 421
A12: unfair_binary | B12: 0.28644 | C12: 0.98256 | D12: 0.44357 | G12: 169 | H12: 421 | I12: 3 | J12: 1014 | K12: 0.73615

Sheet ZS6-Full-5.4n-15.04.26
A1: Category | B1: Precision | C1: Recall | D1: F1 (Macro) | E1: F1 (Micro) | F1: Support | G1: TP | H1: FP | I1: FN | J1: TN | K1: Accuracy | L1: invalid_prediction_count | M1: invalid_prediction_rate
A2: All | B2: 0.69896 | C2: 0.70759 | D2: 0.46996 | E2: 0.70325 | F2: 1607 | K2: 0.69695 | L2: 2 | M2: 0.00124
A3: 0 | B3: 0.21512 | C3: 0.97368 | D3: 0.35238 | F3: 38 | G3: 37 | H3: 135 | I3: 1
A4: 1 | B4: 0.52727 | C4: 0.76316 | D4: 0.62366 | F4: 38 | G4: 29 | H4: 26 | I4: 9
A5: 2 | B5: 0.35227 | C5: 0.81579 | D5: 0.49206 | F5: 38 | G5: 31 | H5: 57 | I5: 7
A6: 3 | B6: 0.15116 | C6: 1 | D6: 0.26263 | F6: 13 | G6: 13 | H6: 73 | I6: 0
A7: 4 | B7: 0.14286 | C7: 0.52174 | D7: 0.2243 | F7: 23 | G7: 12 | H7: 72 | I7: 11
A8: 5 | B8: 0.5 | C8: 1 | D8: 0.66667 | F8: 13 | G8: 13 | H8: 13 | I8: 0
A9: 6 | B9: 0.5 | C9: 1 | D9: 0.66667 | F9: 16 | G9: 16 | H9: 16 | I9: 0
A10: 7 | B10: 0.06796 | C10: 1 | D10: 0.12727 | F10: 7 | G10: 7 | H10: 96 | I10: 0
A11: 8 | B11: 0.99397 | C11: 0.6892 | D11: 0.81399 | F11: 1435 | G11: 989 | H11: 6 | I11: 446
A12: unfair_binary | B12: 0.27213 | C12: 0.96512 | D12: 0.42455 | G12: 166 | H12: 444 | I12: 6 | J12: 991 | K12: 0.71998

Sheet ZS5-Full-5.4n-15.04.26
A1: Category | B1: Precision | C1: Recall | D1: F1 (Macro) | E1: F1 (Micro) | F1: Support | G1: TP | H1: FP | I1: FN | J1: TN | K1: Accuracy | L1: invalid_prediction_count | M1: invalid_prediction_rate
A2: All | B2: 0.6986 | C2: 0.70635 | D2: 0.48443 | E2: 0.70245 | F2: 1607 | K2: 0.69633 | L2: 0 | M2: 0
A3: 0 | B3: 0.19792 | C3: 1 | D3: 0.33043 | F3: 38 | G3: 38 | H3: 154 | I3: 0
A4: 1 | B4: 0.53061 | C4: 0.68421 | D4: 0.5977 | F4: 38 | G4: 26 | H4: 23 | I4: 12
A5: 2 | B5: 0.32292 | C5: 0.81579 | D5: 0.46269 | F5: 38 | G5: 31 | H5: 65 | I5: 7
A6: 3 | B6: 0.15663 | C6: 1 | D6: 0.27083 | F6: 13 | G6: 13 | H6: 70 | I6: 0
A7: 4 | B7: 0.17857 | C7: 0.65217 | D7: 0.28037 | F7: 23 | G7: 15 | H7: 69 | I7: 8
A8: 5 | B8: 0.56522 | C8: 1 | D8: 0.72222 | F8: 13 | G8: 13 | H8: 10 | I8: 0
A9: 6 | B9: 0.59259 | C9: 1 | D9: 0.74419 | F9: 16 | G9: 16 | H9: 11 | I9: 0
A10: 7 | B10: 0.07447 | C10: 1 | D10: 0.13861 | F10: 7 | G10: 7 | H10: 87 | I10: 0
A11: 8 | B11: 0.99495 | C11: 0.68711 | D11: 0.81286 | F11: 1435 | G11: 986 | H11: 5 | I11: 449
A12: unfair_binary | B12: 0.2711 | C12: 0.97093 | D12: 0.42386 | G12: 167 | H12: 449 | I12: 5 | J12: 986 | K12: 0.71749

Sheet ZS4-Full-5.4n-14.04.26
A1: Category | B1: Precision | C1: Recall | D1: F1 (Macro) | E1: F1 (Micro) | F1: Support | G1: TP | H1: FP | I1: FN | J1: TN | K1: Accuracy | L1: invalid_prediction_count | M1: invalid_prediction_rate
A2: All | B2: 0.50232 | C2: 0.53486 | D2: 0.36101 | E2: 0.51808 | F2: 1607 | K2: 0.51711 | L2: 1 | M2: 0.00062
A3: 0 | B3: 0.14859 | C3: 0.97368 | D3: 0.25784 | F3: 38 | G3: 37 | H3: 212 | I3: 1
A4: 1 | B4: 0.34831 | C4: 0.81579 | D4: 0.48819 | F4: 38 | G4: 31 | H4: 58 | I4: 7
A5: 2 | B5: 0.27869 | C5: 0.89474 | D5: 0.425 | F5: 38 | G5: 34 | H5: 88 | I5: 4
A6: 3 | B6: 0.14607 | C6: 1 | D6: 0.2549 | F6: 13 | G6: 13 | H6: 76 | I6: 0
A7: 4 | B7: 0.06746 | C7: 0.73913 | D7: 0.12364 | F7: 23 | G7: 17 | H7: 235 | I7: 6
A8: 5 | B8: 0.30952 | C8: 1 | D8: 0.47273 | F8: 13 | G8: 13 | H8: 29 | I8: 0
A9: 6 | B9: 0.30769 | C9: 1 | D9: 0.47059 | F9: 16 | G9: 16 | H9: 36 | I9: 0
A10: 7 | B10: 0.05344 | C10: 1 | D10: 0.10145 | F10: 7 | G10: 7 | H10: 124 | I10: 0
A11: 8 | B11: 0.99857 | C11: 0.48711 | D11: 0.6548 | F11: 1435 | G11: 699 | H11: 1 | I11: 736
A12: unfair_binary | B12: 0.18874 | C12: 0.99419 | D12: 0.31725 | G12: 171 | H12: 735 | I12: 1 | J12: 700 | K12: 0.542

Sheet ZS3-Full-4.1m-15.04.26
A1: Category | B1: Precision | C1: Recall | D1: F1 (Macro) | E1: F1 (Micro) | F1: Support | G1: TP | H1: FP | I1: FN | J1: TN | K1: Accuracy | L1: invalid_prediction_count | M1: invalid_prediction_rate
A2: All | B2: 0.78186 | C2: 0.78717 | D2: 0.53627 | E2: 0.78451 | F2: 1607 | K2: 0.77909 | L2: 0 | M2: 0
A3: 0 | B3: 0.30357 | C3: 0.89474 | D3: 0.45333 | F3: 38 | G3: 34 | H3: 78 | I3: 4
A4: 1 | B4: 0.30556 | C4: 0.86842 | D4: 0.45205 | F4: 38 | G4: 33 | H4: 75 | I4: 5
A5: 2 | B5: 0.37879 | C5: 0.65789 | D5: 0.48077 | F5: 38 | G5: 25 | H5: 41 | I5: 13
A6: 3 | B6: 0.31707 | C6: 1 | D6: 0.48148 | F6: 13 | G6: 13 | H6: 28 | I6: 0
A7: 4 | B7: 0.21519 | C7: 0.73913 | D7: 0.33333 | F7: 23 | G7: 17 | H7: 62 | I7: 6
A8: 5 | B8: 0.39394 | C8: 1 | D8: 0.56522 | F8: 13 | G8: 13 | H8: 20 | I8: 0
A9: 6 | B9: 0.88889 | C9: 1 | D9: 0.94118 | F9: 16 | G9: 16 | H9: 2 | I9: 0
A10: 7 | B10: 0.14 | C10: 1 | D10: 0.24561 | F10: 7 | G10: 7 | H10: 43 | I10: 0
A11: 8 | B11: 0.99378 | C11: 0.77909 | D11: 0.87344 | F11: 1435 | G11: 1118 | H11: 7 | I11: 317
A12: unfair_binary | B12: 0.34232 | C12: 0.9593 | D12: 0.50459 | G12: 165 | H12: 317 | I12: 7 | J12: 1118 | K12: 0.79838
A15: this test is the same as ZS3 but with 4.1m instead of 5.4n

Sheet ZS3-Full-5.4n-14.04.26
A1: Category | B1: Precision | C1: Recall | D1: F1 (Macro) | E1: F1 (Micro) | F1: Support | G1: TP | H1: FP | I1: FN | J1: TN | K1: Accuracy | L1: invalid_prediction_count | M1: invalid_prediction_rate
A2: All | B2: 0.76951 | C2: 0.77236 | D2: 0.53727 | E2: 0.77094 | F2: 1607 | K2: 0.7654 | L2: 0 | M2: 0
A3: 0 | B3: 0.34043 | C3: 0.84211 | D3: 0.48485 | F3: 38 | G3: 32 | H3: 62 | I3: 6
A4: 1 | B4: 0.40426 | C4: 1 | D4: 0.57576 | F4: 38 | G4: 38 | H4: 56 | I4: 0
A5: 2 | B5: 0.45614 | C5: 0.68421 | D5: 0.54737 | F5: 38 | G5: 26 | H5: 31 | I5: 12
A6: 3 | B6: 0.1625 | C6: 1 | D6: 0.27957 | F6: 13 | G6: 13 | H6: 67 | I6: 0
A7: 4 | B7: 0.23457 | C7: 0.82609 | D7: 0.36538 | F7: 23 | G7: 19 | H7: 62 | I7: 4
A8: 5 | B8: 0.59091 | C8: 1 | D8: 0.74286 | F8: 13 | G8: 13 | H8: 9 | I8: 0
A9: 6 | B9: 0.69565 | C9: 1 | D9: 0.82051 | F9: 16 | G9: 16 | H9: 7 | I9: 0
A10: 7 | B10: 0.08642 | C10: 1 | D10: 0.15909 | F10: 7 | G10: 7 | H10: 74 | I10: 0
A11: 8 | B11: 0.99361 | C11: 0.75819 | D11: 0.86008 | F11: 1435 | G11: 1088 | H11: 7 | I11: 347
A12: unfair_binary | B12: 0.32227 | C12: 0.9593 | D12: 0.48246 | G12: 165 | H12: 347 | I12: 7 | J12: 1088 | K12: 0.77971

Sheet ZS2-Full-4.1m-07.04.26
A1: Category | B1: Precision | C1: Recall | D1: F1 (Macro) | E1: F1 (Micro) | F1: Support | G1: TP | H1: FP | I1: FN | J1: TN | K1: Accuracy | L1: invalid_prediction_count | M1: invalid_prediction_rate
A2: All | B2: 0.63702 | C2: 0.65392 | D2: 0.43696 | E2: 0.64536 | F2: 1607 | K2: 0.63783 | L2: 0 | M2: 0
A3: 0 | B3: 0.17117 | C3: 1 | D3: 0.29231 | F3: 38 | G3: 38 | H3: 184 | I3: 0
A4: 1 | B4: 0.35714 | C4: 0.78947 | D4: 0.4918 | F4: 38 | G4: 30 | H4: 54 | I4: 8
A5: 2 | B5: 0.29293 | C5: 0.76316 | D5: 0.42336 | F5: 38 | G5: 29 | H5: 70 | I5: 9
A6: 3 | B6: 0.125 | C6: 1 | D6: 0.22222 | F6: 13 | G6: 13 | H6: 91 | I6: 0
A7: 4 | B7: 0.27273 | C7: 0.91304 | D7: 0.42 | F7: 23 | G7: 21 | H7: 56 | I7: 2
A8: 5 | B8: 0.26 | C8: 1 | D8: 0.4127 | F8: 13 | G8: 13 | H8: 37 | I8: 0
A9: 6 | B9: 0.64 | C9: 1 | D9: 0.78049 | F9: 16 | G9: 16 | H9: 9 | I9: 0
A10: 7 | B10: 0.06604 | C10: 1 | D10: 0.12389 | F10: 7 | G10: 7 | H10: 99 | I10: 0
A11: 8 | B11: 0.99554 | C11: 0.6223 | D11: 0.76587 | F11: 1435 | G11: 893 | H11: 4 | I11: 542
A12: unfair_binary | B12: 0.23662 | C12: 0.97674 | D12: 0.38095 | G12: 168 | H12: 542 | I12: 4 | J12: 893 | K12: 0.66024

Sheet ZS1-Full-4.1m-21.03.26
A1: Category | B1: Precision | C1: Recall | D1: F1 (Macro) | E1: F1 (Micro) | F1: Support | G1: TP | H1: FP | I1: FN | J1: TN | K1: Accuracy | L1: invalid_prediction_count | M1: invalid_prediction_rate
A2: All | B2: 0.6477 | C2: 0.66009 | D2: 0.45805 | E2: 0.65383 | F2: 1607 | K2: 0.64717 | L2: 0 | M2: 0
A3: 0 | B3: 0.15261 | C3: 1 | D3: 0.26481 | F3: 38 | G3: 38 | H3: 211 | I3: 0
A4: 1 | B4: 0.54348 | C4: 0.65789 | D4: 0.59524 | F4: 38 | G4: 25 | H4: 21 | I4: 13
A5: 2 | B5: 0.33696 | C5: 0.81579 | D5: 0.47692 | F5: 38 | G5: 31 | H5: 61 | I5: 7
A6: 3 | B6: 0.16883 | C6: 1 | D6: 0.28889 | F6: 13 | G6: 13 | H6: 64 | I6: 0
A7: 4 | B7: 0.3 | C7: 0.91304 | D7: 0.45161 | F7: 23 | G7: 21 | H7: 49 | I7: 2
A8: 5 | B8: 0.30233 | C8: 1 | D8: 0.46429 | F8: 13 | G8: 13 | H8: 30 | I8: 0
A9: 6 | B9: 0.55172 | C9: 1 | D9: 0.71111 | F9: 16 | G9: 16 | H9: 13 | I9: 0
A10: 7 | B10: 0.05036 | C10: 1 | D10: 0.09589 | F10: 7 | G10: 7 | H10: 132 | I10: 0
A11: 8 | B11: 0.9989 | C11: 0.63136 | D11: 0.7737 | F11: 1435 | G11: 906 | H11: 1 | I11: 529
A12: unfair_binary | B12: 0.24429 | C12: 0.99419 | D12: 0.3922 | G12: 171 | H12: 529 | I12: 1 | J12: 906 | K12: 0.67019

Sheet FS8-Full-Gemini-2.5-flash-27.05
A1: Category | B1: Precision | C1: Recall | D1: F1 (Macro) | E1: F1 (Micro) | F1: Support | G1: TP | H1: FP | I1: FN | J1: TN | K1: Accuracy | L1: invalid_prediction_count | M1: invalid_prediction_rate
A2: All | B2: 0.8875 | C2: 0.876 | D2: 0.7003 | E2: 0.88171 | F2: 1607 | K2: 0.86745 | L2: 33 | M2: 0.02054
A3: 0 | B3: 0.38462 | C3: 0.92105 | D3: 0.54264 | F3: 38 | G3: 35 | H3: 56 | I3: 3
A4: 1 | B4: 0.64583 | C4: 0.81579 | D4: 0.72093 | F4: 38 | G4: 31 | H4: 17 | I4: 7
A5: 2 | B5: 0.47143 | C5: 0.86842 | D5: 0.61111 | F5: 38 | G5: 33 | H5: 37 | I5: 5
A6: 3 | B6: 0.46429 | C6: 1 | D6: 0.63415 | F6: 13 | G6: 13 | H6: 15 | I6: 0
A7: 4 | B7: 0.46667 | C7: 0.91304 | D7: 0.61765 | F7: 23 | G7: 21 | H7: 24 | I7: 2
A8: 5 | B8: 0.92308 | C8: 0.92308 | D8: 0.92308 | F8: 13 | G8: 12 | H8: 1 | I8: 1
A9: 6 | B9: 1 | C9: 0.9375 | D9: 0.96774 | F9: 16 | G9: 15 | H9: 0 | I9: 1
A10: 7 | B10: 0.2381 | C10: 0.71429 | D10: 0.35714 | F10: 7 | G10: 5 | H10: 16 | I10: 2
A11: 8 | B11: 0.98897 | C11: 0.87456 | D11: 0.92825 | F11: 1435 | G11: 1255 | H11: 14 | I11: 180
A12: unfair_binary | B12: 0.51803 | C12: 0.9186 | D12: 0.66247 | G12: 158 | H12: 147 | I12: 14 | J12: 1288 | K12: 0.89981

Sheet FS7-Full-4.1m-19.05.26
A1: Category | B1: Precision | C1: Recall | D1: F1 (Macro) | E1: F1 (Micro) | F1: Support | G1: TP | H1: FP | I1: FN | J1: TN | K1: Accuracy | L1: invalid_prediction_count | M1: invalid_prediction_rate
A2: All | B2: 0.21033 | C2: 0.10549 | D2: 0.3566 | E2: 0.14051 | F2: 1607 | K2: 0.08836 | L2: 825 | M2: 0.51338
A3: 0 | B3: 0.21384 | C3: 0.89474 | D3: 0.34518 | F3: 38 | G3: 34 | H3: 125 | I3: 4
A4: 1 | B4: 0.22561 | C4: 0.97368 | D4: 0.36634 | F4: 38 | G4: 37 | H4: 127 | I4: 1
A5: 2 | B5: 0.29412 | C5: 0.78947 | D5: 0.42857 | F5: 38 | G5: 30 | H5: 72 | I5: 8
A6: 3 | B6: 0.15294 | C6: 1 | D6: 0.26531 | F6: 13 | G6: 13 | H6: 72 | I6: 0
A7: 4 | B7: 0.23864 | C7: 0.91304 | D7: 0.37838 | F7: 23 | G7: 21 | H7: 67 | I7: 2
A8: 5 | B8: 0.30952 | C8: 1 | D8: 0.47273 | F8: 13 | G8: 13 | H8: 29 | I8: 0
A9: 6 | B9: 0.7619 | C9: 1 | D9: 0.86486 | F9: 16 | G9: 16 | H9: 5 | I9: 0
A10: 7 | B10: 0.04605 | C10: 1 | D10: 0.08805 | F10: 7 | G10: 7 | H10: 145 | I10: 0
A11: 8 | B11: 0 | C11: 0 | D11: 0 | F11: 1435 | G11: 0 | H11: 0 | I11: 1435
A12: unfair_binary | B12: 0.21867 | C12: 0.99419 | D12: 0.35849 | G12: 171 | H12: 611 | I12: 1 | J12: 824 | K12: 0.61917

Sheet FS6-Full-Gemini3.1-pro-25.04.26
A1: Category | B1: Precision | C1: Recall | D1: F1 (Macro) | E1: F1 (Micro) | F1: Support | G1: TP | H1: FP | I1: FN | J1: TN | K1: Accuracy | L1: invalid_prediction_count | M1: invalid_prediction_rate
A2: All | B2: 0.91983 | C2: 0.92721 | D2: 0.73928 | E2: 0.9235 | F2: 1607 | K2: 0.9191 | L2: 0 | M2: 0
A3: 0 | B3: 0.47541 | C3: 0.76316 | D3: 0.58586 | F3: 38 | G3: 29 | H3: 32 | I3: 9
A4: 1 | B4: 0.65455 | C4: 0.94737 | D4: 0.77419 | F4: 38 | G4: 36 | H4: 19 | I4: 2
A5: 2 | B5: 0.54386 | C5: 0.81579 | D5: 0.65263 | F5: 38 | G5: 31 | H5: 26 | I5: 7
A6: 3 | B6: 0.54545 | C6: 0.92308 | D6: 0.68571 | F6: 13 | G6: 12 | H6: 10 | I6: 1
A7: 4 | B7: 0.61765 | C7: 0.91304 | D7: 0.73684 | F7: 23 | G7: 21 | H7: 13 | I7: 2
A8: 5 | B8: 0.85714 | C8: 0.92308 | D8: 0.88889 | F8: 13 | G8: 12 | H8: 2 | I8: 1
A9: 6 | B9: 0.84211 | C9: 1 | D9: 0.91429 | F9: 16 | G9: 16 | H9: 3 | I9: 0
A10: 7 | B10: 0.33333 | C10: 0.71429 | D10: 0.45455 | F10: 7 | G10: 5 | H10: 10 | I10: 2
A11: 8 | B11: 0.98821 | C11: 0.93449 | D11: 0.9606 | F11: 1435 | G11: 1341 | H11: 16 | I11: 94
A12: unfair_binary | B12: 0.624 | C12: 0.90698 | D12: 0.73934 | G12: 156 | H12: 94 | I12: 16 | J12: 1341 | K12: 0.93155

Sheet FS5-Full-gemini-3-flash-preview
A1: Category | B1: Precision | C1: Recall | D1: F1 (Macro) | E1: F1 (Micro) | F1: Support | G1: TP | H1: FP | I1: FN | J1: TN | K1: Accuracy | L1: invalid_prediction_count | M1: invalid_prediction_rate
A2: All | B2: 0.87915 | C2: 0.89759 | D2: 0.68814 | E2: 0.88828 | F2: 1607 | K2: 0.88177 | L2: 0 | M2: 0
A3: 0 | B3: 0.36364 | C3: 0.84211 | D3: 0.50794 | F3: 38 | G3: 32 | H3: 56 | I3: 6
A4: 1 | B4: 0.51515 | C4: 0.89474 | D4: 0.65385 | F4: 38 | G4: 34 | H4: 32 | I4: 4
A5: 2 | B5: 0.41096 | C5: 0.78947 | D5: 0.54054 | F5: 38 | G5: 30 | H5: 43 | I5: 8
A6: 3 | B6: 0.43333 | C6: 1 | D6: 0.60465 | F6: 13 | G6: 13 | H6: 17 | I6: 0
A7: 4 | B7: 0.55556 | C7: 0.86957 | D7: 0.67797 | F7: 23 | G7: 20 | H7: 16 | I7: 3
A8: 5 | B8: 0.92308 | C8: 0.92308 | D8: 0.92308 | F8: 13 | G8: 12 | H8: 1 | I8: 1
A9: 6 | B9: 0.83333 | C9: 0.9375 | D9: 0.88235 | F9: 16 | G9: 15 | H9: 3 | I9: 1
A10: 7 | B10: 0.31579 | C10: 0.85714 | D10: 0.46154 | F10: 7 | G10: 6 | H10: 13 | I10: 1
A11: 8 | B11: 0.98552 | C11: 0.90105 | D11: 0.94139 | F11: 1435 | G11: 1293 | H11: 19 | I11: 142
A12: unfair_binary | B12: 0.51864 | C12: 0.88953 | D12: 0.65525 | G12: 153 | H12: 142 | I12: 19 | J12: 1293 | K12: 0.89981

Sheet FS4-Full-5.4n-10.04.26
A1: Category | B1: Precision | C1: Recall | D1: F1 (Macro) | E1: F1 (Micro) | F1: Support | G1: TP | H1: FP | I1: FN | J1: TN | K1: Accuracy | L1: invalid_prediction_count | M1: invalid_prediction_rate
A2: All | B2: 0.82147 | C2: 0.82603 | D2: 0.58579 | E2: 0.82375 | F2: 1607 | K2: 0.82078 | L2: 0 | M2: 0
A3: 0 | B3: 0.29907 | C3: 0.84211 | D3: 0.44138 | F3: 38 | G3: 32 | H3: 75 | I3: 6
A4: 1 | B4: 0.3913 | C4: 0.94737 | D4: 0.55385 | F4: 38 | G4: 36 | H4: 56 | I4: 2
A5: 2 | B5: 0.49091 | C5: 0.71053 | D5: 0.58065 | F5: 38 | G5: 27 | H5: 28 | I5: 11
A6: 3 | B6: 0.2766 | C6: 1 | D6: 0.43333 | F6: 13 | G6: 13 | H6: 34 | I6: 0
A7: 4 | B7: 0.33962 | C7: 0.78261 | D7: 0.47368 | F7: 23 | G7: 18 | H7: 35 | I7: 5
A8: 5 | B8: 0.56522 | C8: 1 | D8: 0.72222 | F8: 13 | G8: 13 | H8: 10 | I8: 0
A9: 6 | B9: 0.84211 | C9: 1 | D9: 0.91429 | F9: 16 | G9: 16 | H9: 3 | I9: 0
A10: 7 | B10: 0.14583 | C10: 1 | D10: 0.25455 | F10: 7 | G10: 7 | H10: 41 | I10: 0
A11: 8 | B11: 0.99241 | C11: 0.82021 | D11: 0.89813 | F11: 1435 | G11: 1177 | H11: 9 | I11: 258
A12: unfair_binary | B12: 0.38717 | C12: 0.94767 | D12: 0.54975 | G12: 163 | H12: 258 | I12: 9 | J12: 1177 | K12: 0.83385

Sheet FS3-Full-4.1m-08.04.26
A1: Category | B1: Precision | C1: Recall | D1: F1 (Macro) | E1: F1 (Micro) | F1: Support | G1: TP | H1: FP | I1: FN | J1: TN | K1: Accuracy | L1: invalid_prediction_count | M1: invalid_prediction_rate
A2: All | B2: 0.87584 | C2: 0.88341 | D2: 0.65973 | E2: 0.87961 | F2: 1607 | K2: 0.87368 | L2: 0 | M2: 0
A3: 0 | B3: 0.38636 | C3: 0.89474 | D3: 0.53968 | F3: 38 | G3: 34 | H3: 54 | I3: 4
A4: 1 | B4: 0.4375 | C4: 0.92105 | D4: 0.59322 | F4: 38 | G4: 35 | H4: 45 | I4: 3
A5: 2 | B5: 0.52174 | C5: 0.63158 | D5: 0.57143 | F5: 38 | G5: 24 | H5: 22 | I5: 14
A6: 3 | B6: 0.41935 | C6: 1 | D6: 0.59091 | F6: 13 | G6: 13 | H6: 18 | I6: 0
A7: 4 | B7: 0.52941 | C7: 0.78261 | D7: 0.63158 | F7: 23 | G7: 18 | H7: 16 | I7: 5
A8: 5 | B8: 0.65 | C8: 1 | D8: 0.78788 | F8: 13 | G8: 13 | H8: 7 | I8: 0
A9: 6 | B9: 0.9375 | C9: 0.9375 | D9: 0.9375 | F9: 16 | G9: 15 | H9: 1 | I9: 1
A10: 7 | B10: 0.21212 | C10: 1 | D10: 0.35 | F10: 7 | G10: 7 | H10: 26 | I10: 0
A11: 8 | B11: 0.98912 | C11: 0.88711 | D11: 0.93534 | F11: 1435 | G11: 1273 | H11: 14 | I11: 162
A12: unfair_binary | B12: 0.49375 | C12: 0.9186 | D12: 0.64228 | G12: 158 | H12: 162 | I12: 14 | J12: 1273 | K12: 0.89048

Sheet FS2-Full-4.1m-08.04.26
A1: Category | B1: Precision | C1: Recall | D1: F1 (Macro) | E1: F1 (Micro) | F1: Support | G1: TP | H1: FP | I1: FN | J1: TN | K1: Accuracy | L1: invalid_prediction_count | M1: invalid_prediction_rate
A2: All | B2: 0.8364 | C2: 0.84207 | D2: 0.61534 | E2: 0.83923 | F2: 1607 | K2: 0.83385 | L2: 0 | M2: 0
A3: 0 | B3: 0.27206 | C3: 0.97368 | D3: 0.42529 | F3: 38 | G3: 37 | H3: 99 | I3: 1
A4: 1 | B4: 0.59259 | C4: 0.84211 | D4: 0.69565 | F4: 38 | G4: 32 | H4: 22 | I4: 6
A5: 2 | B5: 0.52083 | C5: 0.65789 | D5: 0.5814 | F5: 38 | G5: 25 | H5: 23 | I5: 13
A6: 3 | B6: 0.30952 | C6: 1 | D6: 0.47273 | F6: 13 | G6: 13 | H6: 29 | I6: 0
A7: 4 | B7: 0.54545 | C7: 0.78261 | D7: 0.64286 | F7: 23 | G7: 18 | H7: 15 | I7: 5
A8: 5 | B8: 0.54545 | C8: 0.92308 | D8: 0.68571 | F8: 13 | G8: 12 | H8: 10 | I8: 1
A9: 6 | B9: 0.84211 | C9: 1 | D9: 0.91429 | F9: 16 | G9: 16 | H9: 3 | I9: 0
A10: 7 | B10: 0.11864 | C10: 1 | D10: 0.21212 | F10: 7 | G10: 7 | H10: 52 | I10: 0
A11: 8 | B11: 0.98852 | C11: 0.83972 | D11: 0.90806 | F11: 1435 | G11: 1205 | H11: 14 | I11: 230
A12: unfair_binary | B12: 0.40722 | C12: 0.9186 | D12: 0.56429 | G12: 158 | H12: 230 | I12: 14 | J12: 1205 | K12: 0.84816

Sheet FS1-Full-4.1m-07.04.26
A1: Category | B1: Precision | C1: Recall | D1: F1 (Macro) | E1: F1 (Micro) | F1: Support | G1: TP | H1: FP | I1: FN | J1: TN | K1: Accuracy | L1: invalid_prediction_count | M1: invalid_prediction_rate
A2: All | B2: 0.80906 | C2: 0.81555 | D2: 0.59262 | E2: 0.81229 | F2: 1607 | K2: 0.80585 | L2: 0 | M2: 0
A3: 0 | B3: 0.27612 | C3: 0.97368 | D3: 0.43023 | F3: 38 | G3: 37 | H3: 97 | I3: 1
A4: 1 | B4: 0.61538 | C4: 0.84211 | D4: 0.71111 | F4: 38 | G4: 32 | H4: 20 | I4: 6
A5: 2 | B5: 0.53061 | C5: 0.68421 | D5: 0.5977 | F5: 38 | G5: 26 | H5: 23 | I5: 12
A6: 3 | B6: 0.28889 | C6: 1 | D6: 0.44828 | F6: 13 | G6: 13 | H6: 32 | I6: 0
A7: 4 | B7: 0.4 | C7: 0.86957 | D7: 0.54795 | F7: 23 | G7: 20 | H7: 30 | I7: 3
A8: 5 | B8: 0.48148 | C8: 1 | D8: 0.65 | F8: 13 | G8: 13 | H8: 14 | I8: 0
A9: 6 | B9: 0.84211 | C9: 1 | D9: 0.91429 | F9: 16 | G9: 16 | H9: 3 | I9: 0
A10: 7 | B10: 0.07778 | C10: 1 | D10: 0.14433 | F10: 7 | G10: 7 | H10: 83 | I10: 0
A11: 8 | B11: 0.99144 | C11: 0.80697 | D11: 0.88974 | F11: 1435 | G11: 1158 | H11: 10 | I11: 277
A12: unfair_binary | B12: 0.36902 | C12: 0.94186 | D12: 0.53028 | G12: 162 | H12: 277 | I12: 10 | J12: 1158 | K12: 0.82141

Sheet GPT4.1m-fine-tunned
A1: Category | B1: Precision | C1: Recall | D1: F1 (Macro) | E1: F1 (Micro) | F1: Support | G1: TP | H1: FP | I1: FN | J1: TN | K1: Accuracy | L1: invalid_prediction_count | M1: invalid_prediction_rate
A2: All | B2: 0.95931 | C2: 0.9599 | D2: 0.83037 | E2: 0.95961 | F2: 1607 | K2: 0.95644 | L2: 0 | M2: 0
A3: 0 | B3: 0.70455 | C3: 0.81579 | D3: 0.7561 | F3: 38 | G3: 31 | H3: 13 | I3: 7
A4: 1 | B4: 0.78378 | C4: 0.76316 | D4: 0.77333 | F4: 38 | G4: 29 | H4: 8 | I4: 9
A5: 2 | B5: 0.84375 | C5: 0.71053 | D5: 0.77143 | F5: 38 | G5: 27 | H5: 5 | I5: 11
A6: 3 | B6: 0.61905 | C6: 1 | D6: 0.76471 | F6: 13 | G6: 13 | H6: 8 | I6: 0
A7: 4 | B7: 0.81818 | C7: 0.78261 | D7: 0.8 | F7: 23 | G7: 18 | H7: 4 | I7: 5
A8: 5 | B8: 1 | C8: 0.92308 | D8: 0.96 | F8: 13 | G8: 12 | H8: 0 | I8: 1
A9: 6 | B9: 1 | C9: 1 | D9: 1 | F9: 16 | G9: 16 | H9: 0 | I9: 0
A10: 7 | B10: 0.54545 | C10: 0.85714 | D10: 0.66667 | F10: 7 | G10: 6 | H10: 5 | I10: 1
A11: 8 | B11: 0.98388 | C11: 0.9784 | D11: 0.98113 | F11: 1435 | G11: 1404 | H11: 23 | I11: 31
A12: unfair_binary | B12: 0.82778 | C12: 0.86628 | D12: 0.84659 | G12: 149 | H12: 31 | I12: 23 | J12: 1404 | K12: 0.9664

Sheet Gemini-2.5-flash-fine-tunned
A1: Category | B1: Precision | C1: Recall | D1: F1 (Macro) | E1: F1 (Micro) | F1: Support | G1: TP | H1: FP | I1: FN | J1: TN | K1: Accuracy | L1: invalid_prediction_count | M1: invalid_prediction_rate
A2: All | B2: 0.94479 | C2: 0.95003 | D2: 0.80666 | E2: 0.9474 | F2: 1607 | K2: 0.94213 | L2: 0 | M2: 0
A3: 0 | B3: 0.625 | C3: 0.78947 | D3: 0.69767 | F3: 38 | G3: 30 | H3: 18 | I3: 8
A4: 1 | B4: 0.62264 | C4: 0.86842 | D4: 0.72527 | F4: 38 | G4: 33 | H4: 20 | I4: 5
A5: 2 | B5: 0.64706 | C5: 0.86842 | D5: 0.74157 | F5: 38 | G5: 33 | H5: 18 | I5: 5
A6: 3 | B6: 0.66667 | C6: 0.92308 | D6: 0.77419 | F6: 13 | G6: 12 | H6: 6 | I6: 1
A7: 4 | B7: 0.76 | C7: 0.82609 | D7: 0.79167 | F7: 23 | G7: 19 | H7: 6 | I7: 4
A8: 5 | B8: 0.92308 | C8: 0.92308 | D8: 0.92308 | F8: 13 | G8: 12 | H8: 1 | I8: 1
A9: 6 | B9: 1 | C9: 1 | D9: 1 | F9: 16 | G9: 16 | H9: 0 | I9: 0
A10: 7 | B10: 0.5 | C10: 0.85714 | D10: 0.63158 | F10: 7 | G10: 6 | H10: 6 | I10: 1
A11: 8 | B11: 0.98924 | C11: 0.96098 | D11: 0.9749 | F11: 1435 | G11: 1379 | H11: 15 | I11: 56
A12: unfair_binary | B12: 0.73709 | C12: 0.91279 | D12: 0.81558 | G12: 157 | H12: 56 | I12: 15 | J12: 1379 | K12: 0.95582

Sheet Template
A1: Category | B1: Precision | C1: Recall | D1: F1 (Macro) | E1: F1 (Micro) | F1: Support | G1: TP | H1: FP | I1: FN | J1: TN | K1: Accuracy | L1: invalid_prediction_count | M1: invalid_prediction_rate
A2: All | B2: micro_precision for all categories | C2: micro_recall for all categories | D2: Macro_F1 | E2: Micro_F1 | F2: num_examples | K2: exact_match_accuracy for all Categories
A3: 0 | B3: 0.17117 | C3: 1 | D3: 0.29231 | F3: 38 | G3: 38 | H3: 184 | I3: 0
A4: 1 | B4: 0.35714 | C4: 0.78947 | D4: 0.4918 | F4: 38 | G4: 30 | H4: 54 | I4: 8
A5: 2 | B5: 0.29293 | C5: 0.76316 | D5: 0.42336 | F5: 38 | G5: 29 | H5: 70 | I5: 9
A6: 3 | B6: 0.125 | C6: 1 | D6: 0.22222 | F6: 13 | G6: 13 | H6: 91 | I6: 0
A7: 4 | B7: 0.27273 | C7: 0.91304 | D7: 0.42 | F7: 23 | G7: 21 | H7: 56 | I7: 2
A8: 5 | B8: 0.26 | C8: 1 | D8: 0.4127 | F8: 13 | G8: 13 | H8: 37 | I8: 0
A9: 6 | B9: 0.64 | C9: 1 | D9: 0.78049 | F9: 16 | G9: 16 | H9: 9 | I9: 0
A10: 7 | B10: 0.06604 | C10: 1 | D10: 0.12389 | F10: 7 | G10: 7 | H10: 99 | I10: 0
A11: 8 | B11: 0.99554 | C11: 0.6223 | D11: 0.76587 | F11: 1435 | G11: 893 | H11: 4 | I11: 542
A12: unfair_binary | B12: 0.23662 | C12: 0.97674 | D12: 0.38095 | G12: 168 | H12: 542 | I12: 4 | J12: 893 | K12: 0.66024
